Workbook

Sheet A股港股
B1: 频率 | C1: 代码 | D1: 单位 | E1: 当前数据 | F1: 数据日期 | G1: 变化 | H1: 上期数据 | I1: 上期日期 | J1: 趋势图
A2: 上证指数 | B2: 日度 | C2: 000001.SH | D2: 点 | E2: =IFERROR(LOOKUP(9.99E+307,指数走势!$F$7:$IM$7),"") -> 4043.6432 | F2: =IFERROR(LOOKUP(2,1/(指数走势!$F$7:$IM$7<>""),指数走势!$F$1:$IM$1),"") -> 46206 | G2: =IFERROR(E2-H2,"") -> 14.7394 | H2: =IFERROR(LOOKUP(9.99E+307,OFFSET(指数走势!$F$7,0,0,1,LOOKUP(2,1/(指数走势!$F$7:$IM$7<>""),COLUMN(指数走势!$F$7:$IM$7))-COLUMN(指数走势!$F$7))),"") -> 4028.9038 | I2: =IFERROR(LOOKUP(2,1/(指数走势!$F$7:$IM$7<>"")/(指数走势!$F$1:$IM$1<F2),指数走势!$F$1:$IM$1),"") -> 46205
A3: 深成指数 | B3: 日度 | C3: 399001.SZ | D3: 点 | E3: =IFERROR(LOOKUP(9.99E+307,指数走势!$F$5:$IM$5),"") -> 15597.512 | F3: =IFERROR(LOOKUP(2,1/(指数走势!$F$5:$IM$5<>""),指数走势!$F$1:$IM$1),"") -> 46206 | G3: =IFERROR(E3-H3,"") -> 98.7015 | H3: =IFERROR(LOOKUP(9.99E+307,OFFSET(指数走势!$F$5,0,0,1,LOOKUP(2,1/(指数走势!$F$5:$IM$5<>""),COLUMN(指数走势!$F$5:$IM$5))-COLUMN(指数走势!$F$5))),"") -> 15498.81 | I3: =IFERROR(LOOKUP(2,1/(指数走势!$F$5:$IM$5<>"")/(指数走势!$F$1:$IM$1<F3),指数走势!$F$1:$IM$1),"") -> 46205
A4: 沪深300 | B4: 日度 | C4: 000300.SH | D4: 点 | E4: =IFERROR(LOOKUP(9.99E+307,指数走势!$F$6:$IM$6),"") -> 4842.1737 | F4: =IFERROR(LOOKUP(2,1/(指数走势!$F$6:$IM$6<>""),指数走势!$F$1:$IM$1),"") -> 46206 | G4: =IFERROR(E4-H4,"") -> 29.878 | H4: =IFERROR(LOOKUP(9.99E+307,OFFSET(指数走势!$F$6,0,0,1,LOOKUP(2,1/(指数走势!$F$6:$IM$6<>""),COLUMN(指数走势!$F$6:$IM$6))-COLUMN(指数走势!$F$6))),"") -> 4812.2957 | I4: =IFERROR(LOOKUP(2,1/(指数走势!$F$6:$IM$6<>"")/(指数走势!$F$1:$IM$1<F4),指数走势!$F$1:$IM$1),"") -> 46205
A5: 创业板指 | B5: 日度 | C5: 399006.SZ | D5: 点 | E5: =IFERROR(LOOKUP(9.99E+307,指数走势!$F$4:$IM$4),"") -> 4019.9341 | F5: =IFERROR(LOOKUP(2,1/(指数走势!$F$4:$IM$4<>""),指数走势!$F$1:$IM$1),"") -> 46206 | G5: =IFERROR(E5-H5,"") -> 2.6606 | H5: =IFERROR(LOOKUP(9.99E+307,OFFSET(指数走势!$F$4,0,0,1,LOOKUP(2,1/(指数走势!$F$4:$IM$4<>""),COLUMN(指数走势!$F$4:$IM$4))-COLUMN(指数走势!$F$4))),"") -> 4017.2735 | I5: =IFERROR(LOOKUP(2,1/(指数走势!$F$4:$IM$4<>"")/(指数走势!$F$1:$IM$1<F5),指数走势!$F$1:$IM$1),"") -> 46205
A6: 北向资金成交额 | B6: 日度 | D6: 亿元 | E6: =IFERROR(IF(A股成交额换手率测试1!I8<>"",A股成交额换手率测试1!I8+A股成交额换手率测试1!L8,A股成交额换手率测试1!I9+A股成交额换手率测试1!L9),"") -> 3915.1525 | F6: =IF(A股成交额换手率测试1!I8<>"",A股成交额换手率测试1!H8,A股成交额换手率测试1!H9) -> 46206 | G6: =IFERROR(E6-H6,"") -> -325.028 | H6: =IFERROR(IF(A股成交额换手率测试1!I8<>"",A股成交额换手率测试1!I9+A股成交额换手率测试1!L9,A股成交额换手率测试1!I10+A股成交额换手率测试1!L10),"") -> 4240.1805 | I6: =IF(A股成交额换手率测试1!I8<>"",A股成交额换手率测试1!H9,A股成交额换手率测试1!H10) -> 46205
A7: A股日度成交额 | B7: 日度 | D7: 亿元 | E7: =IFERROR(A股成交额换手率测试1!B9,"") -> 32052.617 | F7: =A股成交额换手率测试1!A9 -> 2026-07-03 | G7: =IFERROR(E7-H7,"") -> -2686.6458 | H7: =IFERROR(A股成交额换手率测试1!B10,"") -> 34739.263 | I7: =A股成交额换手率测试1!A10 -> 2026-07-02
A8: 融资融券余额 | B8: 日度 | D8: 万亿元 | E8: =IFERROR(A股成交额换手率测试1!F9/1000000000000,"") -> 3.0033369 | F8: =A股成交额换手率测试1!E9 -> 46206 | G8: =IFERROR(E8-H8,"") -> -0.019559298 | H8: =IFERROR(A股成交额换手率测试1!F10/1000000000000,"") -> 3.0228962 | I8: =A股成交额换手率测试1!E10 -> 46205
A9: 市场换手率 | B9: 日度 | D9: % | E9: =IFERROR(A股成交额换手率测试1!C9,"") -> 3.8454036 | F9: =A股成交额换手率测试1!A9 -> 2026-07-03 | G9: =IFERROR(E9-H9,"") -> -0.17865275 | H9: =IFERROR(A股成交额换手率测试1!C10,"") -> 4.0240564 | I9: =A股成交额换手率测试1!A10 -> 2026-07-02
A10: 恒生指数 | B10: 日度 | C10: HSI.HI | D10: 点 | E10: =IFERROR(LOOKUP(9.99E+307,指数走势!$F$8:$IM$8),"") -> 23350.03 | F10: =IFERROR(LOOKUP(2,1/(指数走势!$F$8:$IM$8<>""),指数走势!$F$1:$IM$1),"") -> 46206 | G10: =IFERROR(E10-H10,"") -> 295 | H10: =IFERROR(LOOKUP(9.99E+307,OFFSET(指数走势!$F$8,0,0,1,LOOKUP(2,1/(指数走势!$F$8:$IM$8<>""),COLUMN(指数走势!$F$8:$IM$8))-COLUMN(指数走势!$F$8))),"") -> 23055.03 | I10: =IFERROR(LOOKUP(2,1/(指数走势!$F$8:$IM$8<>"")/(指数走势!$F$1:$IM$1<F10),指数走势!$F$1:$IM$1),"") -> 46205
A11: 恒生科技指数 | B11: 日度 | C11: HSTECH.HI | D11: 点 | E11: =IFERROR(LOOKUP(9.99E+307,指数走势!$F$3:$IM$3),"") -> 4499 | F11: =IFERROR(LOOKUP(2,1/(指数走势!$F$3:$IM$3<>""),指数走势!$F$1:$IM$1),"") -> 46206 | G11: =IFERROR(E11-H11,"") -> 44.72 | H11: =IFERROR(LOOKUP(9.99E+307,OFFSET(指数走势!$F$3,0,0,1,LOOKUP(2,1/(指数走势!$F$3:$IM$3<>""),COLUMN(指数走势!$F$3:$IM$3))-COLUMN(指数走势!$F$3))),"") -> 4454.28 | I11: =IFERROR(LOOKUP(2,1/(指数走势!$F$3:$IM$3<>"")/(指数走势!$F$1:$IM$1<F11),指数走势!$F$1:$IM$1),"") -> 46205
A12: 南向资金净流入 | B12: 日度 | D12: 亿元 | E12: =IFERROR(A股成交额换手率测试1!P8+A股成交额换手率测试1!S8,"") -> 39.264 | F12: =A股成交额换手率测试1!O8 -> 46206 | G12: =IFERROR(E12-H12,"") -> 56.3312 | H12: =IFERROR(A股成交额换手率测试1!P9+A股成交额换手率测试1!S9,"") -> -17.0672 | I12: =A股成交额换手率测试1!O9 -> 46205
A13: 港股换手率 | B13: 日度 | D13: % | E13: =IFERROR(LOOKUP(9.99E+307,指数走势!$F$17:$IM$17),"") -> 0.32 | F13: =IFERROR(LOOKUP(2,1/(指数走势!$F$17:$IM$17<>""),指数走势!$F$1:$IM$1),"") -> 46206 | G13: =IFERROR(E13-H13,"") -> -0.0707 | H13: =IFERROR(LOOKUP(9.99E+307,OFFSET(指数走势!$F$17,0,0,1,LOOKUP(2,1/(指数走势!$F$17:$IM$17<>""),COLUMN(指数走势!$F$17:$IM$17))-COLUMN(指数走势!$F$17))),"") -> 0.3907 | I13: =IFERROR(LOOKUP(2,1/(指数走势!$F$17:$IM$17<>"")/(指数走势!$F$1:$IM$1<F13),指数走势!$F$1:$IM$1),"") -> 46205
A14: 港股成交额 | B14: 日度 | C14: G8324453 | D14: 亿 | E14: =IFERROR(LOOKUP(9.99E+307,宏观数据!$F$112:$UN$112)/100,"") -> 3049.54 | F14: =IFERROR(LOOKUP(2,1/(宏观数据!$F$112:$UN$112<>""),宏观数据!$F$1:$UN$1),"") -> 46206 | G14: =IFERROR(E14-H14,"") -> -646.79 | H14: =IFERROR(LOOKUP(9.99E+307,OFFSET(宏观数据!$F$112,0,0,1,LOOKUP(2,1/(宏观数据!$F$112:$UN$112<>""),COLUMN(宏观数据!$F$112:$UN$112))-COLUMN(宏观数据!$F$112)))/100,"") -> 3696.33 | I14: =IFERROR(LOOKUP(2,1/(宏观数据!$F$112:$UN$112<>"")/(宏观数据!$F$1:$UN$1<F14),宏观数据!$F$1:$UN$1),"") -> 46205
A15: 上证所:股票账户新开户数:个人:当月值 | B15: 月度 | C15: F5536637 | E15: =IFERROR(LOOKUP(9.99E+307,宏观数据!$F$86:$UN$86),"") -> 285.2384 | F15: =IFERROR(LOOKUP(2,1/(宏观数据!$F$86:$UN$86<>""),宏观数据!$F$1:$UN$1),"") -> 46203 | G15: =IFERROR(E15-H15,"") -> 9.6554 | H15: =IFERROR(LOOKUP(9.99E+307,OFFSET(宏观数据!$F$86,0,0,1,LOOKUP(2,1/(宏观数据!$F$86:$UN$86<>""),COLUMN(宏观数据!$F$86:$UN$86))-COLUMN(宏观数据!$F$86))),"") -> 275.583 | I15: =IFERROR(LOOKUP(2,1/(宏观数据!$F$86:$UN$86<>"")/(宏观数据!$F$1:$UN$1<F15),宏观数据!$F$1:$UN$1),"") -> 46173
A16: 上证沪港通AH溢价指数 | B16: 日度 | C16: H50066.CSI | D16: 点 | E16: =IFERROR(LOOKUP(9.99E+307,指数走势!$F$9:$IM$9),"") -> 132.836 | F16: =IFERROR(LOOKUP(2,1/(指数走势!$F$9:$IM$9<>""),指数走势!$F$1:$IM$1),"") -> 46206 | G16: =IFERROR(E16-H16,"") -> -0.406 | H16: =IFERROR(LOOKUP(9.99E+307,OFFSET(指数走势!$F$9,0,0,1,LOOKUP(2,1/(指数走势!$F$9:$IM$9<>""),COLUMN(指数走势!$F$9:$IM$9))-COLUMN(指数走势!$F$9))),"") -> 133.242 | I16: =IFERROR(LOOKUP(2,1/(指数走势!$F$9:$IM$9<>"")/(指数走势!$F$1:$IM$1<F16),指数走势!$F$1:$IM$1),"") -> 46205
A17: ETF净流入 | B17: 日度 | C17: ETF市场申赎净流入 | D17: 亿元 | E17: =IFERROR(LOOKUP(2,1/(A股成交额换手率测试1!$AD$7:$AD$400<>""),A股成交额换手率测试1!$AD$7:$AD$400)/100000000,"") -> -81.442033 | F17: =IFERROR(LOOKUP(2,1/(A股成交额换手率测试1!$AD$7:$AD$400<>""),A股成交额换手率测试1!$AC$7:$AC$400),"") -> 46206 | G17: =IFERROR(E17-H17,"") -> -370.19565 | H17: =IFERROR(LOOKUP(2,1/(A股成交额换手率测试1!$AD$7:$AD$400<>"")/(ROW(A股成交额换手率测试1!$AD$7:$AD$400)<LOOKUP(2,1/(A股成交额换手率测试1!$AD$7:$AD$400<>""),ROW(A股成交额换手率测试1!$AD$7:$AD$400))),A股成交额换手率测试1!$AD$7:$AD$400)/100000000,"") -> 288.75362 | I17: =IFERROR(LOOKUP(2,1/(A股成交额换手率测试1!$AD$7:$AD$400<>"")/(ROW(A股成交额换手率测试1!$AD$7:$AD$400)<LOOKUP(2,1/(A股成交额换手率测试1!$AD$7:$AD$400<>""),ROW(A股成交额换手率测试1!$AD$7:$AD$400))),A股成交额换手率测试1!$AC$7:$AC$400),"") -> 46205
A18: 上证指数PE(TTM) | B18: 日度 | C18: 000001.SH | D18: 倍 | E18: =IFERROR(LOOKUP(2,1/(指数走势!$F$32:$ACK$32<=$F$2)/(指数走势!$F$33:$ACK$33<>""),指数走势!$F$33:$ACK$33),"") -> 16.941 | F18: =IFERROR(LOOKUP(2,1/(指数走势!$F$32:$ACK$32<=$F$2)/(指数走势!$F$33:$ACK$33<>""),指数走势!$F$32:$ACK$32),"") -> 46206 | G18: =IFERROR(E18-H18,"") -> 0.062200546 | H18: =IFERROR(LOOKUP(2,1/(指数走势!$F$32:$ACK$32<F18)/(指数走势!$F$33:$ACK$33<>""),指数走势!$F$33:$ACK$33),"") -> 16.878799 | I18: =IFERROR(LOOKUP(2,1/(指数走势!$F$32:$ACK$32<F18)/(指数走势!$F$33:$ACK$33<>""),指数走势!$F$32:$ACK$32),"") -> 46205
A19: 深证成指PE(TTM) | B19: 日度 | C19: 399001.SZ | D19: 倍 | E19: =IFERROR(LOOKUP(2,1/(指数走势!$F$32:$ACK$32<=$F$3)/(指数走势!$F$34:$ACK$34<>""),指数走势!$F$34:$ACK$34),"") -> 37.180401 | F19: =IFERROR(LOOKUP(2,1/(指数走势!$F$32:$ACK$32<=$F$3)/(指数走势!$F$34:$ACK$34<>""),指数走势!$F$32:$ACK$32),"") -> 46206 | G19: =IFERROR(E19-H19,"") -> 0.31999969 | H19: =IFERROR(LOOKUP(2,1/(指数走势!$F$32:$ACK$32<F19)/(指数走势!$F$34:$ACK$34<>""),指数走势!$F$34:$ACK$34),"") -> 36.860401 | I19: =IFERROR(LOOKUP(2,1/(指数走势!$F$32:$ACK$32<F19)/(指数走势!$F$34:$ACK$34<>""),指数走势!$F$32:$ACK$32),"") -> 46205
A20: 沪深300PE(TTM) | B20: 日度 | C20: 000300.SH | D20: 倍 | E20: =IFERROR(LOOKUP(2,1/(指数走势!$F$32:$ACK$32<=$F$4)/(指数走势!$F$35:$ACK$35<>""),指数走势!$F$35:$ACK$35),"") -> 14.3228 | F20: =IFERROR(LOOKUP(2,1/(指数走势!$F$32:$ACK$32<=$F$4)/(指数走势!$F$35:$ACK$35<>""),指数走势!$F$32:$ACK$32),"") -> 46206 | G20: =IFERROR(E20-H20,"") -> 0.085499763 | H20: =IFERROR(LOOKUP(2,1/(指数走势!$F$32:$ACK$32<F20)/(指数走势!$F$35:$ACK$35<>""),指数走势!$F$35:$ACK$35),"") -> 14.2373 | I20: =IFERROR(LOOKUP(2,1/(指数走势!$F$32:$ACK$32<F20)/(指数走势!$F$35:$ACK$35<>""),指数走势!$F$32:$ACK$32),"") -> 46205
A21: 创业板指PE(TTM) | B21: 日度 | C21: 399006.SZ | D21: 倍 | E21: =IFERROR(LOOKUP(2,1/(指数走势!$F$32:$ACK$32<=$F$5)/(指数走势!$F$36:$ACK$36<>""),指数走势!$F$36:$ACK$36),"") -> 51.1866 | F21: =IFERROR(LOOKUP(2,1/(指数走势!$F$32:$ACK$32<=$F$5)/(指数走势!$F$36:$ACK$36<>""),指数走势!$F$32:$ACK$32),"") -> 46206 | G21: =IFERROR(E21-H21,"") -> 0.11370087 | H21: =IFERROR(LOOKUP(2,1/(指数走势!$F$32:$ACK$32<F21)/(指数走势!$F$36:$ACK$36<>""),指数走势!$F$36:$ACK$36),"") -> 51.072899 | I21: =IFERROR(LOOKUP(2,1/(指数走势!$F$32:$ACK$32<F21)/(指数走势!$F$36:$ACK$36<>""),指数走势!$F$32:$ACK$32),"") -> 46205
A22: 恒生指数PE(TTM) | B22: 日度 | C22: HSI.HI | D22: 倍 | E22: =IFERROR(LOOKUP(2,1/(指数走势!$F$32:$ACK$32<=$F$10)/(指数走势!$F$37:$ACK$37<>""),指数走势!$F$37:$ACK$37),"") -> 11.2894 | F22: =IFERROR(LOOKUP(2,1/(指数走势!$F$32:$ACK$32<=$F$10)/(指数走势!$F$37:$ACK$37<>""),指数走势!$F$32:$ACK$32),"") -> 46206 | G22: =IFERROR(E22-H22,"") -> 0.12720013 | H22: =IFERROR(LOOKUP(2,1/(指数走势!$F$32:$ACK$32<F22)/(指数走势!$F$37:$ACK$37<>""),指数走势!$F$37:$ACK$37),"") -> 11.1622 | I22: =IFERROR(LOOKUP(2,1/(指数走势!$F$32:$ACK$32<F22)/(指数走势!$F$37:$ACK$37<>""),指数走势!$F$32:$ACK$32),"") -> 46205
A23: 恒生科技PE(TTM) | B23: 日度 | C23: HSTECH.HI | D23: 倍 | E23: =IFERROR(LOOKUP(2,1/(指数走势!$F$32:$ACK$32<=$F$11)/(指数走势!$F$38:$ACK$38<>""),指数走势!$F$38:$ACK$38),"") -> 21.8529 | F23: =IFERROR(LOOKUP(2,1/(指数走势!$F$32:$ACK$32<=$F$11)/(指数走势!$F$38:$ACK$38<>""),指数走势!$F$32:$ACK$32),"") -> 46206 | G23: =IFERROR(E23-H23,"") -> 0.17479897 | H23: =IFERROR(LOOKUP(2,1/(指数走势!$F$32:$ACK$32<F23)/(指数走势!$F$38:$ACK$38<>""),指数走势!$F$38:$ACK$38),"") -> 21.678101 | I23: =IFERROR(LOOKUP(2,1/(指数走势!$F$32:$ACK$32<F23)/(指数走势!$F$38:$ACK$38<>""),指数走势!$F$32:$ACK$32),"") -> 46205

Sheet 中债
B1: 频率 | C1: 代码 | D1: 单位 | E1: 当前数据 | F1: 数据日期 | G1: 变化 | H1: 上期数据 | I1: 上期日期 | J1: 趋势图
A2: 1年国债收益率 | B2: 日度 | C2: M0325686 | D2: % | E2: =IFERROR(LOOKUP(9.99E+307,宏观数据!$F$43:$UN$43),"") -> 1.1365 | F2: =IFERROR(LOOKUP(2,1/(宏观数据!$F$43:$UN$43<>""),宏观数据!$F$1:$UN$1),"") -> 46206 | G2: =IFERROR(E2-H2,"") -> 0.0029 | H2: =IFERROR(LOOKUP(9.99E+307,OFFSET(宏观数据!$F$43,0,0,1,LOOKUP(2,1/(宏观数据!$F$43:$UN$43<>""),COLUMN(宏观数据!$F$43:$UN$43))-COLUMN(宏观数据!$F$43))),"") -> 1.1336 | I2: =IFERROR(LOOKUP(2,1/(宏观数据!$F$43:$UN$43<>"")/(宏观数据!$F$1:$UN$1<F2),宏观数据!$F$1:$UN$1),"") -> 46205
A3: 10年国债收益率 | B3: 日度 | C3: S0059749 | D3: % | E3: =IFERROR(LOOKUP(9.99E+307,宏观数据!$F$52:$UN$52),"") -> 1.7463 | F3: =IFERROR(LOOKUP(2,1/(宏观数据!$F$52:$UN$52<>""),宏观数据!$F$1:$UN$1),"") -> 46206 | G3: =IFERROR(E3-H3,"") -> 0.0053 | H3: =IFERROR(LOOKUP(9.99E+307,OFFSET(宏观数据!$F$52,0,0,1,LOOKUP(2,1/(宏观数据!$F$52:$UN$52<>""),COLUMN(宏观数据!$F$52:$UN$52))-COLUMN(宏观数据!$F$52))),"") -> 1.741 | I3: =IFERROR(LOOKUP(2,1/(宏观数据!$F$52:$UN$52<>"")/(宏观数据!$F$1:$UN$1<F3),宏观数据!$F$1:$UN$1),"") -> 46205
A4: 期限利差：（国债）10Y-1Y | B4: 日度 | D4: BP | E4: =IFERROR((E3-E2)*100,"") -> 60.98 | F4: =F2 -> 46206 | G4: =IFERROR(E4-H4,"") -> 0.24 | H4: =IFERROR((H3-H2)*100,"") -> 60.74 | I4: =I2 -> 46205
A5: 信用利差：10Y（企业债-国开债） | B5: 日度 | D5: BP | E5: =IFERROR((LOOKUP(9.99E+307,宏观数据!$F$55:$UN$55)-LOOKUP(9.99E+307,宏观数据!$F$54:$UN$54))*100,"") -> 30.06 | F5: =IFERROR(LOOKUP(2,1/(宏观数据!$F$55:$UN$55<>""),宏观数据!$F$1:$UN$1),"") -> 46206 | G5: =IFERROR(E5-H5,"") -> -0.42 | H5: =IFERROR((LOOKUP(9.99E+307,OFFSET(宏观数据!$F$55,0,0,1,LOOKUP(2,1/(宏观数据!$F$55:$UN$55<>""),COLUMN(宏观数据!$F$55:$UN$55))-COLUMN(宏观数据!$F$55)))-LOOKUP(9.99E+307,OFFSET(宏观数据!$F$54,0,0,1,LOOKUP(2,1/(宏观数据!$F$54:$UN$54<>""),COLUMN(宏观数据!$F$54:$UN$54))-COLUMN(宏观数据!$F$54))))*100,"") -> 30.48 | I5: =I3 -> 46205
A6: 中国:社会融资规模存量:企业债券:同比 | B6: 月度 | C6: M5525769 | D6: % | E6: =IFERROR(LOOKUP(9.99E+307,宏观数据!$F$37:$UN$37),"") -> 8.4 | F6: =IFERROR(LOOKUP(2,1/(宏观数据!$F$37:$UN$37<>""),宏观数据!$F$1:$UN$1),"") -> 46173 | G6: =IFERROR(E6-H6,"") -> 0.1 | H6: =IFERROR(LOOKUP(9.99E+307,OFFSET(宏观数据!$F$37,0,0,1,LOOKUP(2,1/(宏观数据!$F$37:$UN$37<>""),COLUMN(宏观数据!$F$37:$UN$37))-COLUMN(宏观数据!$F$37))),"") -> 8.3 | I6: =IFERROR(LOOKUP(2,1/(宏观数据!$F$37:$UN$37<>"")/(宏观数据!$F$1:$UN$1<F6),宏观数据!$F$1:$UN$1),"") -> 46142
A7: 中债国债到期收益率:2年 | B7: 日度 | C7: S0059745 | D7: % | E7: =IFERROR(LOOKUP(9.99E+307,宏观数据!$F$44:$UN$44),"") -> 1.2473 | F7: =IFERROR(LOOKUP(2,1/(宏观数据!$F$44:$UN$44<>""),宏观数据!$F$1:$UN$1),"") -> 46206 | G7: =IFERROR(E7-H7,"") -> 0.0002 | H7: =IFERROR(LOOKUP(9.99E+307,OFFSET(宏观数据!$F$44,0,0,1,LOOKUP(2,1/(宏观数据!$F$44:$UN$44<>""),COLUMN(宏观数据!$F$44:$UN$44))-COLUMN(宏观数据!$F$44))),"") -> 1.2471 | I7: =IFERROR(LOOKUP(2,1/(宏观数据!$F$44:$UN$44<>"")/(宏观数据!$F$1:$UN$1<F7),宏观数据!$F$1:$UN$1),"") -> 46205
A8: 中债国债到期收益率:3年 | B8: 日度 | C8: S0059746 | D8: % | E8: =IFERROR(LOOKUP(9.99E+307,宏观数据!$F$45:$UN$45),"") -> 1.2901 | F8: =IFERROR(LOOKUP(2,1/(宏观数据!$F$45:$UN$45<>""),宏观数据!$F$1:$UN$1),"") -> 46206 | G8: =IFERROR(E8-H8,"") -> -0.0026 | H8: =IFERROR(LOOKUP(9.99E+307,OFFSET(宏观数据!$F$45,0,0,1,LOOKUP(2,1/(宏观数据!$F$45:$UN$45<>""),COLUMN(宏观数据!$F$45:$UN$45))-COLUMN(宏观数据!$F$45))),"") -> 1.2927 | I8: =IFERROR(LOOKUP(2,1/(宏观数据!$F$45:$UN$45<>"")/(宏观数据!$F$1:$UN$1<F8),宏观数据!$F$1:$UN$1),"") -> 46205
A9: 中债国开债到期收益率:3年 | B9: 日度 | C9: M1004265 | D9: % | E9: =IFERROR(LOOKUP(9.99E+307,宏观数据!$F$46:$UN$46),"") -> 1.4701 | F9: =IFERROR(LOOKUP(2,1/(宏观数据!$F$46:$UN$46<>""),宏观数据!$F$1:$UN$1),"") -> 46206 | G9: =IFERROR(E9-H9,"") -> -0.003 | H9: =IFERROR(LOOKUP(9.99E+307,OFFSET(宏观数据!$F$46,0,0,1,LOOKUP(2,1/(宏观数据!$F$46:$UN$46<>""),COLUMN(宏观数据!$F$46:$UN$46))-COLUMN(宏观数据!$F$46))),"") -> 1.4731 | I9: =IFERROR(LOOKUP(2,1/(宏观数据!$F$46:$UN$46<>"")/(宏观数据!$F$1:$UN$1<F9),宏观数据!$F$1:$UN$1),"") -> 46205
A10: 中债国开债到期收益率:1年 | B10: 日度 | C10: M1004263 | D10: % | E10: =IFERROR(LOOKUP(9.99E+307,宏观数据!$F$47:$UN$47),"") -> 1.3566 | F10: =IFERROR(LOOKUP(2,1/(宏观数据!$F$47:$UN$47<>""),宏观数据!$F$1:$UN$1),"") -> 46206 | G10: =IFERROR(E10-H10,"") -> -0.005 | H10: =IFERROR(LOOKUP(9.99E+307,OFFSET(宏观数据!$F$47,0,0,1,LOOKUP(2,1/(宏观数据!$F$47:$UN$47<>""),COLUMN(宏观数据!$F$47:$UN$47))-COLUMN(宏观数据!$F$47))),"") -> 1.3616 | I10: =IFERROR(LOOKUP(2,1/(宏观数据!$F$47:$UN$47<>"")/(宏观数据!$F$1:$UN$1<F10),宏观数据!$F$1:$UN$1),"") -> 46205
A11: 中债企业债到期收益率(AAA):1年 | B11: 日度 | C11: S0059771 | D11: % | E11: =IFERROR(LOOKUP(9.99E+307,宏观数据!$F$48:$UN$48),"") -> 1.505 | F11: =IFERROR(LOOKUP(2,1/(宏观数据!$F$48:$UN$48<>""),宏观数据!$F$1:$UN$1),"") -> 46206 | G11: =IFERROR(E11-H11,"") -> 0 | H11: =IFERROR(LOOKUP(9.99E+307,OFFSET(宏观数据!$F$48,0,0,1,LOOKUP(2,1/(宏观数据!$F$48:$UN$48<>""),COLUMN(宏观数据!$F$48:$UN$48))-COLUMN(宏观数据!$F$48))),"") -> 1.505 | I11: =IFERROR(LOOKUP(2,1/(宏观数据!$F$48:$UN$48<>"")/(宏观数据!$F$1:$UN$1<F11),宏观数据!$F$1:$UN$1),"") -> 46205
A12: 中债城投债到期收益率(AAA):1年 | B12: 日度 | C12: M0048432 | D12: % | E12: =IFERROR(LOOKUP(9.99E+307,宏观数据!$F$49:$UN$49),"") -> 1.5297 | F12: =IFERROR(LOOKUP(2,1/(宏观数据!$F$49:$UN$49<>""),宏观数据!$F$1:$UN$1),"") -> 46206 | G12: =IFERROR(E12-H12,"") -> -0.0019 | H12: =IFERROR(LOOKUP(9.99E+307,OFFSET(宏观数据!$F$49,0,0,1,LOOKUP(2,1/(宏观数据!$F$49:$UN$49<>""),COLUMN(宏观数据!$F$49:$UN$49))-COLUMN(宏观数据!$F$49))),"") -> 1.5316 | I12: =IFERROR(LOOKUP(2,1/(宏观数据!$F$49:$UN$49<>"")/(宏观数据!$F$1:$UN$1<F12),宏观数据!$F$1:$UN$1),"") -> 46205
A13: 中债城投债到期收益率(AAA):3年 | B13: 日度 | C13: M0048434 | D13: % | E13: =IFERROR(LOOKUP(9.99E+307,宏观数据!$F$50:$UN$50),"") -> 1.6675 | F13: =IFERROR(LOOKUP(2,1/(宏观数据!$F$50:$UN$50<>""),宏观数据!$F$1:$UN$1),"") -> 46206 | G13: =IFERROR(E13-H13,"") -> 0.0043 | H13: =IFERROR(LOOKUP(9.99E+307,OFFSET(宏观数据!$F$50,0,0,1,LOOKUP(2,1/(宏观数据!$F$50:$UN$50<>""),COLUMN(宏观数据!$F$50:$UN$50))-COLUMN(宏观数据!$F$50))),"") -> 1.6632 | I13: =IFERROR(LOOKUP(2,1/(宏观数据!$F$50:$UN$50<>"")/(宏观数据!$F$1:$UN$1<F13),宏观数据!$F$1:$UN$1),"") -> 46205
A14: 中债企业债到期收益率(AAA):3年 | B14: 日度 | C14: S0059773 | D14: % | E14: =IFERROR(LOOKUP(9.99E+307,宏观数据!$F$51:$UN$51),"") -> 1.643 | F14: =IFERROR(LOOKUP(2,1/(宏观数据!$F$51:$UN$51<>""),宏观数据!$F$1:$UN$1),"") -> 46206 | G14: =IFERROR(E14-H14,"") -> 0 | H14: =IFERROR(LOOKUP(9.99E+307,OFFSET(宏观数据!$F$51,0,0,1,LOOKUP(2,1/(宏观数据!$F$51:$UN$51<>""),COLUMN(宏观数据!$F$51:$UN$51))-COLUMN(宏观数据!$F$51))),"") -> 1.643 | I14: =IFERROR(LOOKUP(2,1/(宏观数据!$F$51:$UN$51<>"")/(宏观数据!$F$1:$UN$1<F14),宏观数据!$F$1:$UN$1),"") -> 46205
A15: 中债国债到期收益率:30年 | B15: 日度 | C15: S0059752 | D15: % | E15: =IFERROR(LOOKUP(9.99E+307,宏观数据!$F$53:$UN$53),"") -> 2.2685 | F15: =IFERROR(LOOKUP(2,1/(宏观数据!$F$53:$UN$53<>""),宏观数据!$F$1:$UN$1),"") -> 46206 | G15: =IFERROR(E15-H15,"") -> 0.0105 | H15: =IFERROR(LOOKUP(9.99E+307,OFFSET(宏观数据!$F$53,0,0,1,LOOKUP(2,1/(宏观数据!$F$53:$UN$53<>""),COLUMN(宏观数据!$F$53:$UN$53))-COLUMN(宏观数据!$F$53))),"") -> 2.258 | I15: =IFERROR(LOOKUP(2,1/(宏观数据!$F$53:$UN$53<>"")/(宏观数据!$F$1:$UN$1<F15),宏观数据!$F$1:$UN$1),"") -> 46205
A16: 中债国开债到期收益率:10年 | B16: 日度 | C16: M1004271 | D16: % | E16: =IFERROR(LOOKUP(9.99E+307,宏观数据!$F$54:$UN$54),"") -> 1.797 | F16: =IFERROR(LOOKUP(2,1/(宏观数据!$F$54:$UN$54<>""),宏观数据!$F$1:$UN$1),"") -> 46206 | G16: =IFERROR(E16-H16,"") -> 0.004 | H16: =IFERROR(LOOKUP(9.99E+307,OFFSET(宏观数据!$F$54,0,0,1,LOOKUP(2,1/(宏观数据!$F$54:$UN$54<>""),COLUMN(宏观数据!$F$54:$UN$54))-COLUMN(宏观数据!$F$54))),"") -> 1.793 | I16: =IFERROR(LOOKUP(2,1/(宏观数据!$F$54:$UN$54<>"")/(宏观数据!$F$1:$UN$1<F16),宏观数据!$F$1:$UN$1),"") -> 46205
A17: 中债企业债到期收益率(AAA):10年 | B17: 日度 | C17: S0059776 | D17: % | E17: =IFERROR(LOOKUP(9.99E+307,宏观数据!$F$55:$UN$55),"") -> 2.0976 | F17: =IFERROR(LOOKUP(2,1/(宏观数据!$F$55:$UN$55<>""),宏观数据!$F$1:$UN$1),"") -> 46206 | G17: =IFERROR(E17-H17,"") -> -0.0002 | H17: =IFERROR(LOOKUP(9.99E+307,OFFSET(宏观数据!$F$55,0,0,1,LOOKUP(2,1/(宏观数据!$F$55:$UN$55<>""),COLUMN(宏观数据!$F$55:$UN$55))-COLUMN(宏观数据!$F$55))),"") -> 2.0978 | I17: =IFERROR(LOOKUP(2,1/(宏观数据!$F$55:$UN$55<>"")/(宏观数据!$F$1:$UN$1<F17),宏观数据!$F$1:$UN$1),"") -> 46205
A18: 中债城投债到期收益率(AAA):10年 | B18: 日度 | C18: M0048437 | D18: % | E18: =IFERROR(LOOKUP(9.99E+307,宏观数据!$F$56:$UN$56),"") -> 2.1476 | F18: =IFERROR(LOOKUP(2,1/(宏观数据!$F$56:$UN$56<>""),宏观数据!$F$1:$UN$1),"") -> 46206 | G18: =IFERROR(E18-H18,"") -> 0.0018 | H18: =IFERROR(LOOKUP(9.99E+307,OFFSET(宏观数据!$F$56,0,0,1,LOOKUP(2,1/(宏观数据!$F$56:$UN$56<>""),COLUMN(宏观数据!$F$56:$UN$56))-COLUMN(宏观数据!$F$56))),"") -> 2.1458 | I18: =IFERROR(LOOKUP(2,1/(宏观数据!$F$56:$UN$56<>"")/(宏观数据!$F$1:$UN$1<F18),宏观数据!$F$1:$UN$1),"") -> 46205
A19: DR001 | B19: 日度 | C19: M1006336 | E19: =IFERROR(LOOKUP(9.99E+307,宏观数据!$F$81:$UN$81),"") -> 1.3608 | F19: =IFERROR(LOOKUP(2,1/(宏观数据!$F$81:$UN$81<>""),宏观数据!$F$1:$UN$1),"") -> 46206 | G19: =IFERROR(E19-H19,"") -> -0.044 | H19: =IFERROR(LOOKUP(9.99E+307,OFFSET(宏观数据!$F$81,0,0,1,LOOKUP(2,1/(宏观数据!$F$81:$UN$81<>""),COLUMN(宏观数据!$F$81:$UN$81))-COLUMN(宏观数据!$F$81))),"") -> 1.4048 | I19: =IFERROR(LOOKUP(2,1/(宏观数据!$F$81:$UN$81<>"")/(宏观数据!$F$1:$UN$1<F19),宏观数据!$F$1:$UN$1),"") -> 46205
A20: DR007 | B20: 日度 | C20: M1006337 | E20: =IFERROR(LOOKUP(9.99E+307,宏观数据!$F$82:$UN$82),"") -> 1.3924 | F20: =IFERROR(LOOKUP(2,1/(宏观数据!$F$82:$UN$82<>""),宏观数据!$F$1:$UN$1),"") -> 46206 | G20: =IFERROR(E20-H20,"") -> -0.0354 | H20: =IFERROR(LOOKUP(9.99E+307,OFFSET(宏观数据!$F$82,0,0,1,LOOKUP(2,1/(宏观数据!$F$82:$UN$82<>""),COLUMN(宏观数据!$F$82:$UN$82))-COLUMN(宏观数据!$F$82))),"") -> 1.4278 | I20: =IFERROR(LOOKUP(2,1/(宏观数据!$F$82:$UN$82<>"")/(宏观数据!$F$1:$UN$1<F20),宏观数据!$F$1:$UN$1),"") -> 46205
A21: R001 | B21: 日度 | C21: M1001794 | E21: =IFERROR(LOOKUP(9.99E+307,宏观数据!$F$83:$UN$83),"") -> 1.3861 | F21: =IFERROR(LOOKUP(2,1/(宏观数据!$F$83:$UN$83<>""),宏观数据!$F$1:$UN$1),"") -> 46206 | G21: =IFERROR(E21-H21,"") -> -0.0503 | H21: =IFERROR(LOOKUP(9.99E+307,OFFSET(宏观数据!$F$83,0,0,1,LOOKUP(2,1/(宏观数据!$F$83:$UN$83<>""),COLUMN(宏观数据!$F$83:$UN$83))-COLUMN(宏观数据!$F$83))),"") -> 1.4364 | I21: =IFERROR(LOOKUP(2,1/(宏观数据!$F$83:$UN$83<>"")/(宏观数据!$F$1:$UN$1<F21),宏观数据!$F$1:$UN$1),"") -> 46205
A22: R007 | B22: 日度 | C22: M1001795 | E22: =IFERROR(LOOKUP(9.99E+307,宏观数据!$F$84:$UN$84),"") -> 1.4225 | F22: =IFERROR(LOOKUP(2,1/(宏观数据!$F$84:$UN$84<>""),宏观数据!$F$1:$UN$1),"") -> 46206 | G22: =IFERROR(E22-H22,"") -> -0.0612 | H22: =IFERROR(LOOKUP(9.99E+307,OFFSET(宏观数据!$F$84,0,0,1,LOOKUP(2,1/(宏观数据!$F$84:$UN$84<>""),COLUMN(宏观数据!$F$84:$UN$84))-COLUMN(宏观数据!$F$84))),"") -> 1.4837 | I22: =IFERROR(LOOKUP(2,1/(宏观数据!$F$84:$UN$84<>"")/(宏观数据!$F$1:$UN$1<F22),宏观数据!$F$1:$UN$1),"") -> 46205
A23: 中国:同业存单到期收益率(AAA):1年 | B23: 日度 | C23: M1004902 | D23: % | E23: =IFERROR(LOOKUP(9.99E+307,宏观数据!$F$106:$UN$106),"") -> 1.465 | F23: =IFERROR(LOOKUP(2,1/(宏观数据!$F$106:$UN$106<>""),宏观数据!$F$1:$UN$1),"") -> 46206 | G23: =IFERROR(E23-H23,"") -> -0.005 | H23: =IFERROR(LOOKUP(9.99E+307,OFFSET(宏观数据!$F$106,0,0,1,LOOKUP(2,1/(宏观数据!$F$106:$UN$106<>""),COLUMN(宏观数据!$F$106:$UN$106))-COLUMN(宏观数据!$F$106))),"") -> 1.47 | I23: =IFERROR(LOOKUP(2,1/(宏观数据!$F$106:$UN$106<>"")/(宏观数据!$F$1:$UN$1<F23),宏观数据!$F$1:$UN$1),"") -> 46205
A24: 中国:社会融资规模:企业债券融资:当月值 | B24: 月度 | C24: M5206736 | D24: 亿元 | E24: =IFERROR(LOOKUP(9.99E+307,宏观数据!$F$117:$UN$117),"") -> 1680 | F24: =IFERROR(LOOKUP(2,1/(宏观数据!$F$117:$UN$117<>""),宏观数据!$F$1:$UN$1),"") -> 46173 | G24: =IFERROR(E24-H24,"") -> -2840 | H24: =IFERROR(LOOKUP(9.99E+307,OFFSET(宏观数据!$F$117,0,0,1,LOOKUP(2,1/(宏观数据!$F$117:$UN$117<>""),COLUMN(宏观数据!$F$117:$UN$117))-COLUMN(宏观数据!$F$117))),"") -> 4520 | I24: =IFERROR(LOOKUP(2,1/(宏观数据!$F$117:$UN$117<>"")/(宏观数据!$F$1:$UN$1<F24),宏观数据!$F$1:$UN$1),"") -> 46142
A25: SHIBOR:3个月 | B25: 日度 | C25: M0017142 | D25: % | E25: =IFERROR(LOOKUP(9.99E+307,宏观数据!$F$151:$UN$151),"") -> 1.435 | F25: =IFERROR(LOOKUP(2,1/(宏观数据!$F$151:$UN$151<>""),宏观数据!$F$1:$UN$1),"") -> 46206 | G25: =IFERROR(E25-H25,"") -> -0.002 | H25: =IFERROR(LOOKUP(9.99E+307,OFFSET(宏观数据!$F$151,0,0,1,LOOKUP(2,1/(宏观数据!$F$151:$UN$151<>""),COLUMN(宏观数据!$F$151:$UN$151))-COLUMN(宏观数据!$F$151))),"") -> 1.437 | I25: =IFERROR(LOOKUP(2,1/(宏观数据!$F$151:$UN$151<>"")/(宏观数据!$F$1:$UN$1<F25),宏观数据!$F$1:$UN$1),"") -> 46205
A26: 中国:贷款市场报价利率(LPR):1年 | B26: 月度 | C26: M0096870 | D26: % | E26: =IFERROR(LOOKUP(9.99E+307,宏观数据!$F$155:$UN$155),"") -> 3 | F26: =IFERROR(LOOKUP(2,1/(宏观数据!$F$155:$UN$155<>""),宏观数据!$F$1:$UN$1),"") -> 46195 | G26: =IFERROR(E26-H26,"") -> 0 | H26: =IFERROR(LOOKUP(9.99E+307,OFFSET(宏观数据!$F$155,0,0,1,LOOKUP(2,1/(宏观数据!$F$155:$UN$155<>""),COLUMN(宏观数据!$F$155:$UN$155))-COLUMN(宏观数据!$F$155))),"") -> 3 | I26: =IFERROR(LOOKUP(2,1/(宏观数据!$F$155:$UN$155<>"")/(宏观数据!$F$1:$UN$1<F26),宏观数据!$F$1:$UN$1),"") -> 46162
A27: 中国:国债收益率:10年 | B27: 日度 | C27: M0325687 | D27: % | E27: =IFERROR(LOOKUP(9.99E+307,宏观数据!$F$156:$UN$156),"") -> 1.7423 | F27: =IFERROR(LOOKUP(2,1/(宏观数据!$F$156:$UN$156<>""),宏观数据!$F$1:$UN$1),"") -> 46206 | G27: =IFERROR(E27-H27,"") -> 0.0054 | H27: =IFERROR(LOOKUP(9.99E+307,OFFSET(宏观数据!$F$156,0,0,1,LOOKUP(2,1/(宏观数据!$F$156:$UN$156<>""),COLUMN(宏观数据!$F$156:$UN$156))-COLUMN(宏观数据!$F$156))),"") -> 1.7369 | I27: =IFERROR(LOOKUP(2,1/(宏观数据!$F$156:$UN$156<>"")/(宏观数据!$F$1:$UN$1<F27),宏观数据!$F$1:$UN$1),"") -> 46205
A28: 中美10年期国债利差 (中-美) | B28: 日度 | C28: M0325687-G0000891 | D28: % | E28: =IFERROR(LOOKUP(9.99E+307,宏观数据!$F$176:$UN$176),"") -> -2.7069 | F28: =IFERROR(LOOKUP(2,1/(宏观数据!$F$176:$UN$176<>""),宏观数据!$F$1:$UN$1),"") -> 46185 | G28: =IFERROR(E28-H28,"") -> -0.0312 | H28: =IFERROR(LOOKUP(9.99E+307,OFFSET(宏观数据!$F$176,0,0,1,LOOKUP(2,1/(宏观数据!$F$176:$UN$176<>""),COLUMN(宏观数据!$F$176:$UN$176))-COLUMN(宏观数据!$F$176))),"") -> -2.6757 | I28: =IFERROR(LOOKUP(2,1/(宏观数据!$F$176:$UN$176<>"")/(宏观数据!$F$1:$UN$1<F28),宏观数据!$F$1:$UN$1),"") -> 46184

Sheet 中国宏观
B1: 频率 | C1: 代码 | D1: 单位 | E1: 当前数据 | F1: 数据日期 | G1: 变化 | H1: 上期数据 | I1: 上期日期 | J1: 趋势图
A2: 7天逆回购 | B2: 日度 | C2: M0041371 | D2: % | E2: =IFERROR(LOOKUP(9.99E+307,宏观数据!$F$85:$UN$85),"") -> 1.4 | F2: =IFERROR(LOOKUP(2,1/(宏观数据!$F$85:$UN$85<>""),宏观数据!$F$1:$UN$1),"") -> 46209 | G2: =IFERROR(E2-H2,"") -> 0 | H2: =IFERROR(LOOKUP(9.99E+307,OFFSET(宏观数据!$F$85,0,0,1,LOOKUP(2,1/(宏观数据!$F$85:$UN$85<>""),COLUMN(宏观数据!$F$85:$UN$85))-COLUMN(宏观数据!$F$85))),"") -> 1.4 | I2: =IFERROR(LOOKUP(2,1/(宏观数据!$F$85:$UN$85<>"")/(宏观数据!$F$1:$UN$1<F2),宏观数据!$F$1:$UN$1),"") -> 46206
A3: 法定存准率 | B3: 月度 | C3: M0061518 | D3: % | E3: =IFERROR(LOOKUP(9.99E+307,宏观数据!$F$27:$UN$27),"") -> 9 | F3: =IFERROR(LOOKUP(2,1/(宏观数据!$F$27:$UN$27<>""),宏观数据!$F$1:$UN$1),"") -> 46203 | G3: =IFERROR(E3-H3,"") -> 0 | H3: =IFERROR(LOOKUP(9.99E+307,OFFSET(宏观数据!$F$27,0,0,1,LOOKUP(2,1/(宏观数据!$F$27:$UN$27<>""),COLUMN(宏观数据!$F$27:$UN$27))-COLUMN(宏观数据!$F$27))),"") -> 9 | I3: =IFERROR(LOOKUP(2,1/(宏观数据!$F$27:$UN$27<>"")/(宏观数据!$F$1:$UN$1<F3),宏观数据!$F$1:$UN$1),"") -> 46173
A4: 公开市场操作净投放 | B4: 日度 | C4: A4087688 | D4: 亿元 | E4: =IFERROR(LOOKUP(9.99E+307,宏观数据!$F$79:$UN$79),"") -> 495 | F4: =IFERROR(LOOKUP(2,1/(宏观数据!$F$79:$UN$79<>""),宏观数据!$F$1:$UN$1),"") -> 46209 | G4: =IFERROR(E4-H4,"") -> 2180 | H4: =IFERROR(LOOKUP(9.99E+307,OFFSET(宏观数据!$F$79,0,0,1,LOOKUP(2,1/(宏观数据!$F$79:$UN$79<>""),COLUMN(宏观数据!$F$79:$UN$79))-COLUMN(宏观数据!$F$79))),"") -> -1685 | I4: =IFERROR(LOOKUP(2,1/(宏观数据!$F$79:$UN$79<>"")/(宏观数据!$F$1:$UN$1<F4),宏观数据!$F$1:$UN$1),"") -> 46206
A5: 中央银行贷款-总投放 | B5: 月度 | C5: N7822723+Z0569230+Z7194825+P5747228+C8808133 | E5: =IFERROR(IFERROR(LOOKUP(9.99E+307,宏观数据!$F$28:$UN$28),0)+IFERROR(LOOKUP(9.99E+307,宏观数据!$F$29:$UN$29),0)+IFERROR(LOOKUP(9.99E+307,宏观数据!$F$30:$UN$30),0)+IFERROR(LOOKUP(9.99E+307,宏观数据!$F$31:$UN$31),0)+IFERROR(LOOKUP(9.99E+307,宏观数据!$F$32:$UN$32),0),"") -> 10128 | F5: =IFERROR(LOOKUP(2,1/(宏观数据!$F$29:$UN$29<>""),宏观数据!$F$1:$UN$1),"") -> 46203 | G5: =IFERROR(E5-H5,"") -> 9535 | H5: =IFERROR(IFERROR(LOOKUP(9.99E+307,OFFSET(宏观数据!$F$28,0,0,1,LOOKUP(2,1/(宏观数据!$F$28:$UN$28<>""),COLUMN(宏观数据!$F$28:$UN$28))-COLUMN(宏观数据!$F$28))),0)+IFERROR(LOOKUP(9.99E+307,OFFSET(宏观数据!$F$29,0,0,1,LOOKUP(2,1/(宏观数据!$F$29:$UN$29<>""),COLUMN(宏观数据!$F$29:$UN$29))-COLUMN(宏观数据!$F$29))),0)+IFERROR(LOOKUP(9.99E+307,OFFSET(宏观数据!$F$30,0,0,1,LOOKUP(2,1/(宏观数据!$F$30:$UN$30<>""),COLUMN(宏观数据!$F$30:$UN$30))-COLUMN(宏观数据!$F$30))),0)+IFERROR(LOOKUP(9.99E+307,OFFSET(宏观数据!$F$31,0,0,1,LOOKUP(2,1/(宏观数据!$F$31:$UN$31<>""),COLUMN(宏观数据!$F$31:$UN$31))-COLUMN(宏观数据!$F$31))),0)+IFERROR(LOOKUP(9.99E+307,OFFSET(宏观数据!$F$32,0,0,1,LOOKUP(2,1/(宏观数据!$F$32:$UN$32<>""),COLUMN(宏观数据!$F$32:$UN$32))-COLUMN(宏观数据!$F$32))),0),"") -> 593 | I5: =IFERROR(LOOKUP(2,1/(宏观数据!$F$29:$UN$29<>"")/(宏观数据!$F$1:$UN$1<F5),宏观数据!$F$1:$UN$1),"") -> 46173
A6: DR001 | B6: 日度 | C6: M1006336 | D6: % | E6: =IFERROR(LOOKUP(9.99E+307,宏观数据!$F$81:$UN$81),"") -> 1.3608 | F6: =IFERROR(LOOKUP(2,1/(宏观数据!$F$81:$UN$81<>""),宏观数据!$F$1:$UN$1),"") -> 46206 | G6: =IFERROR(E6-H6,"") -> -0.044 | H6: =IFERROR(LOOKUP(9.99E+307,OFFSET(宏观数据!$F$81,0,0,1,LOOKUP(2,1/(宏观数据!$F$81:$UN$81<>""),COLUMN(宏观数据!$F$81:$UN$81))-COLUMN(宏观数据!$F$81))),"") -> 1.4048 | I6: =IFERROR(LOOKUP(2,1/(宏观数据!$F$81:$UN$81<>"")/(宏观数据!$F$1:$UN$1<F6),宏观数据!$F$1:$UN$1),"") -> 46205
A7: DR007 | B7: 日度 | C7: M1006337 | D7: % | E7: =IFERROR(LOOKUP(9.99E+307,宏观数据!$F$82:$UN$82),"") -> 1.3924 | F7: =IFERROR(LOOKUP(2,1/(宏观数据!$F$82:$UN$82<>""),宏观数据!$F$1:$UN$1),"") -> 46206 | G7: =IFERROR(E7-H7,"") -> -0.0354 | H7: =IFERROR(LOOKUP(9.99E+307,OFFSET(宏观数据!$F$82,0,0,1,LOOKUP(2,1/(宏观数据!$F$82:$UN$82<>""),COLUMN(宏观数据!$F$82:$UN$82))-COLUMN(宏观数据!$F$82))),"") -> 1.4278 | I7: =IFERROR(LOOKUP(2,1/(宏观数据!$F$82:$UN$82<>"")/(宏观数据!$F$1:$UN$1<F7),宏观数据!$F$1:$UN$1),"") -> 46205
A8: R001 | B8: 日度 | C8: M1001794 | D8: % | E8: =IFERROR(LOOKUP(9.99E+307,宏观数据!$F$83:$UN$83),"") -> 1.3861 | F8: =IFERROR(LOOKUP(2,1/(宏观数据!$F$83:$UN$83<>""),宏观数据!$F$1:$UN$1),"") -> 46206 | G8: =IFERROR(E8-H8,"") -> -0.0503 | H8: =IFERROR(LOOKUP(9.99E+307,OFFSET(宏观数据!$F$83,0,0,1,LOOKUP(2,1/(宏观数据!$F$83:$UN$83<>""),COLUMN(宏观数据!$F$83:$UN$83))-COLUMN(宏观数据!$F$83))),"") -> 1.4364 | I8: =IFERROR(LOOKUP(2,1/(宏观数据!$F$83:$UN$83<>"")/(宏观数据!$F$1:$UN$1<F8),宏观数据!$F$1:$UN$1),"") -> 46205
A9: R007 | B9: 日度 | C9: M1001795 | D9: % | E9: =IFERROR(LOOKUP(9.99E+307,宏观数据!$F$84:$UN$84),"") -> 1.4225 | F9: =IFERROR(LOOKUP(2,1/(宏观数据!$F$84:$UN$84<>""),宏观数据!$F$1:$UN$1),"") -> 46206 | G9: =IFERROR(E9-H9,"") -> -0.0612 | H9: =IFERROR(LOOKUP(9.99E+307,OFFSET(宏观数据!$F$84,0,0,1,LOOKUP(2,1/(宏观数据!$F$84:$UN$84<>""),COLUMN(宏观数据!$F$84:$UN$84))-COLUMN(宏观数据!$F$84))),"") -> 1.4837 | I9: =IFERROR(LOOKUP(2,1/(宏观数据!$F$84:$UN$84<>"")/(宏观数据!$F$1:$UN$1<F9),宏观数据!$F$1:$UN$1),"") -> 46205
A10: 社融存量 | B10: 月度 | C10: M5525763 | D10: % | E10: =IFERROR(LOOKUP(9.99E+307,宏观数据!$F$33:$UN$33),"") -> 7.7 | F10: =IFERROR(LOOKUP(2,1/(宏观数据!$F$33:$UN$33<>""),宏观数据!$F$1:$UN$1),"") -> 46173 | G10: =IFERROR(E10-H10,"") -> -0.1 | H10: =IFERROR(LOOKUP(9.99E+307,OFFSET(宏观数据!$F$33,0,0,1,LOOKUP(2,1/(宏观数据!$F$33:$UN$33<>""),COLUMN(宏观数据!$F$33:$UN$33))-COLUMN(宏观数据!$F$33))),"") -> 7.8 | I10: =IFERROR(LOOKUP(2,1/(宏观数据!$F$33:$UN$33<>"")/(宏观数据!$F$1:$UN$1<F10),宏观数据!$F$1:$UN$1),"") -> 46142
A11: 新增人民币贷款 | B11: 月度 | C11: M5525764 | D11: % | E11: =IFERROR(LOOKUP(9.99E+307,宏观数据!$F$35:$UN$35),"") -> 5.5 | F11: =IFERROR(LOOKUP(2,1/(宏观数据!$F$35:$UN$35<>""),宏观数据!$F$1:$UN$1),"") -> 46173 | G11: =IFERROR(E11-H11,"") -> -0.1 | H11: =IFERROR(LOOKUP(9.99E+307,OFFSET(宏观数据!$F$35,0,0,1,LOOKUP(2,1/(宏观数据!$F$35:$UN$35<>""),COLUMN(宏观数据!$F$35:$UN$35))-COLUMN(宏观数据!$F$35))),"") -> 5.6 | I11: =IFERROR(LOOKUP(2,1/(宏观数据!$F$35:$UN$35<>"")/(宏观数据!$F$1:$UN$1<F11),宏观数据!$F$1:$UN$1),"") -> 46142
A12: M1 | B12: 月度 | C12: M0001383 | D12: % | E12: =IFERROR(LOOKUP(9.99E+307,宏观数据!$F$39:$UN$39),"") -> 5.5 | F12: =IFERROR(LOOKUP(2,1/(宏观数据!$F$39:$UN$39<>""),宏观数据!$F$1:$UN$1),"") -> 46173 | G12: =IFERROR(E12-H12,"") -> 0.5 | H12: =IFERROR(LOOKUP(9.99E+307,OFFSET(宏观数据!$F$39,0,0,1,LOOKUP(2,1/(宏观数据!$F$39:$UN$39<>""),COLUMN(宏观数据!$F$39:$UN$39))-COLUMN(宏观数据!$F$39))),"") -> 5 | I12: =IFERROR(LOOKUP(2,1/(宏观数据!$F$39:$UN$39<>"")/(宏观数据!$F$1:$UN$1<F12),宏观数据!$F$1:$UN$1),"") -> 46142
A13: M2 | B13: 月度 | C13: M0001385 | D13: % | E13: =IFERROR(LOOKUP(9.99E+307,宏观数据!$F$41:$UN$41),"") -> 8.6 | F13: =IFERROR(LOOKUP(2,1/(宏观数据!$F$41:$UN$41<>""),宏观数据!$F$1:$UN$1),"") -> 46173 | G13: =IFERROR(E13-H13,"") -> 0 | H13: =IFERROR(LOOKUP(9.99E+307,OFFSET(宏观数据!$F$41,0,0,1,LOOKUP(2,1/(宏观数据!$F$41:$UN$41<>""),COLUMN(宏观数据!$F$41:$UN$41))-COLUMN(宏观数据!$F$41))),"") -> 8.6 | I13: =IFERROR(LOOKUP(2,1/(宏观数据!$F$41:$UN$41<>"")/(宏观数据!$F$1:$UN$1<F13),宏观数据!$F$1:$UN$1),"") -> 46142
A14: 社零 | B14: 月度 | C14: M0001428 | D14: % | E14: =IFERROR(LOOKUP(9.99E+307,宏观数据!$F$9:$UN$9),"") -> -0.6 | F14: =IFERROR(LOOKUP(2,1/(宏观数据!$F$9:$UN$9<>""),宏观数据!$F$1:$UN$1),"") -> 46173 | G14: =IFERROR(E14-H14,"") -> -0.8 | H14: =IFERROR(LOOKUP(9.99E+307,OFFSET(宏观数据!$F$9,0,0,1,LOOKUP(2,1/(宏观数据!$F$9:$UN$9<>""),COLUMN(宏观数据!$F$9:$UN$9))-COLUMN(宏观数据!$F$9))),"") -> 0.2 | I14: =IFERROR(LOOKUP(2,1/(宏观数据!$F$9:$UN$9<>"")/(宏观数据!$F$1:$UN$1<F14),宏观数据!$F$1:$UN$1),"") -> 46142
A15: 固定投资 | B15: 月度 | C15: M0000273 | D15: % | E15: =IFERROR(LOOKUP(9.99E+307,宏观数据!$F$15:$UN$15),"") -> -4.1 | F15: =IFERROR(LOOKUP(2,1/(宏观数据!$F$15:$UN$15<>""),宏观数据!$F$1:$UN$1),"") -> 46173 | G15: =IFERROR(E15-H15,"") -> -2.5 | H15: =IFERROR(LOOKUP(9.99E+307,OFFSET(宏观数据!$F$15,0,0,1,LOOKUP(2,1/(宏观数据!$F$15:$UN$15<>""),COLUMN(宏观数据!$F$15:$UN$15))-COLUMN(宏观数据!$F$15))),"") -> -1.6 | I15: =IFERROR(LOOKUP(2,1/(宏观数据!$F$15:$UN$15<>"")/(宏观数据!$F$1:$UN$1<F15),宏观数据!$F$1:$UN$1),"") -> 46142
A16: 房屋销售 | B16: 月度 | C16: S0073300 | D16: % | E16: =IFERROR(LOOKUP(9.99E+307,宏观数据!$F$105:$UN$105),"") -> -10.8 | F16: =IFERROR(LOOKUP(2,1/(宏观数据!$F$105:$UN$105<>""),宏观数据!$F$1:$UN$1),"") -> 46173 | G16: =IFERROR(E16-H16,"") -> -0.6 | H16: =IFERROR(LOOKUP(9.99E+307,OFFSET(宏观数据!$F$105,0,0,1,LOOKUP(2,1/(宏观数据!$F$105:$UN$105<>""),COLUMN(宏观数据!$F$105:$UN$105))-COLUMN(宏观数据!$F$105))),"") -> -10.2 | I16: =IFERROR(LOOKUP(2,1/(宏观数据!$F$105:$UN$105<>"")/(宏观数据!$F$1:$UN$1<F16),宏观数据!$F$1:$UN$1),"") -> 46142
A17: 制造业PMI | B17: 月度 | C17: M0017126 | D17: % | E17: =IFERROR(LOOKUP(9.99E+307,宏观数据!$F$3:$UN$3),"") -> 50.3 | F17: =IFERROR(LOOKUP(2,1/(宏观数据!$F$3:$UN$3<>""),宏观数据!$F$1:$UN$1),"") -> 46203 | G17: =IFERROR(E17-H17,"") -> 0.3 | H17: =IFERROR(LOOKUP(9.99E+307,OFFSET(宏观数据!$F$3,0,0,1,LOOKUP(2,1/(宏观数据!$F$3:$UN$3<>""),COLUMN(宏观数据!$F$3:$UN$3))-COLUMN(宏观数据!$F$3))),"") -> 50 | I17: =IFERROR(LOOKUP(2,1/(宏观数据!$F$3:$UN$3<>"")/(宏观数据!$F$1:$UN$1<F17),宏观数据!$F$1:$UN$1),"") -> 46173
A18: 非制造业PMI | B18: 月度 | C18: M0048236 | D18: % | E18: =IFERROR(LOOKUP(9.99E+307,宏观数据!$F$8:$UN$8),"") -> 50.2 | F18: =IFERROR(LOOKUP(2,1/(宏观数据!$F$8:$UN$8<>""),宏观数据!$F$1:$UN$1),"") -> 46203 | G18: =IFERROR(E18-H18,"") -> 0.1 | H18: =IFERROR(LOOKUP(9.99E+307,OFFSET(宏观数据!$F$8,0,0,1,LOOKUP(2,1/(宏观数据!$F$8:$UN$8<>""),COLUMN(宏观数据!$F$8:$UN$8))-COLUMN(宏观数据!$F$8))),"") -> 50.1 | I18: =IFERROR(LOOKUP(2,1/(宏观数据!$F$8:$UN$8<>"")/(宏观数据!$F$1:$UN$1<F18),宏观数据!$F$1:$UN$1),"") -> 46173
A19: 工业增加值 | B19: 月度 | C19: M0000545 | D19: % | E19: =IFERROR(LOOKUP(9.99E+307,宏观数据!$F$20:$UN$20),"") -> 4.5 | F19: =IFERROR(LOOKUP(2,1/(宏观数据!$F$20:$UN$20<>""),宏观数据!$F$1:$UN$1),"") -> 46173 | G19: =IFERROR(E19-H19,"") -> 0.4 | H19: =IFERROR(LOOKUP(9.99E+307,OFFSET(宏观数据!$F$20,0,0,1,LOOKUP(2,1/(宏观数据!$F$20:$UN$20<>""),COLUMN(宏观数据!$F$20:$UN$20))-COLUMN(宏观数据!$F$20))),"") -> 4.1 | I19: =IFERROR(LOOKUP(2,1/(宏观数据!$F$20:$UN$20<>"")/(宏观数据!$F$1:$UN$1<F19),宏观数据!$F$1:$UN$1),"") -> 46142
A20: 出口 | B20: 月度 | C20: M0000607 | D20: % | E20: =IFERROR(LOOKUP(9.99E+307,宏观数据!$F$21:$UN$21),"") -> 19.4 | F20: =IFERROR(LOOKUP(2,1/(宏观数据!$F$21:$UN$21<>""),宏观数据!$F$1:$UN$1),"") -> 46173 | G20: =IFERROR(E20-H20,"") -> 5.4 | H20: =IFERROR(LOOKUP(9.99E+307,OFFSET(宏观数据!$F$21,0,0,1,LOOKUP(2,1/(宏观数据!$F$21:$UN$21<>""),COLUMN(宏观数据!$F$21:$UN$21))-COLUMN(宏观数据!$F$21))),"") -> 14 | I20: =IFERROR(LOOKUP(2,1/(宏观数据!$F$21:$UN$21<>"")/(宏观数据!$F$1:$UN$1<F20),宏观数据!$F$1:$UN$1),"") -> 46142
A21: PPI | B21: 月度 | C21: M0001227 | D21: % | E21: =IFERROR(LOOKUP(9.99E+307,宏观数据!$F$23:$UN$23),"") -> 3.9 | F21: =IFERROR(LOOKUP(2,1/(宏观数据!$F$23:$UN$23<>""),宏观数据!$F$1:$UN$1),"") -> 46173 | G21: =IFERROR(E21-H21,"") -> 1.1 | H21: =IFERROR(LOOKUP(9.99E+307,OFFSET(宏观数据!$F$23,0,0,1,LOOKUP(2,1/(宏观数据!$F$23:$UN$23<>""),COLUMN(宏观数据!$F$23:$UN$23))-COLUMN(宏观数据!$F$23))),"") -> 2.8 | I21: =IFERROR(LOOKUP(2,1/(宏观数据!$F$23:$UN$23<>"")/(宏观数据!$F$1:$UN$1<F21),宏观数据!$F$1:$UN$1),"") -> 46142
A22: CPI | B22: 月度 | C22: M0000612 | D22: % | E22: =IFERROR(LOOKUP(9.99E+307,宏观数据!$F$25:$UN$25),"") -> 1.2 | F22: =IFERROR(LOOKUP(2,1/(宏观数据!$F$25:$UN$25<>""),宏观数据!$F$1:$UN$1),"") -> 46173 | G22: =IFERROR(E22-H22,"") -> 0 | H22: =IFERROR(LOOKUP(9.99E+307,OFFSET(宏观数据!$F$25,0,0,1,LOOKUP(2,1/(宏观数据!$F$25:$UN$25<>""),COLUMN(宏观数据!$F$25:$UN$25))-COLUMN(宏观数据!$F$25))),"") -> 1.2 | I22: =IFERROR(LOOKUP(2,1/(宏观数据!$F$25:$UN$25<>"")/(宏观数据!$F$1:$UN$1<F22),宏观数据!$F$1:$UN$1),"") -> 46142
A23: 原材料购价 | B23: 月度 | C23: M0017134 | E23: =IFERROR(LOOKUP(9.99E+307,宏观数据!$F$107:$UN$107),"") -> 54.2 | F23: =IFERROR(LOOKUP(2,1/(宏观数据!$F$107:$UN$107<>""),宏观数据!$F$1:$UN$1),"") -> 46203 | G23: =IFERROR(E23-H23,"") -> -6.3 | H23: =IFERROR(LOOKUP(9.99E+307,OFFSET(宏观数据!$F$107,0,0,1,LOOKUP(2,1/(宏观数据!$F$107:$UN$107<>""),COLUMN(宏观数据!$F$107:$UN$107))-COLUMN(宏观数据!$F$107))),"") -> 60.5 | I23: =IFERROR(LOOKUP(2,1/(宏观数据!$F$107:$UN$107<>"")/(宏观数据!$F$1:$UN$1<F23),宏观数据!$F$1:$UN$1),"") -> 46173
A24: 中国:社会融资规模:当月值 | B24: 月度 | C24: M5206730 | D24: 亿元 | E24: =IFERROR(LOOKUP(9.99E+307,宏观数据!$F$114:$UN$114),"") -> 20264 | F24: =IFERROR(LOOKUP(2,1/(宏观数据!$F$114:$UN$114<>""),宏观数据!$F$1:$UN$1),"") -> 46173 | G24: =IFERROR(E24-H24,"") -> 14026 | H24: =IFERROR(LOOKUP(9.99E+307,OFFSET(宏观数据!$F$114,0,0,1,LOOKUP(2,1/(宏观数据!$F$114:$UN$114<>""),COLUMN(宏观数据!$F$114:$UN$114))-COLUMN(宏观数据!$F$114))),"") -> 6238 | I24: =IFERROR(LOOKUP(2,1/(宏观数据!$F$114:$UN$114<>"")/(宏观数据!$F$1:$UN$1<F24),宏观数据!$F$1:$UN$1),"") -> 46142
A25: 中国:社会融资规模:新增人民币贷款:当月值 | B25: 月度 | C25: M5206731 | D25: 亿元 | E25: =IFERROR(LOOKUP(9.99E+307,宏观数据!$F$115:$UN$115),"") -> 4965 | F25: =IFERROR(LOOKUP(2,1/(宏观数据!$F$115:$UN$115<>""),宏观数据!$F$1:$UN$1),"") -> 46173 | G25: =IFERROR(E25-H25,"") -> 8971 | H25: =IFERROR(LOOKUP(9.99E+307,OFFSET(宏观数据!$F$115,0,0,1,LOOKUP(2,1/(宏观数据!$F$115:$UN$115<>""),COLUMN(宏观数据!$F$115:$UN$115))-COLUMN(宏观数据!$F$115))),"") -> -4006 | I25: =IFERROR(LOOKUP(2,1/(宏观数据!$F$115:$UN$115<>"")/(宏观数据!$F$1:$UN$1<F25),宏观数据!$F$1:$UN$1),"") -> 46142
A26: 中国:社会融资规模:政府债券:当月值 | B26: 月度 | C26: M6179492 | D26: 亿元 | E26: =IFERROR(LOOKUP(9.99E+307,宏观数据!$F$116:$UN$116),"") -> 12236 | F26: =IFERROR(LOOKUP(2,1/(宏观数据!$F$116:$UN$116<>""),宏观数据!$F$1:$UN$1),"") -> 46173 | G26: =IFERROR(E26-H26,"") -> 3195 | H26: =IFERROR(LOOKUP(9.99E+307,OFFSET(宏观数据!$F$116,0,0,1,LOOKUP(2,1/(宏观数据!$F$116:$UN$116<>""),COLUMN(宏观数据!$F$116:$UN$116))-COLUMN(宏观数据!$F$116))),"") -> 9041 | I26: =IFERROR(LOOKUP(2,1/(宏观数据!$F$116:$UN$116<>"")/(宏观数据!$F$1:$UN$1<F26),宏观数据!$F$1:$UN$1),"") -> 46142
A27: 中国:社会融资规模:企业债券融资:当月值 | B27: 月度 | C27: M5206736 | D27: 亿元 | E27: =IFERROR(LOOKUP(9.99E+307,宏观数据!$F$117:$UN$117),"") -> 1680 | F27: =IFERROR(LOOKUP(2,1/(宏观数据!$F$117:$UN$117<>""),宏观数据!$F$1:$UN$1),"") -> 46173 | G27: =IFERROR(E27-H27,"") -> -2840 | H27: =IFERROR(LOOKUP(9.99E+307,OFFSET(宏观数据!$F$117,0,0,1,LOOKUP(2,1/(宏观数据!$F$117:$UN$117<>""),COLUMN(宏观数据!$F$117:$UN$117))-COLUMN(宏观数据!$F$117))),"") -> 4520 | I27: =IFERROR(LOOKUP(2,1/(宏观数据!$F$117:$UN$117<>"")/(宏观数据!$F$1:$UN$1<F27),宏观数据!$F$1:$UN$1),"") -> 46142
A28: 中国:社会融资规模:新增未贴现银行承兑汇票:当月值 | B28: 月度 | C28: M5206735 | D28: 亿元 | E28: =IFERROR(LOOKUP(9.99E+307,宏观数据!$F$118:$UN$118),"") -> -685 | F28: =IFERROR(LOOKUP(2,1/(宏观数据!$F$118:$UN$118<>""),宏观数据!$F$1:$UN$1),"") -> 46173 | G28: =IFERROR(E28-H28,"") -> 4599 | H28: =IFERROR(LOOKUP(9.99E+307,OFFSET(宏观数据!$F$118,0,0,1,LOOKUP(2,1/(宏观数据!$F$118:$UN$118<>""),COLUMN(宏观数据!$F$118:$UN$118))-COLUMN(宏观数据!$F$118))),"") -> -5284 | I28: =IFERROR(LOOKUP(2,1/(宏观数据!$F$118:$UN$118<>"")/(宏观数据!$F$1:$UN$1<F28),宏观数据!$F$1:$UN$1),"") -> 46142
A29: 中国:社会融资规模:新增外币贷款:当月值 | B29: 月度 | C29: M5206732 | D29: 亿元 | E29: =IFERROR(LOOKUP(9.99E+307,宏观数据!$F$119:$UN$119),"") -> 117 | F29: =IFERROR(LOOKUP(2,1/(宏观数据!$F$119:$UN$119<>""),宏观数据!$F$1:$UN$1),"") -> 46173 | G29: =IFERROR(E29-H29,"") -> -67 | H29: =IFERROR(LOOKUP(9.99E+307,OFFSET(宏观数据!$F$119,0,0,1,LOOKUP(2,1/(宏观数据!$F$119:$UN$119<>""),COLUMN(宏观数据!$F$119:$UN$119))-COLUMN(宏观数据!$F$119))),"") -> 184 | I29: =IFERROR(LOOKUP(2,1/(宏观数据!$F$119:$UN$119<>"")/(宏观数据!$F$1:$UN$1<F29),宏观数据!$F$1:$UN$1),"") -> 46142
A30: 中国:金融机构:新增人民币存款:财政存款:当月值 | B30: 月度 | C30: M0009945 | D30: 亿元 | E30: =IFERROR(LOOKUP(9.99E+307,宏观数据!$F$120:$UN$120),"") -> 7100 | F30: =IFERROR(LOOKUP(2,1/(宏观数据!$F$120:$UN$120<>""),宏观数据!$F$1:$UN$1),"") -> 46173 | G30: =IFERROR(E30-H30,"") -> -294 | H30: =IFERROR(LOOKUP(9.99E+307,OFFSET(宏观数据!$F$120,0,0,1,LOOKUP(2,1/(宏观数据!$F$120:$UN$120<>""),COLUMN(宏观数据!$F$120:$UN$120))-COLUMN(宏观数据!$F$120))),"") -> 7394 | I30: =IFERROR(LOOKUP(2,1/(宏观数据!$F$120:$UN$120<>"")/(宏观数据!$F$1:$UN$1<F30),宏观数据!$F$1:$UN$1),"") -> 46142
A31: 中国:房屋销售价格指数:二手住宅:70个大中城市:当月同比 | B31: 月度 | C31: S2707425 | D31: % | E31: =IFERROR(LOOKUP(9.99E+307,宏观数据!$F$121:$UN$121),"") -> -5.9 | F31: =IFERROR(LOOKUP(2,1/(宏观数据!$F$121:$UN$121<>""),宏观数据!$F$1:$UN$1),"") -> 46173 | G31: =IFERROR(E31-H31,"") -> 0.3 | H31: =IFERROR(LOOKUP(9.99E+307,OFFSET(宏观数据!$F$121,0,0,1,LOOKUP(2,1/(宏观数据!$F$121:$UN$121<>""),COLUMN(宏观数据!$F$121:$UN$121))-COLUMN(宏观数据!$F$121))),"") -> -6.2 | I31: =IFERROR(LOOKUP(2,1/(宏观数据!$F$121:$UN$121<>"")/(宏观数据!$F$1:$UN$1<F31),宏观数据!$F$1:$UN$1),"") -> 46142
A32: 中国:制造业PMI:新订单 | B32: 月度 | C32: M0017128 | D32: % | E32: =IFERROR(LOOKUP(9.99E+307,宏观数据!$F$122:$UN$122),"") -> 51.2 | F32: =IFERROR(LOOKUP(2,1/(宏观数据!$F$122:$UN$122<>""),宏观数据!$F$1:$UN$1),"") -> 46203 | G32: =IFERROR(E32-H32,"") -> 1.3 | H32: =IFERROR(LOOKUP(9.99E+307,OFFSET(宏观数据!$F$122,0,0,1,LOOKUP(2,1/(宏观数据!$F$122:$UN$122<>""),COLUMN(宏观数据!$F$122:$UN$122))-COLUMN(宏观数据!$F$122))),"") -> 49.9 | I32: =IFERROR(LOOKUP(2,1/(宏观数据!$F$122:$UN$122<>"")/(宏观数据!$F$1:$UN$1<F32),宏观数据!$F$1:$UN$1),"") -> 46173
A33: 中国:制造业PMI:生产 | B33: 月度 | C33: M0017127 | D33: % | E33: =IFERROR(LOOKUP(9.99E+307,宏观数据!$F$123:$UN$123),"") -> 51.4 | F33: =IFERROR(LOOKUP(2,1/(宏观数据!$F$123:$UN$123<>""),宏观数据!$F$1:$UN$1),"") -> 46203 | G33: =IFERROR(E33-H33,"") -> 0.2 | H33: =IFERROR(LOOKUP(9.99E+307,OFFSET(宏观数据!$F$123,0,0,1,LOOKUP(2,1/(宏观数据!$F$123:$UN$123<>""),COLUMN(宏观数据!$F$123:$UN$123))-COLUMN(宏观数据!$F$123))),"") -> 51.2 | I33: =IFERROR(LOOKUP(2,1/(宏观数据!$F$123:$UN$123<>"")/(宏观数据!$F$1:$UN$1<F33),宏观数据!$F$1:$UN$1),"") -> 46173
A34: 中国:营业收入利润率:规模以上工业企业:累计值 | B34: 月度 | C34: M5207655 | D34: % | E34: =IFERROR(LOOKUP(9.99E+307,宏观数据!$F$124:$UN$124),"") -> 5.56 | F34: =IFERROR(LOOKUP(2,1/(宏观数据!$F$124:$UN$124<>""),宏观数据!$F$1:$UN$1),"") -> 46173 | G34: =IFERROR(E34-H34,"") -> 0.13 | H34: =IFERROR(LOOKUP(9.99E+307,OFFSET(宏观数据!$F$124,0,0,1,LOOKUP(2,1/(宏观数据!$F$124:$UN$124<>""),COLUMN(宏观数据!$F$124:$UN$124))-COLUMN(宏观数据!$F$124))),"") -> 5.43 | I34: =IFERROR(LOOKUP(2,1/(宏观数据!$F$124:$UN$124<>"")/(宏观数据!$F$1:$UN$1<F34),宏观数据!$F$1:$UN$1),"") -> 46142
A35: 中国:利润总额:规模以上工业企业:累计同比 | B35: 月度 | C35: M0000557 | D35: % | E35: =IFERROR(LOOKUP(9.99E+307,宏观数据!$F$125:$UN$125),"") -> 18.8 | F35: =IFERROR(LOOKUP(2,1/(宏观数据!$F$125:$UN$125<>""),宏观数据!$F$1:$UN$1),"") -> 46173 | G35: =IFERROR(E35-H35,"") -> 0.6 | H35: =IFERROR(LOOKUP(9.99E+307,OFFSET(宏观数据!$F$125,0,0,1,LOOKUP(2,1/(宏观数据!$F$125:$UN$125<>""),COLUMN(宏观数据!$F$125:$UN$125))-COLUMN(宏观数据!$F$125))),"") -> 18.2 | I35: =IFERROR(LOOKUP(2,1/(宏观数据!$F$125:$UN$125<>"")/(宏观数据!$F$1:$UN$1<F35),宏观数据!$F$1:$UN$1),"") -> 46142
A36: 万得一致预测:中国:制造业PMI | B36: 月度 | C36: M0331594 | D36: % | E36: =IFERROR(LOOKUP(9.99E+307,宏观数据!$F$2:$UN$2),"") -> 50.08 | F36: =IFERROR(LOOKUP(2,1/(宏观数据!$F$2:$UN$2<>""),宏观数据!$F$1:$UN$1),"") -> 46234 | G36: =IFERROR(E36-H36,"") -> -0.12 | H36: =IFERROR(LOOKUP(9.99E+307,OFFSET(宏观数据!$F$2,0,0,1,LOOKUP(2,1/(宏观数据!$F$2:$UN$2<>""),COLUMN(宏观数据!$F$2:$UN$2))-COLUMN(宏观数据!$F$2))),"") -> 50.2 | I36: =IFERROR(LOOKUP(2,1/(宏观数据!$F$2:$UN$2<>"")/(宏观数据!$F$1:$UN$1<F36),宏观数据!$F$1:$UN$1),"") -> 46203
A37: 万得一致预测:中国:非制造业PMI | B37: 月度 | C37: A9541823 | D37: % | E37: =IFERROR(LOOKUP(9.99E+307,宏观数据!$F$4:$UN$4),"") -> 49.85 | F37: =IFERROR(LOOKUP(2,1/(宏观数据!$F$4:$UN$4<>""),宏观数据!$F$1:$UN$1),"") -> 46203 | G37: =IFERROR(E37-H37,"") -> -0.05 | H37: =IFERROR(LOOKUP(9.99E+307,OFFSET(宏观数据!$F$4,0,0,1,LOOKUP(2,1/(宏观数据!$F$4:$UN$4<>""),COLUMN(宏观数据!$F$4:$UN$4))-COLUMN(宏观数据!$F$4))),"") -> 49.9 | I37: =IFERROR(LOOKUP(2,1/(宏观数据!$F$4:$UN$4<>"")/(宏观数据!$F$1:$UN$1<F37),宏观数据!$F$1:$UN$1),"") -> 46142
A38: 中国:制造业PMI:新出口订单 | B38: 月度 | C38: M0017129 | D38: % | E38: =IFERROR(LOOKUP(9.99E+307,宏观数据!$F$7:$UN$7),"") -> 50.1 | F38: =IFERROR(LOOKUP(2,1/(宏观数据!$F$7:$UN$7<>""),宏观数据!$F$1:$UN$1),"") -> 46203 | G38: =IFERROR(E38-H38,"") -> 1.5 | H38: =IFERROR(LOOKUP(9.99E+307,OFFSET(宏观数据!$F$7,0,0,1,LOOKUP(2,1/(宏观数据!$F$7:$UN$7<>""),COLUMN(宏观数据!$F$7:$UN$7))-COLUMN(宏观数据!$F$7))),"") -> 48.6 | I38: =IFERROR(LOOKUP(2,1/(宏观数据!$F$7:$UN$7<>"")/(宏观数据!$F$1:$UN$1<F38),宏观数据!$F$1:$UN$1),"") -> 46173
A39: 万得一致预测:中国:社会消费品零售总额:当月同比 | B39: 月度 | C39: M0061679 | D39: % | E39: =IFERROR(LOOKUP(9.99E+307,宏观数据!$F$10:$UN$10),"") -> 1.5 | F39: =IFERROR(LOOKUP(2,1/(宏观数据!$F$10:$UN$10<>""),宏观数据!$F$1:$UN$1),"") -> 46234 | G39: =IFERROR(E39-H39,"") -> 1.37 | H39: =IFERROR(LOOKUP(9.99E+307,OFFSET(宏观数据!$F$10,0,0,1,LOOKUP(2,1/(宏观数据!$F$10:$UN$10<>""),COLUMN(宏观数据!$F$10:$UN$10))-COLUMN(宏观数据!$F$10))),"") -> 0.13 | I39: =IFERROR(LOOKUP(2,1/(宏观数据!$F$10:$UN$10<>"")/(宏观数据!$F$1:$UN$1<F39),宏观数据!$F$1:$UN$1),"") -> 46203
A40: 万得一致预测:中国:固定资产投资完成额:累计同比 | B40: 月度 | C40: M0061678 | D40: % | E40: =IFERROR(LOOKUP(9.99E+307,宏观数据!$F$11:$UN$11),"") -> -4.77 | F40: =IFERROR(LOOKUP(2,1/(宏观数据!$F$11:$UN$11<>""),宏观数据!$F$1:$UN$1),"") -> 46203 | G40: =IFERROR(E40-H40,"") -> -3.08 | H40: =IFERROR(LOOKUP(9.99E+307,OFFSET(宏观数据!$F$11,0,0,1,LOOKUP(2,1/(宏观数据!$F$11:$UN$11<>""),COLUMN(宏观数据!$F$11:$UN$11))-COLUMN(宏观数据!$F$11))),"") -> -1.69 | I40: =IFERROR(LOOKUP(2,1/(宏观数据!$F$11:$UN$11<>"")/(宏观数据!$F$1:$UN$1<F40),宏观数据!$F$1:$UN$1),"") -> 46173
A41: 万得一致预测:中国:固定资产投资完成额:制造业:累计同比 | B41: 月度 | C41: T2627623 | D41: % | E41: =IFERROR(LOOKUP(9.99E+307,宏观数据!$F$12:$UN$12),"") -> -0.4 | F41: =IFERROR(LOOKUP(2,1/(宏观数据!$F$12:$UN$12<>""),宏观数据!$F$1:$UN$1),"") -> 46203 | G41: =IFERROR(E41-H41,"") -> -0.5 | H41: =IFERROR(LOOKUP(9.99E+307,OFFSET(宏观数据!$F$12,0,0,1,LOOKUP(2,1/(宏观数据!$F$12:$UN$12<>""),COLUMN(宏观数据!$F$12:$UN$12))-COLUMN(宏观数据!$F$12))),"") -> 0.1 | I41: =IFERROR(LOOKUP(2,1/(宏观数据!$F$12:$UN$12<>"")/(宏观数据!$F$1:$UN$1<F41),宏观数据!$F$1:$UN$1),"") -> 46173
A42: 万得一致预测:中国:固定资产投资完成额:基础设施建设:累计同比 | B42: 月度 | C42: L7439791 | D42: % | E42: =IFERROR(LOOKUP(9.99E+307,宏观数据!$F$13:$UN$13),"") -> 0.75 | F42: =IFERROR(LOOKUP(2,1/(宏观数据!$F$13:$UN$13<>""),宏观数据!$F$1:$UN$1),"") -> 46203 | G42: =IFERROR(E42-H42,"") -> -1.3 | H42: =IFERROR(LOOKUP(9.99E+307,OFFSET(宏观数据!$F$13,0,0,1,LOOKUP(2,1/(宏观数据!$F$13:$UN$13<>""),COLUMN(宏观数据!$F$13:$UN$13))-COLUMN(宏观数据!$F$13))),"") -> 2.05 | I42: =IFERROR(LOOKUP(2,1/(宏观数据!$F$13:$UN$13<>"")/(宏观数据!$F$1:$UN$1<F42),宏观数据!$F$1:$UN$1),"") -> 46173
A43: 万得一致预测:中国:固定资产投资完成额:房地产开发:累计同比 | B43: 月度 | C43: V6384553 | D43: % | E43: =IFERROR(LOOKUP(9.99E+307,宏观数据!$F$14:$UN$14),"") -> -17.4 | F43: =IFERROR(LOOKUP(2,1/(宏观数据!$F$14:$UN$14<>""),宏观数据!$F$1:$UN$1),"") -> 46203 | G43: =IFERROR(E43-H43,"") -> -2.77 | H43: =IFERROR(LOOKUP(9.99E+307,OFFSET(宏观数据!$F$14,0,0,1,LOOKUP(2,1/(宏观数据!$F$14:$UN$14<>""),COLUMN(宏观数据!$F$14:$UN$14))-COLUMN(宏观数据!$F$14))),"") -> -14.63 | I43: =IFERROR(LOOKUP(2,1/(宏观数据!$F$14:$UN$14<>"")/(宏观数据!$F$1:$UN$1<F43),宏观数据!$F$1:$UN$1),"") -> 46173
A44: 中国:固定资产投资完成额:制造业:累计同比 | B44: 月度 | C44: M0000357 | D44: % | E44: =IFERROR(LOOKUP(9.99E+307,宏观数据!$F$16:$UN$16),"") -> -0.4 | F44: =IFERROR(LOOKUP(2,1/(宏观数据!$F$16:$UN$16<>""),宏观数据!$F$1:$UN$1),"") -> 46173 | G44: =IFERROR(E44-H44,"") -> -1.6 | H44: =IFERROR(LOOKUP(9.99E+307,OFFSET(宏观数据!$F$16,0,0,1,LOOKUP(2,1/(宏观数据!$F$16:$UN$16<>""),COLUMN(宏观数据!$F$16:$UN$16))-COLUMN(宏观数据!$F$16))),"") -> 1.2 | I44: =IFERROR(LOOKUP(2,1/(宏观数据!$F$16:$UN$16<>"")/(宏观数据!$F$1:$UN$1<F44),宏观数据!$F$1:$UN$1),"") -> 46142
A45: 中国:固定资产投资完成额:基础设施建设(Wind衍生计算):累计同比 | B45: 月度 | C45: M5440435 | D45: % | E45: =IFERROR(LOOKUP(9.99E+307,宏观数据!$F$17:$UN$17),"") -> 0.75 | F45: =IFERROR(LOOKUP(2,1/(宏观数据!$F$17:$UN$17<>""),宏观数据!$F$1:$UN$1),"") -> 46173 | G45: =IFERROR(E45-H45,"") -> -4.17 | H45: =IFERROR(LOOKUP(9.99E+307,OFFSET(宏观数据!$F$17,0,0,1,LOOKUP(2,1/(宏观数据!$F$17:$UN$17<>""),COLUMN(宏观数据!$F$17:$UN$17))-COLUMN(宏观数据!$F$17))),"") -> 4.92 | I45: =IFERROR(LOOKUP(2,1/(宏观数据!$F$17:$UN$17<>"")/(宏观数据!$F$1:$UN$1<F45),宏观数据!$F$1:$UN$1),"") -> 46142
A46: 中国:固定资产投资完成额:房地产业:累计同比 | B46: 月度 | C46: M0000449 | D46: % | E46: =IFERROR(LOOKUP(9.99E+307,宏观数据!$F$18:$UN$18),"") -> -15.9 | F46: =IFERROR(LOOKUP(2,1/(宏观数据!$F$18:$UN$18<>""),宏观数据!$F$1:$UN$1),"") -> 46173 | G46: =IFERROR(E46-H46,"") -> -2.5 | H46: =IFERROR(LOOKUP(9.99E+307,OFFSET(宏观数据!$F$18,0,0,1,LOOKUP(2,1/(宏观数据!$F$18:$UN$18<>""),COLUMN(宏观数据!$F$18:$UN$18))-COLUMN(宏观数据!$F$18))),"") -> -13.4 | I46: =IFERROR(LOOKUP(2,1/(宏观数据!$F$18:$UN$18<>"")/(宏观数据!$F$1:$UN$1<F46),宏观数据!$F$1:$UN$1),"") -> 46142
A47: 中国:民间固定资产投资完成额:累计同比 | B47: 月度 | C47: M5438208 | D47: % | E47: =IFERROR(LOOKUP(9.99E+307,宏观数据!$F$19:$UN$19),"") -> -7.1 | F47: =IFERROR(LOOKUP(2,1/(宏观数据!$F$19:$UN$19<>""),宏观数据!$F$1:$UN$1),"") -> 46173 | G47: =IFERROR(E47-H47,"") -> -1.9 | H47: =IFERROR(LOOKUP(9.99E+307,OFFSET(宏观数据!$F$19,0,0,1,LOOKUP(2,1/(宏观数据!$F$19:$UN$19<>""),COLUMN(宏观数据!$F$19:$UN$19))-COLUMN(宏观数据!$F$19))),"") -> -5.2 | I47: =IFERROR(LOOKUP(2,1/(宏观数据!$F$19:$UN$19<>"")/(宏观数据!$F$1:$UN$1<F47),宏观数据!$F$1:$UN$1),"") -> 46142
A48: 万得一致预测:中国:出口金额:当月同比 | B48: 月度 | C48: M0061680 | D48: % | E48: =IFERROR(LOOKUP(9.99E+307,宏观数据!$F$22:$UN$22),"") -> 18.51 | F48: =IFERROR(LOOKUP(2,1/(宏观数据!$F$22:$UN$22<>""),宏观数据!$F$1:$UN$1),"") -> 46203 | G48: =IFERROR(E48-H48,"") -> 6.18 | H48: =IFERROR(LOOKUP(9.99E+307,OFFSET(宏观数据!$F$22,0,0,1,LOOKUP(2,1/(宏观数据!$F$22:$UN$22<>""),COLUMN(宏观数据!$F$22:$UN$22))-COLUMN(宏观数据!$F$22))),"") -> 12.33 | I48: =IFERROR(LOOKUP(2,1/(宏观数据!$F$22:$UN$22<>"")/(宏观数据!$F$1:$UN$1<F48),宏观数据!$F$1:$UN$1),"") -> 46173
A49: 万得一致预测:中国:PPI:当月同比 | B49: 月度 | C49: M0061677 | D49: % | E49: =IFERROR(LOOKUP(9.99E+307,宏观数据!$F$24:$UN$24),"") -> 4.07 | F49: =IFERROR(LOOKUP(2,1/(宏观数据!$F$24:$UN$24<>""),宏观数据!$F$1:$UN$1),"") -> 46203 | G49: =IFERROR(E49-H49,"") -> 0.54 | H49: =IFERROR(LOOKUP(9.99E+307,OFFSET(宏观数据!$F$24,0,0,1,LOOKUP(2,1/(宏观数据!$F$24:$UN$24<>""),COLUMN(宏观数据!$F$24:$UN$24))-COLUMN(宏观数据!$F$24))),"") -> 3.53 | I49: =IFERROR(LOOKUP(2,1/(宏观数据!$F$24:$UN$24<>"")/(宏观数据!$F$1:$UN$1<F49),宏观数据!$F$1:$UN$1),"") -> 46173
A50: 万得一致预测:中国:CPI:当月同比 | B50: 月度 | C50: M0061676 | D50: % | E50: =IFERROR(LOOKUP(9.99E+307,宏观数据!$F$26:$UN$26),"") -> 0.1 | F50: =IFERROR(LOOKUP(2,1/(宏观数据!$F$26:$UN$26<>""),宏观数据!$F$1:$UN$1),"") -> 46234 | G50: =IFERROR(E50-H50,"") -> -1.08 | H50: =IFERROR(LOOKUP(9.99E+307,OFFSET(宏观数据!$F$26,0,0,1,LOOKUP(2,1/(宏观数据!$F$26:$UN$26<>""),COLUMN(宏观数据!$F$26:$UN$26))-COLUMN(宏观数据!$F$26))),"") -> 1.18 | I50: =IFERROR(LOOKUP(2,1/(宏观数据!$F$26:$UN$26<>"")/(宏观数据!$F$1:$UN$1<F50),宏观数据!$F$1:$UN$1),"") -> 46203
A51: 中国:央行工具流动性投放情况:常备借贷便利(SLF):净投放 | B51: 月度 | C51: N7822723 | D51: 亿元 | E51: =IFERROR(LOOKUP(9.99E+307,宏观数据!$F$28:$UN$28),"") -> 0 | F51: =IFERROR(LOOKUP(2,1/(宏观数据!$F$28:$UN$28<>""),宏观数据!$F$1:$UN$1),"") -> 46203 | G51: =IFERROR(E51-H51,"") -> -9 | H51: =IFERROR(LOOKUP(9.99E+307,OFFSET(宏观数据!$F$28,0,0,1,LOOKUP(2,1/(宏观数据!$F$28:$UN$28<>""),COLUMN(宏观数据!$F$28:$UN$28))-COLUMN(宏观数据!$F$28))),"") -> 9 | I51: =IFERROR(LOOKUP(2,1/(宏观数据!$F$28:$UN$28<>"")/(宏观数据!$F$1:$UN$1<F51),宏观数据!$F$1:$UN$1),"") -> 46173
A52: 中国:央行工具流动性投放情况:中期借贷便利(MLF):净投放 | B52: 月度 | C52: Z0569230 | D52: 亿元 | E52: =IFERROR(LOOKUP(9.99E+307,宏观数据!$F$29:$UN$29),"") -> 2000 | F52: =IFERROR(LOOKUP(2,1/(宏观数据!$F$29:$UN$29<>""),宏观数据!$F$1:$UN$1),"") -> 46203 | G52: =IFERROR(E52-H52,"") -> 1000 | H52: =IFERROR(LOOKUP(9.99E+307,OFFSET(宏观数据!$F$29,0,0,1,LOOKUP(2,1/(宏观数据!$F$29:$UN$29<>""),COLUMN(宏观数据!$F$29:$UN$29))-COLUMN(宏观数据!$F$29))),"") -> 1000 | I52: =IFERROR(LOOKUP(2,1/(宏观数据!$F$29:$UN$29<>"")/(宏观数据!$F$1:$UN$1<F52),宏观数据!$F$1:$UN$1),"") -> 46173
A53: 中国:央行工具流动性投放情况:抵押补充贷款(PSL):净投放 | B53: 月度 | C53: Z7194825 | D53: 亿元 | E53: =IFERROR(LOOKUP(9.99E+307,宏观数据!$F$30:$UN$30),"") -> -500 | F53: =IFERROR(LOOKUP(2,1/(宏观数据!$F$30:$UN$30<>""),宏观数据!$F$1:$UN$1),"") -> 46203 | G53: =IFERROR(E53-H53,"") -> 1045 | H53: =IFERROR(LOOKUP(9.99E+307,OFFSET(宏观数据!$F$30,0,0,1,LOOKUP(2,1/(宏观数据!$F$30:$UN$30<>""),COLUMN(宏观数据!$F$30:$UN$30))-COLUMN(宏观数据!$F$30))),"") -> -1545 | I53: =IFERROR(LOOKUP(2,1/(宏观数据!$F$30:$UN$30<>"")/(宏观数据!$F$1:$UN$1<F53),宏观数据!$F$1:$UN$1),"") -> 46173
A54: 中国:央行工具流动性投放情况:其他结构性货币政策工具:净投放 | B54: 月度 | C54: P5747228 | D54: 亿元 | E54: =IFERROR(LOOKUP(9.99E+307,宏观数据!$F$31:$UN$31),"") -> -1372 | F54: =IFERROR(LOOKUP(2,1/(宏观数据!$F$31:$UN$31<>""),宏观数据!$F$1:$UN$1),"") -> 46203 | G54: =IFERROR(E54-H54,"") -> -2501 | H54: =IFERROR(LOOKUP(9.99E+307,OFFSET(宏观数据!$F$31,0,0,1,LOOKUP(2,1/(宏观数据!$F$31:$UN$31<>""),COLUMN(宏观数据!$F$31:$UN$31))-COLUMN(宏观数据!$F$31))),"") -> 1129 | I54: =IFERROR(LOOKUP(2,1/(宏观数据!$F$31:$UN$31<>"")/(宏观数据!$F$1:$UN$1<F54),宏观数据!$F$1:$UN$1),"") -> 46173
A55: 中国:央行工具流动性投放情况:法定存款准备金率:净投放 | B55: 月度 | C55: C8808133 | D55: 亿元 | E55: =IFERROR(LOOKUP(9.99E+307,宏观数据!$F$32:$UN$32),"") -> 10000 | F55: =IFERROR(LOOKUP(2,1/(宏观数据!$F$32:$UN$32<>""),宏观数据!$F$1:$UN$1),"") -> 45808 | G55: =IFERROR(E55-H55,"") | H55: =IFERROR(LOOKUP(9.99E+307,OFFSET(宏观数据!$F$32,0,0,1,LOOKUP(2,1/(宏观数据!$F$32:$UN$32<>""),COLUMN(宏观数据!$F$32:$UN$32))-COLUMN(宏观数据!$F$32))),"") | I55: =IFERROR(LOOKUP(2,1/(宏观数据!$F$32:$UN$32<>"")/(宏观数据!$F$1:$UN$1<F55),宏观数据!$F$1:$UN$1),"")
A56: 万得一致预测:中国:社会融资规模存量:同比 | B56: 月度 | C56: X5100205 | D56: % | E56: =IFERROR(LOOKUP(9.99E+307,宏观数据!$F$34:$UN$34),"") -> 7.43 | F56: =IFERROR(LOOKUP(2,1/(宏观数据!$F$34:$UN$34<>""),宏观数据!$F$1:$UN$1),"") -> 46203 | G56: =IFERROR(E56-H56,"") -> -0.16 | H56: =IFERROR(LOOKUP(9.99E+307,OFFSET(宏观数据!$F$34,0,0,1,LOOKUP(2,1/(宏观数据!$F$34:$UN$34<>""),COLUMN(宏观数据!$F$34:$UN$34))-COLUMN(宏观数据!$F$34))),"") -> 7.59 | I56: =IFERROR(LOOKUP(2,1/(宏观数据!$F$34:$UN$34<>"")/(宏观数据!$F$1:$UN$1<F56),宏观数据!$F$1:$UN$1),"") -> 46173
A57: 中国:社会融资规模存量:未贴现银行承兑汇票:同比 | B57: 月度 | C57: M5525768 | D57: % | E57: =IFERROR(LOOKUP(9.99E+307,宏观数据!$F$36:$UN$36),"") -> -6.2 | F57: =IFERROR(LOOKUP(2,1/(宏观数据!$F$36:$UN$36<>""),宏观数据!$F$1:$UN$1),"") -> 46173 | G57: =IFERROR(E57-H57,"") -> 1.7 | H57: =IFERROR(LOOKUP(9.99E+307,OFFSET(宏观数据!$F$36,0,0,1,LOOKUP(2,1/(宏观数据!$F$36:$UN$36<>""),COLUMN(宏观数据!$F$36:$UN$36))-COLUMN(宏观数据!$F$36))),"") -> -7.9 | I57: =IFERROR(LOOKUP(2,1/(宏观数据!$F$36:$UN$36<>"")/(宏观数据!$F$1:$UN$1<F57),宏观数据!$F$1:$UN$1),"") -> 46142
A58: 中国:社会融资规模存量:政府债券:同比 | B58: 月度 | C58: M6179510 | D58: % | E58: =IFERROR(LOOKUP(9.99E+307,宏观数据!$F$38:$UN$38),"") -> 15.1 | F58: =IFERROR(LOOKUP(2,1/(宏观数据!$F$38:$UN$38<>""),宏观数据!$F$1:$UN$1),"") -> 46173 | G58: =IFERROR(E58-H58,"") -> -0.5 | H58: =IFERROR(LOOKUP(9.99E+307,OFFSET(宏观数据!$F$38,0,0,1,LOOKUP(2,1/(宏观数据!$F$38:$UN$38<>""),COLUMN(宏观数据!$F$38:$UN$38))-COLUMN(宏观数据!$F$38))),"") -> 15.6 | I58: =IFERROR(LOOKUP(2,1/(宏观数据!$F$38:$UN$38<>"")/(宏观数据!$F$1:$UN$1<F58),宏观数据!$F$1:$UN$1),"") -> 46142
A59: 万得一致预测:中国:M1:同比 | B59: 月度 | C59: Y0910594 | D59: % | E59: =IFERROR(LOOKUP(9.99E+307,宏观数据!$F$40:$UN$40),"") -> 3.8 | F59: =IFERROR(LOOKUP(2,1/(宏观数据!$F$40:$UN$40<>""),宏观数据!$F$1:$UN$1),"") -> 46265 | G59: =IFERROR(E59-H59,"") -> 0.1 | H59: =IFERROR(LOOKUP(9.99E+307,OFFSET(宏观数据!$F$40,0,0,1,LOOKUP(2,1/(宏观数据!$F$40:$UN$40<>""),COLUMN(宏观数据!$F$40:$UN$40))-COLUMN(宏观数据!$F$40))),"") -> 3.7 | I59: =IFERROR(LOOKUP(2,1/(宏观数据!$F$40:$UN$40<>"")/(宏观数据!$F$1:$UN$1<F59),宏观数据!$F$1:$UN$1),"") -> 46234
A60: 万得一致预测:中国:M2:同比 | B60: 月度 | C60: M0061683 | D60: % | E60: =IFERROR(LOOKUP(9.99E+307,宏观数据!$F$42:$UN$42),"") -> 8.48 | F60: =IFERROR(LOOKUP(2,1/(宏观数据!$F$42:$UN$42<>""),宏观数据!$F$1:$UN$1),"") -> 46203 | G60: =IFERROR(E60-H60,"") -> -0.07 | H60: =IFERROR(LOOKUP(9.99E+307,OFFSET(宏观数据!$F$42,0,0,1,LOOKUP(2,1/(宏观数据!$F$42:$UN$42<>""),COLUMN(宏观数据!$F$42:$UN$42))-COLUMN(宏观数据!$F$42))),"") -> 8.55 | I60: =IFERROR(LOOKUP(2,1/(宏观数据!$F$42:$UN$42<>"")/(宏观数据!$F$1:$UN$1<F60),宏观数据!$F$1:$UN$1),"") -> 46173
A61: 中国:公开市场操作:货币净投放 | B61: 月度 | C61: M0061614 | D61: 亿元 | E61: =IFERROR(LOOKUP(9.99E+307,宏观数据!$F$80:$UN$80),"") -> -15870 | F61: =IFERROR(LOOKUP(2,1/(宏观数据!$F$80:$UN$80<>""),宏观数据!$F$1:$UN$1),"") -> 46206 | G61: =IFERROR(E61-H61,"") -> -19167 | H61: =IFERROR(LOOKUP(9.99E+307,OFFSET(宏观数据!$F$80,0,0,1,LOOKUP(2,1/(宏观数据!$F$80:$UN$80<>""),COLUMN(宏观数据!$F$80:$UN$80))-COLUMN(宏观数据!$F$80))),"") -> 3297 | I61: =IFERROR(LOOKUP(2,1/(宏观数据!$F$80:$UN$80<>"")/(宏观数据!$F$1:$UN$1<F61),宏观数据!$F$1:$UN$1),"") -> 46199
A62: 中国:金融机构:新增人民币贷款:居民户:短期:当月值 | B62: 月度 | C62: M0057874 | D62: 亿元 | E62: =IFERROR(LOOKUP(9.99E+307,宏观数据!$F$100:$UN$100),"") -> -840 | F62: =IFERROR(LOOKUP(2,1/(宏观数据!$F$100:$UN$100<>""),宏观数据!$F$1:$UN$1),"") -> 46173 | G62: =IFERROR(E62-H62,"") -> 3622 | H62: =IFERROR(LOOKUP(9.99E+307,OFFSET(宏观数据!$F$100,0,0,1,LOOKUP(2,1/(宏观数据!$F$100:$UN$100<>""),COLUMN(宏观数据!$F$100:$UN$100))-COLUMN(宏观数据!$F$100))),"") -> -4462 | I62: =IFERROR(LOOKUP(2,1/(宏观数据!$F$100:$UN$100<>"")/(宏观数据!$F$1:$UN$1<F62),宏观数据!$F$1:$UN$1),"") -> 46142
A63: 中国:金融机构:新增人民币贷款:居民户:中长期:当月值 | B63: 月度 | C63: M0057875 | D63: 亿元 | E63: =IFERROR(LOOKUP(9.99E+307,宏观数据!$F$101:$UN$101),"") -> -571 | F63: =IFERROR(LOOKUP(2,1/(宏观数据!$F$101:$UN$101<>""),宏观数据!$F$1:$UN$1),"") -> 46173 | G63: =IFERROR(E63-H63,"") -> 2837 | H63: =IFERROR(LOOKUP(9.99E+307,OFFSET(宏观数据!$F$101,0,0,1,LOOKUP(2,1/(宏观数据!$F$101:$UN$101<>""),COLUMN(宏观数据!$F$101:$UN$101))-COLUMN(宏观数据!$F$101))),"") -> -3408 | I63: =IFERROR(LOOKUP(2,1/(宏观数据!$F$101:$UN$101<>"")/(宏观数据!$F$1:$UN$1<F63),宏观数据!$F$1:$UN$1),"") -> 46142
A64: 中国:金融机构:新增人民币贷款:居民户:累计值 | B64: 月度 | C64: M0048258 | D64: 亿元 | E64: =IFERROR(LOOKUP(9.99E+307,宏观数据!$F$102:$UN$102),"") -> -6314 | F64: =IFERROR(LOOKUP(2,1/(宏观数据!$F$102:$UN$102<>""),宏观数据!$F$1:$UN$1),"") -> 46173 | G64: =IFERROR(E64-H64,"") -> -1412 | H64: =IFERROR(LOOKUP(9.99E+307,OFFSET(宏观数据!$F$102,0,0,1,LOOKUP(2,1/(宏观数据!$F$102:$UN$102<>""),COLUMN(宏观数据!$F$102:$UN$102))-COLUMN(宏观数据!$F$102))),"") -> -4902 | I64: =IFERROR(LOOKUP(2,1/(宏观数据!$F$102:$UN$102<>"")/(宏观数据!$F$1:$UN$1<F64),宏观数据!$F$1:$UN$1),"") -> 46142
A65: 中国:金融机构:新增人民币贷款:企(事)业单位:中长期:当月值 | B65: 月度 | C65: M0057877 | D65: 亿元 | E65: =IFERROR(LOOKUP(9.99E+307,宏观数据!$F$103:$UN$103),"") -> -200 | F65: =IFERROR(LOOKUP(2,1/(宏观数据!$F$103:$UN$103<>""),宏观数据!$F$1:$UN$1),"") -> 46173 | G65: =IFERROR(E65-H65,"") -> 3900 | H65: =IFERROR(LOOKUP(9.99E+307,OFFSET(宏观数据!$F$103,0,0,1,LOOKUP(2,1/(宏观数据!$F$103:$UN$103<>""),COLUMN(宏观数据!$F$103:$UN$103))-COLUMN(宏观数据!$F$103))),"") -> -4100 | I65: =IFERROR(LOOKUP(2,1/(宏观数据!$F$103:$UN$103<>"")/(宏观数据!$F$1:$UN$1<F65),宏观数据!$F$1:$UN$1),"") -> 46142
A66: 中国:金融机构:新增人民币贷款:短期贷款及票据融资:累计值 | B66: 月度 | C66: M0048256 | D66: 亿元 | E66: =IFERROR(LOOKUP(9.99E+307,宏观数据!$F$104:$UN$104),"") -> 37757 | F66: =IFERROR(LOOKUP(2,1/(宏观数据!$F$104:$UN$104<>""),宏观数据!$F$1:$UN$1),"") -> 46173 | G66: =IFERROR(E66-H66,"") -> 5730 | H66: =IFERROR(LOOKUP(9.99E+307,OFFSET(宏观数据!$F$104,0,0,1,LOOKUP(2,1/(宏观数据!$F$104:$UN$104<>""),COLUMN(宏观数据!$F$104:$UN$104))-COLUMN(宏观数据!$F$104))),"") -> 32027 | I66: =IFERROR(LOOKUP(2,1/(宏观数据!$F$104:$UN$104<>"")/(宏观数据!$F$1:$UN$1<F66),宏观数据!$F$1:$UN$1),"") -> 46142
A67: CFETS人民币汇率指数 | B67: 日度 | C67: M0325601 | D67: 点 | E67: =IFERROR(LOOKUP(9.99E+307,宏观数据!$F$109:$UN$109),"") -> 102.65 | F67: =IFERROR(LOOKUP(2,1/(宏观数据!$F$109:$UN$109<>""),宏观数据!$F$1:$UN$1),"") -> 46206 | G67: =IFERROR(E67-H67,"") -> 0.06 | H67: =IFERROR(LOOKUP(9.99E+307,OFFSET(宏观数据!$F$109,0,0,1,LOOKUP(2,1/(宏观数据!$F$109:$UN$109<>""),COLUMN(宏观数据!$F$109:$UN$109))-COLUMN(宏观数据!$F$109))),"") -> 102.59 | I67: =IFERROR(LOOKUP(2,1/(宏观数据!$F$109:$UN$109<>"")/(宏观数据!$F$1:$UN$1<F67),宏观数据!$F$1:$UN$1),"") -> 46203
A68: 财政赤字脉冲 | B68: 月度 | C68: M0046168-M0046166/M0001395 | D68: % | E68: =IFERROR(LOOKUP(9.99E+307,宏观数据!$F$177:$UN$177),"") -> -0.95671581 | F68: =IFERROR(LOOKUP(2,1/(宏观数据!$F$177:$UN$177<>""),宏观数据!$F$1:$UN$1),"") -> 46173 | G68: =IFERROR(E68-H68,"") -> -0.14316497 | H68: =IFERROR(LOOKUP(9.99E+307,OFFSET(宏观数据!$F$177,0,0,1,LOOKUP(2,1/(宏观数据!$F$177:$UN$177<>""),COLUMN(宏观数据!$F$177:$UN$177))-COLUMN(宏观数据!$F$177))),"") -> -0.81355084 | I68: =IFERROR(LOOKUP(2,1/(宏观数据!$F$177:$UN$177<>"")/(宏观数据!$F$1:$UN$1<F68),宏观数据!$F$1:$UN$1),"") -> 46142
A69: 中国:银行结售汇差额:当月值 | B69: 月度 | C69: M5207849 | D69: 亿美元 | E69: =IFERROR(LOOKUP(9.99E+307,宏观数据!$F$147:$UN$147),"") -> 357.9242 | F69: =IFERROR(LOOKUP(2,1/(宏观数据!$F$147:$UN$147<>""),宏观数据!$F$1:$UN$1),"") -> 46173 | G69: =IFERROR(E69-H69,"") -> -42.8748 | H69: =IFERROR(LOOKUP(9.99E+307,OFFSET(宏观数据!$F$147,0,0,1,LOOKUP(2,1/(宏观数据!$F$147:$UN$147<>""),COLUMN(宏观数据!$F$147:$UN$147))-COLUMN(宏观数据!$F$147))),"") -> 400.799 | I69: =IFERROR(LOOKUP(2,1/(宏观数据!$F$147:$UN$147<>"")/(宏观数据!$F$1:$UN$1<F69),宏观数据!$F$1:$UN$1),"") -> 46142
A70: 中国:居民部门杠杆率 | B70: 季度 | C70: M6404533 | D70: % | E70: =IFERROR(LOOKUP(9.99E+307,宏观数据!$F$152:$UN$152),"") -> 59 | F70: =IFERROR(LOOKUP(2,1/(宏观数据!$F$152:$UN$152<>""),宏观数据!$F$1:$UN$1),"") -> 46112 | G70: =IFERROR(E70-H70,"") -> -0.4 | H70: =IFERROR(LOOKUP(9.99E+307,OFFSET(宏观数据!$F$152,0,0,1,LOOKUP(2,1/(宏观数据!$F$152:$UN$152<>""),COLUMN(宏观数据!$F$152:$UN$152))-COLUMN(宏观数据!$F$152))),"") -> 59.4 | I70: =IFERROR(LOOKUP(2,1/(宏观数据!$F$152:$UN$152<>"")/(宏观数据!$F$1:$UN$1<F70),宏观数据!$F$1:$UN$1),"") -> 46022
A71: 中国:政府部门杠杆率 | B71: 季度 | C71: M6404535 | D71: % | E71: =IFERROR(LOOKUP(9.99E+307,宏观数据!$F$153:$UN$153),"") -> 70.3 | F71: =IFERROR(LOOKUP(2,1/(宏观数据!$F$153:$UN$153<>""),宏观数据!$F$1:$UN$1),"") -> 46112 | G71: =IFERROR(E71-H71,"") -> 1.9 | H71: =IFERROR(LOOKUP(9.99E+307,OFFSET(宏观数据!$F$153,0,0,1,LOOKUP(2,1/(宏观数据!$F$153:$UN$153<>""),COLUMN(宏观数据!$F$153:$UN$153))-COLUMN(宏观数据!$F$153))),"") -> 68.4 | I71: =IFERROR(LOOKUP(2,1/(宏观数据!$F$153:$UN$153<>"")/(宏观数据!$F$1:$UN$1<F71),宏观数据!$F$1:$UN$1),"") -> 46022
A72: 中国:非金融企业部门杠杆率 | B72: 季度 | C72: M6404534 | D72: % | E72: =IFERROR(LOOKUP(9.99E+307,宏观数据!$F$154:$UN$154),"") -> 180 | F72: =IFERROR(LOOKUP(2,1/(宏观数据!$F$154:$UN$154<>""),宏观数据!$F$1:$UN$1),"") -> 46112 | G72: =IFERROR(E72-H72,"") -> 5.4 | H72: =IFERROR(LOOKUP(9.99E+307,OFFSET(宏观数据!$F$154,0,0,1,LOOKUP(2,1/(宏观数据!$F$154:$UN$154<>""),COLUMN(宏观数据!$F$154:$UN$154))-COLUMN(宏观数据!$F$154))),"") -> 174.6 | I72: =IFERROR(LOOKUP(2,1/(宏观数据!$F$154:$UN$154<>"")/(宏观数据!$F$1:$UN$1<F72),宏观数据!$F$1:$UN$1),"") -> 46022
A73: 中国:公共财政收入:累计值 | B73: 月度 | C73: M0046168 | D73: 亿元 | E73: =IFERROR(LOOKUP(9.99E+307,宏观数据!$F$144:$UN$144),"") -> 100465 | F73: =IFERROR(LOOKUP(2,1/(宏观数据!$F$144:$UN$144<>""),宏观数据!$F$1:$UN$1),"") -> 46173 | G73: =IFERROR(E73-H73,"") -> 17061 | H73: =IFERROR(LOOKUP(9.99E+307,OFFSET(宏观数据!$F$144,0,0,1,LOOKUP(2,1/(宏观数据!$F$144:$UN$144<>""),COLUMN(宏观数据!$F$144:$UN$144))-COLUMN(宏观数据!$F$144))),"") -> 83404 | I73: =IFERROR(LOOKUP(2,1/(宏观数据!$F$144:$UN$144<>"")/(宏观数据!$F$1:$UN$1<F73),宏观数据!$F$1:$UN$1),"") -> 46142
A74: 中国:公共财政支出:累计同比 | B74: 月度 | C74: M0046167 | D74: % | E74: =IFERROR(LOOKUP(9.99E+307,宏观数据!$F$157:$UN$157),"") -> 0.8 | F74: =IFERROR(LOOKUP(2,1/(宏观数据!$F$157:$UN$157<>""),宏观数据!$F$1:$UN$1),"") -> 46173 | G74: =IFERROR(E74-H74,"") -> -0.5 | H74: =IFERROR(LOOKUP(9.99E+307,OFFSET(宏观数据!$F$157,0,0,1,LOOKUP(2,1/(宏观数据!$F$157:$UN$157<>""),COLUMN(宏观数据!$F$157:$UN$157))-COLUMN(宏观数据!$F$157))),"") -> 1.3 | I74: =IFERROR(LOOKUP(2,1/(宏观数据!$F$157:$UN$157<>"")/(宏观数据!$F$1:$UN$1<F74),宏观数据!$F$1:$UN$1),"") -> 46142
A75: 中国:地方政府性基金收入:国有土地使用权出让收入:累计同比 | B75: 月度 | C75: M0096886 | D75: % | E75: =IFERROR(LOOKUP(9.99E+307,宏观数据!$F$158:$UN$158),"") -> -28.7 | F75: =IFERROR(LOOKUP(2,1/(宏观数据!$F$158:$UN$158<>""),宏观数据!$F$1:$UN$1),"") -> 46173 | G75: =IFERROR(E75-H75,"") -> -1.5 | H75: =IFERROR(LOOKUP(9.99E+307,OFFSET(宏观数据!$F$158,0,0,1,LOOKUP(2,1/(宏观数据!$F$158:$UN$158<>""),COLUMN(宏观数据!$F$158:$UN$158))-COLUMN(宏观数据!$F$158))),"") -> -27.2 | I75: =IFERROR(LOOKUP(2,1/(宏观数据!$F$158:$UN$158<>"")/(宏观数据!$F$1:$UN$1<F75),宏观数据!$F$1:$UN$1),"") -> 46142
A76: 中国:中央政府债务余额 | B76: 月度 | C76: M5567950 | D76: 亿元 | E76: =IFERROR(LOOKUP(9.99E+307,宏观数据!$F$159:$UN$159),"") -> 42349.8 | F76: =IFERROR(LOOKUP(2,1/(宏观数据!$F$159:$UN$159<>""),宏观数据!$F$1:$UN$1),"") -> 46112 | G76: =IFERROR(E76-H76,"") -> 1118 | H76: =IFERROR(LOOKUP(9.99E+307,OFFSET(宏观数据!$F$159,0,0,1,LOOKUP(2,1/(宏观数据!$F$159:$UN$159<>""),COLUMN(宏观数据!$F$159:$UN$159))-COLUMN(宏观数据!$F$159))),"") -> 41231.8 | I76: =IFERROR(LOOKUP(2,1/(宏观数据!$F$159:$UN$159<>"")/(宏观数据!$F$1:$UN$1<F76),宏观数据!$F$1:$UN$1),"") -> 46022
A77: 中国:财政赤字率 (赤字/GDP) | B77: 年度 | C77: M5405502 | D77: % | E77: =IFERROR(LOOKUP(9.99E+307,宏观数据!$F$160:$UN$160),"") -> 4 | F77: =IFERROR(LOOKUP(2,1/(宏观数据!$F$160:$UN$160<>""),宏观数据!$F$1:$UN$1),"") -> 46022 | G77: =IFERROR(E77-H77,"") | H77: =IFERROR(LOOKUP(9.99E+307,OFFSET(宏观数据!$F$160,0,0,1,LOOKUP(2,1/(宏观数据!$F$160:$UN$160<>""),COLUMN(宏观数据!$F$160:$UN$160))-COLUMN(宏观数据!$F$160))),"") | I77: =IFERROR(LOOKUP(2,1/(宏观数据!$F$160:$UN$160<>"")/(宏观数据!$F$1:$UN$1<F77),宏观数据!$F$1:$UN$1),"")
A78: GDP总量：中国 | B78: 季度 | C78: M5567876 | D78: 亿元 | E78: =IFERROR(LOOKUP(9.99E+307,宏观数据!$F$162:$UN$162),"") -> 334192.9 | F78: =IFERROR(LOOKUP(2,1/(宏观数据!$F$162:$UN$162<>""),宏观数据!$F$1:$UN$1),"") -> 46112 | G78: =IFERROR(E78-H78,"") -> -53718.4 | H78: =IFERROR(LOOKUP(9.99E+307,OFFSET(宏观数据!$F$162,0,0,1,LOOKUP(2,1/(宏观数据!$F$162:$UN$162<>""),COLUMN(宏观数据!$F$162:$UN$162))-COLUMN(宏观数据!$F$162))),"") -> 387911.3 | I78: =IFERROR(LOOKUP(2,1/(宏观数据!$F$162:$UN$162<>"")/(宏观数据!$F$1:$UN$1<F78),宏观数据!$F$1:$UN$1),"") -> 46022
A79: 中国:GDP累计同比贡献率:最终消费支出:支出法 | B79: 季度 | C79: M6001128 | D79: % | E79: =IFERROR(LOOKUP(9.99E+307,宏观数据!$F$163:$UN$163),"") -> 46.7 | F79: =IFERROR(LOOKUP(2,1/(宏观数据!$F$163:$UN$163<>""),宏观数据!$F$1:$UN$1),"") -> 46112 | G79: =IFERROR(E79-H79,"") -> -5.3 | H79: =IFERROR(LOOKUP(9.99E+307,OFFSET(宏观数据!$F$163,0,0,1,LOOKUP(2,1/(宏观数据!$F$163:$UN$163<>""),COLUMN(宏观数据!$F$163:$UN$163))-COLUMN(宏观数据!$F$163))),"") -> 52 | I79: =IFERROR(LOOKUP(2,1/(宏观数据!$F$163:$UN$163<>"")/(宏观数据!$F$1:$UN$1<F79),宏观数据!$F$1:$UN$1),"") -> 46022
A80: 中国:GDP累计同比贡献率:资本形成总额:支出法 | B80: 季度 | C80: M6001129 | D80: % | E80: =IFERROR(LOOKUP(9.99E+307,宏观数据!$F$164:$UN$164),"") -> 38 | F80: =IFERROR(LOOKUP(2,1/(宏观数据!$F$164:$UN$164<>""),宏观数据!$F$1:$UN$1),"") -> 46112 | G80: =IFERROR(E80-H80,"") -> 22.7 | H80: =IFERROR(LOOKUP(9.99E+307,OFFSET(宏观数据!$F$164,0,0,1,LOOKUP(2,1/(宏观数据!$F$164:$UN$164<>""),COLUMN(宏观数据!$F$164:$UN$164))-COLUMN(宏观数据!$F$164))),"") -> 15.3 | I80: =IFERROR(LOOKUP(2,1/(宏观数据!$F$164:$UN$164<>"")/(宏观数据!$F$1:$UN$1<F80),宏观数据!$F$1:$UN$1),"") -> 46022
A81: 中国:GDP累计同比贡献率:货物和服务净出口:支出法 | B81: 季度 | C81: M6001130 | D81: % | E81: =IFERROR(LOOKUP(9.99E+307,宏观数据!$F$165:$UN$165),"") -> 15.3 | F81: =IFERROR(LOOKUP(2,1/(宏观数据!$F$165:$UN$165<>""),宏观数据!$F$1:$UN$1),"") -> 46112 | G81: =IFERROR(E81-H81,"") -> -17.4 | H81: =IFERROR(LOOKUP(9.99E+307,OFFSET(宏观数据!$F$165,0,0,1,LOOKUP(2,1/(宏观数据!$F$165:$UN$165<>""),COLUMN(宏观数据!$F$165:$UN$165))-COLUMN(宏观数据!$F$165))),"") -> 32.7 | I81: =IFERROR(LOOKUP(2,1/(宏观数据!$F$165:$UN$165<>"")/(宏观数据!$F$1:$UN$1<F81),宏观数据!$F$1:$UN$1),"") -> 46022
A82: 中国:房地产开发投资完成额:累计同比 | B82: 月度 | C82: S0029657 | D82: % | E82: =IFERROR(LOOKUP(9.99E+307,宏观数据!$F$166:$UN$166),"") -> -16.2 | F82: =IFERROR(LOOKUP(2,1/(宏观数据!$F$166:$UN$166<>""),宏观数据!$F$1:$UN$1),"") -> 46173 | G82: =IFERROR(E82-H82,"") -> -2.5 | H82: =IFERROR(LOOKUP(9.99E+307,OFFSET(宏观数据!$F$166,0,0,1,LOOKUP(2,1/(宏观数据!$F$166:$UN$166<>""),COLUMN(宏观数据!$F$166:$UN$166))-COLUMN(宏观数据!$F$166))),"") -> -13.7 | I82: =IFERROR(LOOKUP(2,1/(宏观数据!$F$166:$UN$166<>"")/(宏观数据!$F$1:$UN$1<F82),宏观数据!$F$1:$UN$1),"") -> 46142
A83: 中国:出口金额:美国:累计同比 | B83: 月度 | C83: M0008499 | D83: % | E83: =IFERROR(LOOKUP(9.99E+307,宏观数据!$F$167:$UN$167),"") -> -2.7 | F83: =IFERROR(LOOKUP(2,1/(宏观数据!$F$167:$UN$167<>""),宏观数据!$F$1:$UN$1),"") -> 46173 | G83: =IFERROR(E83-H83,"") -> 7.5 | H83: =IFERROR(LOOKUP(9.99E+307,OFFSET(宏观数据!$F$167,0,0,1,LOOKUP(2,1/(宏观数据!$F$167:$UN$167<>""),COLUMN(宏观数据!$F$167:$UN$167))-COLUMN(宏观数据!$F$167))),"") -> -10.2 | I83: =IFERROR(LOOKUP(2,1/(宏观数据!$F$167:$UN$167<>"")/(宏观数据!$F$1:$UN$1<F83),宏观数据!$F$1:$UN$1),"") -> 46142
A84: 中国:出口金额:东南亚国家联盟:累计同比 | B84: 月度 | C84: M0007911 | D84: % | E84: =IFERROR(LOOKUP(9.99E+307,宏观数据!$F$168:$UN$168),"") -> 20.3 | F84: =IFERROR(LOOKUP(2,1/(宏观数据!$F$168:$UN$168<>""),宏观数据!$F$1:$UN$1),"") -> 46173 | G84: =IFERROR(E84-H84,"") -> 1.2 | H84: =IFERROR(LOOKUP(9.99E+307,OFFSET(宏观数据!$F$168,0,0,1,LOOKUP(2,1/(宏观数据!$F$168:$UN$168<>""),COLUMN(宏观数据!$F$168:$UN$168))-COLUMN(宏观数据!$F$168))),"") -> 19.1 | I84: =IFERROR(LOOKUP(2,1/(宏观数据!$F$168:$UN$168<>"")/(宏观数据!$F$1:$UN$1<F84),宏观数据!$F$1:$UN$1),"") -> 46142
A85: 进出口：中国:贸易差额 | B85: 月度 | C85: M0000610 | D85: 亿美元 | E85: =IFERROR(LOOKUP(9.99E+307,宏观数据!$F$169:$UN$169),"") -> 1054.3358 | F85: =IFERROR(LOOKUP(2,1/(宏观数据!$F$169:$UN$169<>""),宏观数据!$F$1:$UN$1),"") -> 46173 | G85: =IFERROR(E85-H85,"") -> 207.47813 | H85: =IFERROR(LOOKUP(9.99E+307,OFFSET(宏观数据!$F$169,0,0,1,LOOKUP(2,1/(宏观数据!$F$169:$UN$169<>""),COLUMN(宏观数据!$F$169:$UN$169))-COLUMN(宏观数据!$F$169))),"") -> 846.85771 | I85: =IFERROR(LOOKUP(2,1/(宏观数据!$F$169:$UN$169<>"")/(宏观数据!$F$1:$UN$1<F85),宏观数据!$F$1:$UN$1),"") -> 46142
A86: 中国:农产品批发价格指数:猪肉 | B86: 日度 | C86: V6842305 | D86: 点 | E86: =IFERROR(LOOKUP(9.99E+307,宏观数据!$F$170:$UN$170),"") -> 79.58 | F86: =IFERROR(LOOKUP(2,1/(宏观数据!$F$170:$UN$170<>""),宏观数据!$F$1:$UN$1),"") -> 46206 | G86: =IFERROR(E86-H86,"") -> 1.12 | H86: =IFERROR(LOOKUP(9.99E+307,OFFSET(宏观数据!$F$170,0,0,1,LOOKUP(2,1/(宏观数据!$F$170:$UN$170<>""),COLUMN(宏观数据!$F$170:$UN$170))-COLUMN(宏观数据!$F$170))),"") -> 78.46 | I86: =IFERROR(LOOKUP(2,1/(宏观数据!$F$170:$UN$170<>"")/(宏观数据!$F$1:$UN$1<F86),宏观数据!$F$1:$UN$1),"") -> 46205
A87: 中国:产成品存货:规模以上工业企业:同比 | B87: 月度 | C87: M0000561 | D87: % | E87: =IFERROR(LOOKUP(9.99E+307,宏观数据!$F$171:$UN$171),"") -> 8.8 | F87: =IFERROR(LOOKUP(2,1/(宏观数据!$F$171:$UN$171<>""),宏观数据!$F$1:$UN$1),"") -> 46173 | G87: =IFERROR(E87-H87,"") -> 2.1 | H87: =IFERROR(LOOKUP(9.99E+307,OFFSET(宏观数据!$F$171,0,0,1,LOOKUP(2,1/(宏观数据!$F$171:$UN$171<>""),COLUMN(宏观数据!$F$171:$UN$171))-COLUMN(宏观数据!$F$171))),"") -> 6.7 | I87: =IFERROR(LOOKUP(2,1/(宏观数据!$F$171:$UN$171<>"")/(宏观数据!$F$1:$UN$1<F87),宏观数据!$F$1:$UN$1),"") -> 46142
A88: 中国:利润总额:制造业:累计同比 | B88: 月度 | C88: S0206721 | D88: % | E88: =IFERROR(LOOKUP(9.99E+307,宏观数据!$F$172:$UN$172),"") -> 20 | F88: =IFERROR(LOOKUP(2,1/(宏观数据!$F$172:$UN$172<>""),宏观数据!$F$1:$UN$1),"") -> 46173 | G88: =IFERROR(E88-H88,"") -> -0.4 | H88: =IFERROR(LOOKUP(9.99E+307,OFFSET(宏观数据!$F$172,0,0,1,LOOKUP(2,1/(宏观数据!$F$172:$UN$172<>""),COLUMN(宏观数据!$F$172:$UN$172))-COLUMN(宏观数据!$F$172))),"") -> 20.4 | I88: =IFERROR(LOOKUP(2,1/(宏观数据!$F$172:$UN$172<>"")/(宏观数据!$F$1:$UN$1<F88),宏观数据!$F$1:$UN$1),"") -> 46142
A89: 中国:金融机构:新增人民币存款:财政存款:累计值 | B89: 月度 | C89: M0048264 | D89: 亿元 | E89: =IFERROR(LOOKUP(9.99E+307,宏观数据!$F$173:$UN$173),"") -> 19100 | F89: =IFERROR(LOOKUP(2,1/(宏观数据!$F$173:$UN$173<>""),宏观数据!$F$1:$UN$1),"") -> 46173 | G89: =IFERROR(E89-H89,"") -> 7100 | H89: =IFERROR(LOOKUP(9.99E+307,OFFSET(宏观数据!$F$173,0,0,1,LOOKUP(2,1/(宏观数据!$F$173:$UN$173<>""),COLUMN(宏观数据!$F$173:$UN$173))-COLUMN(宏观数据!$F$173))),"") -> 12000 | I89: =IFERROR(LOOKUP(2,1/(宏观数据!$F$173:$UN$173<>"")/(宏观数据!$F$1:$UN$1<F89),宏观数据!$F$1:$UN$1),"") -> 46142
A90: 中国:社会消费品零售总额:当月值 | B90: 月度 | C90: M0001427 | D90: 亿元 | E90: =IFERROR(LOOKUP(9.99E+307,宏观数据!$F$174:$UN$174),"") -> 41090 | F90: =IFERROR(LOOKUP(2,1/(宏观数据!$F$174:$UN$174<>""),宏观数据!$F$1:$UN$1),"") -> 46173 | G90: =IFERROR(E90-H90,"") -> 3843.5 | H90: =IFERROR(LOOKUP(9.99E+307,OFFSET(宏观数据!$F$174,0,0,1,LOOKUP(2,1/(宏观数据!$F$174:$UN$174<>""),COLUMN(宏观数据!$F$174:$UN$174))-COLUMN(宏观数据!$F$174))),"") -> 37246.5 | I90: =IFERROR(LOOKUP(2,1/(宏观数据!$F$174:$UN$174<>"")/(宏观数据!$F$1:$UN$1<F90),宏观数据!$F$1:$UN$1),"") -> 46142
A91: 中国:GDP:不变价:当季同比 | B91: 季度 | C91: M0039354 | D91: % | E91: =IFERROR(LOOKUP(9.99E+307,宏观数据!$F$175:$UN$175),"") -> 5 | F91: =IFERROR(LOOKUP(2,1/(宏观数据!$F$175:$UN$175<>""),宏观数据!$F$1:$UN$1),"") -> 46112 | G91: =IFERROR(E91-H91,"") -> 0.5 | H91: =IFERROR(LOOKUP(9.99E+307,OFFSET(宏观数据!$F$175,0,0,1,LOOKUP(2,1/(宏观数据!$F$175:$UN$175<>""),COLUMN(宏观数据!$F$175:$UN$175))-COLUMN(宏观数据!$F$175))),"") -> 4.5 | I91: =IFERROR(LOOKUP(2,1/(宏观数据!$F$175:$UN$175<>"")/(宏观数据!$F$1:$UN$1<F91),宏观数据!$F$1:$UN$1),"") -> 46022

Sheet 海外数据
B1: 频率 | C1: 代码 | D1: 单位 | E1: 当前数据 | F1: 数据日期 | G1: 变化 | H1: 上期数据 | I1: 上期日期 | J1: 趋势图
A2: 美国:国债收益率:2年 | B2: 日度 | C2: G0000887 | D2: % | E2: =IFERROR(LOOKUP(9.99E+307,宏观数据!$F$57:$UN$57),"") -> 4.14 | F2: =IFERROR(LOOKUP(2,1/(宏观数据!$F$57:$UN$57<>""),宏观数据!$F$1:$UN$1),"") -> 46205 | G2: =IFERROR(E2-H2,"") -> -0.03 | H2: =IFERROR(LOOKUP(9.99E+307,OFFSET(宏观数据!$F$57,0,0,1,LOOKUP(2,1/(宏观数据!$F$57:$UN$57<>""),COLUMN(宏观数据!$F$57:$UN$57))-COLUMN(宏观数据!$F$57))),"") -> 4.17 | I2: =IFERROR(LOOKUP(2,1/(宏观数据!$F$57:$UN$57<>"")/(宏观数据!$F$1:$UN$1<F2),宏观数据!$F$1:$UN$1),"") -> 46204
A3: 美国:国债收益率:10年 | B3: 日度 | C3: G0000891 | D3: % | E3: =IFERROR(LOOKUP(9.99E+307,宏观数据!$F$58:$UN$58),"") -> 4.49 | F3: =IFERROR(LOOKUP(2,1/(宏观数据!$F$58:$UN$58<>""),宏观数据!$F$1:$UN$1),"") -> 46205 | G3: =IFERROR(E3-H3,"") -> 0.01 | H3: =IFERROR(LOOKUP(9.99E+307,OFFSET(宏观数据!$F$58,0,0,1,LOOKUP(2,1/(宏观数据!$F$58:$UN$58<>""),COLUMN(宏观数据!$F$58:$UN$58))-COLUMN(宏观数据!$F$58))),"") -> 4.48 | I3: =IFERROR(LOOKUP(2,1/(宏观数据!$F$58:$UN$58<>"")/(宏观数据!$F$1:$UN$1<F3),宏观数据!$F$1:$UN$1),"") -> 46204
A4: 美元指数 | B4: 日度 | C4: M0000271 | D4: 点 | E4: =IFERROR(LOOKUP(9.99E+307,宏观数据!$F$59:$UN$59),"") -> 100.8749 | F4: =IFERROR(LOOKUP(2,1/(宏观数据!$F$59:$UN$59<>""),宏观数据!$F$1:$UN$1),"") -> 46206 | G4: =IFERROR(E4-H4,"") -> 0.0097 | H4: =IFERROR(LOOKUP(9.99E+307,OFFSET(宏观数据!$F$59,0,0,1,LOOKUP(2,1/(宏观数据!$F$59:$UN$59<>""),COLUMN(宏观数据!$F$59:$UN$59))-COLUMN(宏观数据!$F$59))),"") -> 100.8652 | I4: =IFERROR(LOOKUP(2,1/(宏观数据!$F$59:$UN$59<>"")/(宏观数据!$F$1:$UN$1<F4),宏观数据!$F$1:$UN$1),"") -> 46205
A5: 美国:CPI:非季调:同比 | B5: 月度 | C5: G0000027 | D5: % | E5: =IFERROR(LOOKUP(9.99E+307,宏观数据!$F$60:$UN$60),"") -> 4.2 | F5: =IFERROR(LOOKUP(2,1/(宏观数据!$F$60:$UN$60<>""),宏观数据!$F$1:$UN$1),"") -> 46173 | G5: =IFERROR(E5-H5,"") -> 0.4 | H5: =IFERROR(LOOKUP(9.99E+307,OFFSET(宏观数据!$F$60,0,0,1,LOOKUP(2,1/(宏观数据!$F$60:$UN$60<>""),COLUMN(宏观数据!$F$60:$UN$60))-COLUMN(宏观数据!$F$60))),"") -> 3.8 | I5: =IFERROR(LOOKUP(2,1/(宏观数据!$F$60:$UN$60<>"")/(宏观数据!$F$1:$UN$1<F5),宏观数据!$F$1:$UN$1),"") -> 46142
A6: 黄金ETF波动率指数 | B6: 日度 | C6: G1122642 | D6: 点 | E6: =IFERROR(LOOKUP(9.99E+307,宏观数据!$F$61:$UN$61),"") -> 26 | F6: =IFERROR(LOOKUP(2,1/(宏观数据!$F$61:$UN$61<>""),宏观数据!$F$1:$UN$1),"") -> 46205 | G6: =IFERROR(E6-H6,"") -> -1.12 | H6: =IFERROR(LOOKUP(9.99E+307,OFFSET(宏观数据!$F$61,0,0,1,LOOKUP(2,1/(宏观数据!$F$61:$UN$61<>""),COLUMN(宏观数据!$F$61:$UN$61))-COLUMN(宏观数据!$F$61))),"") -> 27.12 | I6: =IFERROR(LOOKUP(2,1/(宏观数据!$F$61:$UN$61<>"")/(宏观数据!$F$1:$UN$1<F6),宏观数据!$F$1:$UN$1),"") -> 46204
A7: CFETS:即期汇率:美元兑人民币 | B7: 日度 | C7: M0067855 | E7: =IFERROR(LOOKUP(9.99E+307,宏观数据!$F$62:$UN$62),"") -> 6.7804 | F7: =IFERROR(LOOKUP(2,1/(宏观数据!$F$62:$UN$62<>""),宏观数据!$F$1:$UN$1),"") -> 46206 | G7: =IFERROR(E7-H7,"") -> -0.0062 | H7: =IFERROR(LOOKUP(9.99E+307,OFFSET(宏观数据!$F$62,0,0,1,LOOKUP(2,1/(宏观数据!$F$62:$UN$62<>""),COLUMN(宏观数据!$F$62:$UN$62))-COLUMN(宏观数据!$F$62))),"") -> 6.7866 | I7: =IFERROR(LOOKUP(2,1/(宏观数据!$F$62:$UN$62<>"")/(宏观数据!$F$1:$UN$1<F7),宏观数据!$F$1:$UN$1),"") -> 46205
A8: 美国:PPI:最终需求:非季调:同比 | B8: 月度 | C8: G1138811 | D8: % | E8: =IFERROR(LOOKUP(9.99E+307,宏观数据!$F$63:$UN$63),"") -> 6.5 | F8: =IFERROR(LOOKUP(2,1/(宏观数据!$F$63:$UN$63<>""),宏观数据!$F$1:$UN$1),"") -> 46173 | G8: =IFERROR(E8-H8,"") -> 0.8 | H8: =IFERROR(LOOKUP(9.99E+307,OFFSET(宏观数据!$F$63,0,0,1,LOOKUP(2,1/(宏观数据!$F$63:$UN$63<>""),COLUMN(宏观数据!$F$63:$UN$63))-COLUMN(宏观数据!$F$63))),"") -> 5.7 | I8: =IFERROR(LOOKUP(2,1/(宏观数据!$F$63:$UN$63<>"")/(宏观数据!$F$1:$UN$1<F8),宏观数据!$F$1:$UN$1),"") -> 46142
A9: 美国:核心PCE:同比 | B9: 月度 | C9: G1100005 | D9: % | E9: =IFERROR(LOOKUP(9.99E+307,宏观数据!$F$64:$UN$64),"") -> 3.412 | F9: =IFERROR(LOOKUP(2,1/(宏观数据!$F$64:$UN$64<>""),宏观数据!$F$1:$UN$1),"") -> 46173 | G9: =IFERROR(E9-H9,"") -> 0.0933 | H9: =IFERROR(LOOKUP(9.99E+307,OFFSET(宏观数据!$F$64,0,0,1,LOOKUP(2,1/(宏观数据!$F$64:$UN$64<>""),COLUMN(宏观数据!$F$64:$UN$64))-COLUMN(宏观数据!$F$64))),"") -> 3.3187 | I9: =IFERROR(LOOKUP(2,1/(宏观数据!$F$64:$UN$64<>"")/(宏观数据!$F$1:$UN$1<F9),宏观数据!$F$1:$UN$1),"") -> 46142
A10: 美国:所有联储银行:资产:总资产 | B10: 月度 | C10: G1100075 | D10: 亿美元 | E10: =IFERROR(LOOKUP(9.99E+307,宏观数据!$F$65:$UN$65),"") -> 6724564 | F10: =IFERROR(LOOKUP(2,1/(宏观数据!$F$65:$UN$65<>""),宏观数据!$F$1:$UN$1),"") -> 46204 | G10: =IFERROR(E10-H10,"") -> -11081 | H10: =IFERROR(LOOKUP(9.99E+307,OFFSET(宏观数据!$F$65,0,0,1,LOOKUP(2,1/(宏观数据!$F$65:$UN$65<>""),COLUMN(宏观数据!$F$65:$UN$65))-COLUMN(宏观数据!$F$65))),"") -> 6735645 | I10: =IFERROR(LOOKUP(2,1/(宏观数据!$F$65:$UN$65<>"")/(宏观数据!$F$1:$UN$1<F10),宏观数据!$F$1:$UN$1),"") -> 46197
A11: 美国:国债未偿余额:适销国债 | B11: 月度 | C11: G1133075 | E11: =IFERROR(LOOKUP(9.99E+307,宏观数据!$F$66:$UN$66),"") -> 30909.941 | F11: =IFERROR(LOOKUP(2,1/(宏观数据!$F$66:$UN$66<>""),宏观数据!$F$1:$UN$1),"") -> 46173 | G11: =IFERROR(E11-H11,"") -> 236.82978 | H11: =IFERROR(LOOKUP(9.99E+307,OFFSET(宏观数据!$F$66,0,0,1,LOOKUP(2,1/(宏观数据!$F$66:$UN$66<>""),COLUMN(宏观数据!$F$66:$UN$66))-COLUMN(宏观数据!$F$66))),"") -> 30673.112 | I11: =IFERROR(LOOKUP(2,1/(宏观数据!$F$66:$UN$66<>"")/(宏观数据!$F$1:$UN$1<F11),宏观数据!$F$1:$UN$1),"") -> 46142
A12: 美国:有效联邦基金利率(EFFR) | B12: 日度 | C12: G0001699 | D12: % | E12: =IFERROR(LOOKUP(9.99E+307,宏观数据!$F$67:$UN$67),"") -> 3.63 | F12: =IFERROR(LOOKUP(2,1/(宏观数据!$F$67:$UN$67<>""),宏观数据!$F$1:$UN$1),"") -> 46204 | G12: =IFERROR(E12-H12,"") -> 0 | H12: =IFERROR(LOOKUP(9.99E+307,OFFSET(宏观数据!$F$67,0,0,1,LOOKUP(2,1/(宏观数据!$F$67:$UN$67<>""),COLUMN(宏观数据!$F$67:$UN$67))-COLUMN(宏观数据!$F$67))),"") -> 3.63 | I12: =IFERROR(LOOKUP(2,1/(宏观数据!$F$67:$UN$67<>"")/(宏观数据!$F$1:$UN$1<F12),宏观数据!$F$1:$UN$1),"") -> 46203
A13: 美国担保隔夜融资利率(SOFR) | B13: 周度 | C13: M0341926 | D13: % | E13: =IFERROR(LOOKUP(9.99E+307,宏观数据!$F$68:$UN$68),"") -> 3.66 | F13: =IFERROR(LOOKUP(2,1/(宏观数据!$F$68:$UN$68<>""),宏观数据!$F$1:$UN$1),"") -> 46204 | G13: =IFERROR(E13-H13,"") -> -0.02 | H13: =IFERROR(LOOKUP(9.99E+307,OFFSET(宏观数据!$F$68,0,0,1,LOOKUP(2,1/(宏观数据!$F$68:$UN$68<>""),COLUMN(宏观数据!$F$68:$UN$68))-COLUMN(宏观数据!$F$68))),"") -> 3.68 | I13: =IFERROR(LOOKUP(2,1/(宏观数据!$F$68:$UN$68<>"")/(宏观数据!$F$1:$UN$1<F13),宏观数据!$F$1:$UN$1),"") -> 46203
A14: 美国:ISM:制造业PMI | B14: 月度 | C14: G0002323 | D14: % | E14: =IFERROR(LOOKUP(9.99E+307,宏观数据!$F$69:$UN$69),"") -> 53.3 | F14: =IFERROR(LOOKUP(2,1/(宏观数据!$F$69:$UN$69<>""),宏观数据!$F$1:$UN$1),"") -> 46203 | G14: =IFERROR(E14-H14,"") -> -0.7 | H14: =IFERROR(LOOKUP(9.99E+307,OFFSET(宏观数据!$F$69,0,0,1,LOOKUP(2,1/(宏观数据!$F$69:$UN$69<>""),COLUMN(宏观数据!$F$69:$UN$69))-COLUMN(宏观数据!$F$69))),"") -> 54 | I14: =IFERROR(LOOKUP(2,1/(宏观数据!$F$69:$UN$69<>"")/(宏观数据!$F$1:$UN$1<F14),宏观数据!$F$1:$UN$1),"") -> 46173
A15: 美国:零售和食品服务销售额:季调:环比 | B15: 月度 | C15: G1109265 | D15: % | E15: =IFERROR(LOOKUP(9.99E+307,宏观数据!$F$70:$UN$70),"") -> 0.880936 | F15: =IFERROR(LOOKUP(2,1/(宏观数据!$F$70:$UN$70<>""),宏观数据!$F$1:$UN$1),"") -> 46173 | G15: =IFERROR(E15-H15,"") -> 0.480015 | H15: =IFERROR(LOOKUP(9.99E+307,OFFSET(宏观数据!$F$70,0,0,1,LOOKUP(2,1/(宏观数据!$F$70:$UN$70<>""),COLUMN(宏观数据!$F$70:$UN$70))-COLUMN(宏观数据!$F$70))),"") -> 0.400921 | I15: =IFERROR(LOOKUP(2,1/(宏观数据!$F$70:$UN$70<>"")/(宏观数据!$F$1:$UN$1<F15),宏观数据!$F$1:$UN$1),"") -> 46142
A16: 美国:密歇根大学消费者信心指数 | B16: 月度 | C16: G0002325 | D16: 点 | E16: =IFERROR(LOOKUP(9.99E+307,宏观数据!$F$71:$UN$71),"") -> 49.5 | F16: =IFERROR(LOOKUP(2,1/(宏观数据!$F$71:$UN$71<>""),宏观数据!$F$1:$UN$1),"") -> 46203 | G16: =IFERROR(E16-H16,"") -> 4.7 | H16: =IFERROR(LOOKUP(9.99E+307,OFFSET(宏观数据!$F$71,0,0,1,LOOKUP(2,1/(宏观数据!$F$71:$UN$71<>""),COLUMN(宏观数据!$F$71:$UN$71))-COLUMN(宏观数据!$F$71))),"") -> 44.8 | I16: =IFERROR(LOOKUP(2,1/(宏观数据!$F$71:$UN$71<>"")/(宏观数据!$F$1:$UN$1<F16),宏观数据!$F$1:$UN$1),"") -> 46173
A17: 美国:新建住房销量:非季调 | B17: 月度 | C17: G0003645 | E17: =IFERROR(LOOKUP(9.99E+307,宏观数据!$F$72:$UN$72),"") -> 51 | F17: =IFERROR(LOOKUP(2,1/(宏观数据!$F$72:$UN$72<>""),宏观数据!$F$1:$UN$1),"") -> 46173 | G17: =IFERROR(E17-H17,"") -> -8 | H17: =IFERROR(LOOKUP(9.99E+307,OFFSET(宏观数据!$F$72,0,0,1,LOOKUP(2,1/(宏观数据!$F$72:$UN$72<>""),COLUMN(宏观数据!$F$72:$UN$72))-COLUMN(宏观数据!$F$72))),"") -> 59 | I17: =IFERROR(LOOKUP(2,1/(宏观数据!$F$72:$UN$72<>"")/(宏观数据!$F$1:$UN$1<F17),宏观数据!$F$1:$UN$1),"") -> 46142
A18: 美国:建造支出:非季调 | B18: 月度 | C18: G0003478 | E18: =IFERROR(LOOKUP(9.99E+307,宏观数据!$F$73:$UN$73),"") -> 191951 | F18: =IFERROR(LOOKUP(2,1/(宏观数据!$F$73:$UN$73<>""),宏观数据!$F$1:$UN$1),"") -> 46173 | G18: =IFERROR(E18-H18,"") -> 9942 | H18: =IFERROR(LOOKUP(9.99E+307,OFFSET(宏观数据!$F$73,0,0,1,LOOKUP(2,1/(宏观数据!$F$73:$UN$73<>""),COLUMN(宏观数据!$F$73:$UN$73))-COLUMN(宏观数据!$F$73))),"") -> 182009 | I18: =IFERROR(LOOKUP(2,1/(宏观数据!$F$73:$UN$73<>"")/(宏观数据!$F$1:$UN$1<F18),宏观数据!$F$1:$UN$1),"") -> 46142
A19: 美国:ISM:服务业PMI:新订单 | B19: 月度 | C19: G0008356 | D19: % | E19: =IFERROR(LOOKUP(9.99E+307,宏观数据!$F$74:$UN$74),"") -> 57.3 | F19: =IFERROR(LOOKUP(2,1/(宏观数据!$F$74:$UN$74<>""),宏观数据!$F$1:$UN$1),"") -> 46173 | G19: =IFERROR(E19-H19,"") -> 3.8 | H19: =IFERROR(LOOKUP(9.99E+307,OFFSET(宏观数据!$F$74,0,0,1,LOOKUP(2,1/(宏观数据!$F$74:$UN$74<>""),COLUMN(宏观数据!$F$74:$UN$74))-COLUMN(宏观数据!$F$74))),"") -> 53.5 | I19: =IFERROR(LOOKUP(2,1/(宏观数据!$F$74:$UN$74<>"")/(宏观数据!$F$1:$UN$1<F19),宏观数据!$F$1:$UN$1),"") -> 46142
A20: 美国:出口金额:商品和服务贸易:季调:同比 | B20: 月度 | C20: G1100352 | D20: % | E20: =IFERROR(LOOKUP(9.99E+307,宏观数据!$F$75:$UN$75),"") -> 12.56 | F20: =IFERROR(LOOKUP(2,1/(宏观数据!$F$75:$UN$75<>""),宏观数据!$F$1:$UN$1),"") -> 46142 | G20: =IFERROR(E20-H20,"") -> 0.06 | H20: =IFERROR(LOOKUP(9.99E+307,OFFSET(宏观数据!$F$75,0,0,1,LOOKUP(2,1/(宏观数据!$F$75:$UN$75<>""),COLUMN(宏观数据!$F$75:$UN$75))-COLUMN(宏观数据!$F$75))),"") -> 12.5 | I20: =IFERROR(LOOKUP(2,1/(宏观数据!$F$75:$UN$75<>"")/(宏观数据!$F$1:$UN$1<F20),宏观数据!$F$1:$UN$1),"") -> 46112
A21: 美国:失业率:季调 | B21: 月度 | C21: G0000067 | D21: % | E21: =IFERROR(LOOKUP(9.99E+307,宏观数据!$F$76:$UN$76),"") -> 4.2 | F21: =IFERROR(LOOKUP(2,1/(宏观数据!$F$76:$UN$76<>""),宏观数据!$F$1:$UN$1),"") -> 46203 | G21: =IFERROR(E21-H21,"") -> -0.1 | H21: =IFERROR(LOOKUP(9.99E+307,OFFSET(宏观数据!$F$76,0,0,1,LOOKUP(2,1/(宏观数据!$F$76:$UN$76<>""),COLUMN(宏观数据!$F$76:$UN$76))-COLUMN(宏观数据!$F$76))),"") -> 4.3 | I21: =IFERROR(LOOKUP(2,1/(宏观数据!$F$76:$UN$76<>"")/(宏观数据!$F$1:$UN$1<F21),宏观数据!$F$1:$UN$1),"") -> 46173
A22: 美国:新增ADP就业人数:季调 | B22: 月度 | C22: L7714005 | E22: =IFERROR(LOOKUP(9.99E+307,宏观数据!$F$77:$UN$77),"") -> 98000 | F22: =IFERROR(LOOKUP(2,1/(宏观数据!$F$77:$UN$77<>""),宏观数据!$F$1:$UN$1),"") -> 46203 | G22: =IFERROR(E22-H22,"") -> -24000 | H22: =IFERROR(LOOKUP(9.99E+307,OFFSET(宏观数据!$F$77,0,0,1,LOOKUP(2,1/(宏观数据!$F$77:$UN$77<>""),COLUMN(宏观数据!$F$77:$UN$77))-COLUMN(宏观数据!$F$77))),"") -> 122000 | I22: =IFERROR(LOOKUP(2,1/(宏观数据!$F$77:$UN$77<>"")/(宏观数据!$F$1:$UN$1<F22),宏观数据!$F$1:$UN$1),"") -> 46173
A23: 美国:财政赤字(盈余为负):同比 | B23: 月度 | C23: G1100346 | D23: % | E23: =IFERROR(LOOKUP(9.99E+307,宏观数据!$F$78:$UN$78),"") -> -7.29 | F23: =IFERROR(LOOKUP(2,1/(宏观数据!$F$78:$UN$78<>""),宏观数据!$F$1:$UN$1),"") -> 46173 | G23: =IFERROR(E23-H23,"") -> -24.08 | H23: =IFERROR(LOOKUP(9.99E+307,OFFSET(宏观数据!$F$78,0,0,1,LOOKUP(2,1/(宏观数据!$F$78:$UN$78<>""),COLUMN(宏观数据!$F$78:$UN$78))-COLUMN(宏观数据!$F$78))),"") -> 16.79 | I23: =IFERROR(LOOKUP(2,1/(宏观数据!$F$78:$UN$78<>"")/(宏观数据!$F$1:$UN$1<F23),宏观数据!$F$1:$UN$1),"") -> 46142
A24: 美国:ISM:服务业PMI | B24: 月度 | C24: G0002324 | D24: % | E24: =IFERROR(LOOKUP(9.99E+307,宏观数据!$F$87:$UN$87),"") -> 54.5 | F24: =IFERROR(LOOKUP(2,1/(宏观数据!$F$87:$UN$87<>""),宏观数据!$F$1:$UN$1),"") -> 46173 | G24: =IFERROR(E24-H24,"") -> 0.9 | H24: =IFERROR(LOOKUP(9.99E+307,OFFSET(宏观数据!$F$87,0,0,1,LOOKUP(2,1/(宏观数据!$F$87:$UN$87<>""),COLUMN(宏观数据!$F$87:$UN$87))-COLUMN(宏观数据!$F$87))),"") -> 53.6 | I24: =IFERROR(LOOKUP(2,1/(宏观数据!$F$87:$UN$87<>"")/(宏观数据!$F$1:$UN$1<F24),宏观数据!$F$1:$UN$1),"") -> 46142
A25: 美国:所有商业银行:资产:银行信贷:季调 | B25: 月度 | C25: G1109077 | D25: 亿美元 | E25: =IFERROR(LOOKUP(9.99E+307,宏观数据!$F$88:$UN$88),"") -> 19643284 | F25: =IFERROR(LOOKUP(2,1/(宏观数据!$F$88:$UN$88<>""),宏观数据!$F$1:$UN$1),"") -> 46197 | G25: =IFERROR(E25-H25,"") -> 22441.4 | H25: =IFERROR(LOOKUP(9.99E+307,OFFSET(宏观数据!$F$88,0,0,1,LOOKUP(2,1/(宏观数据!$F$88:$UN$88<>""),COLUMN(宏观数据!$F$88:$UN$88))-COLUMN(宏观数据!$F$88))),"") -> 19620843 | I25: =IFERROR(LOOKUP(2,1/(宏观数据!$F$88:$UN$88<>"")/(宏观数据!$F$1:$UN$1<F25),宏观数据!$F$1:$UN$1),"") -> 46190
A26: 美国:存款机构:负债:除储备金外的联储银行存款:美国财政部一般账户 | B26: 月度 | C26: G1100038 | D26: 亿美元 | E26: =IFERROR(LOOKUP(9.99E+307,宏观数据!$F$89:$UN$89),"") -> 807359 | F26: =IFERROR(LOOKUP(2,1/(宏观数据!$F$89:$UN$89<>""),宏观数据!$F$1:$UN$1),"") -> 46204 | G26: =IFERROR(E26-H26,"") -> -94486 | H26: =IFERROR(LOOKUP(9.99E+307,OFFSET(宏观数据!$F$89,0,0,1,LOOKUP(2,1/(宏观数据!$F$89:$UN$89<>""),COLUMN(宏观数据!$F$89:$UN$89))-COLUMN(宏观数据!$F$89))),"") -> 901845 | I26: =IFERROR(LOOKUP(2,1/(宏观数据!$F$89:$UN$89<>"")/(宏观数据!$F$1:$UN$1<F26),宏观数据!$F$1:$UN$1),"") -> 46197
A27: 标准普尔500波动率指数(VIX) | B27: 日度 | C27: G0003892 | D27: 点 | E27: =IFERROR(LOOKUP(9.99E+307,宏观数据!$F$90:$UN$90),"") -> 15.81 | F27: =IFERROR(LOOKUP(2,1/(宏观数据!$F$90:$UN$90<>""),宏观数据!$F$1:$UN$1),"") -> 46206 | G27: =IFERROR(E27-H27,"") -> -0.34 | H27: =IFERROR(LOOKUP(9.99E+307,OFFSET(宏观数据!$F$90,0,0,1,LOOKUP(2,1/(宏观数据!$F$90:$UN$90<>""),COLUMN(宏观数据!$F$90:$UN$90))-COLUMN(宏观数据!$F$90))),"") -> 16.15 | I27: =IFERROR(LOOKUP(2,1/(宏观数据!$F$90:$UN$90<>"")/(宏观数据!$F$1:$UN$1<F27),宏观数据!$F$1:$UN$1),"") -> 46205
A28: 市盈率:标准普尔500指数 | B28: 月度 | C28: G0011297 | D28: 点 | E28: =IFERROR(LOOKUP(9.99E+307,宏观数据!$F$91:$UN$91),"") -> 28.3122 | F28: =IFERROR(LOOKUP(2,1/(宏观数据!$F$91:$UN$91<>""),宏观数据!$F$1:$UN$1),"") -> 46208 | G28: =IFERROR(E28-H28,"") -> 0 | H28: =IFERROR(LOOKUP(9.99E+307,OFFSET(宏观数据!$F$91,0,0,1,LOOKUP(2,1/(宏观数据!$F$91:$UN$91<>""),COLUMN(宏观数据!$F$91:$UN$91))-COLUMN(宏观数据!$F$91))),"") -> 28.3122 | I28: =IFERROR(LOOKUP(2,1/(宏观数据!$F$91:$UN$91<>"")/(宏观数据!$F$1:$UN$1<F28),宏观数据!$F$1:$UN$1),"") -> 46207
A29: 美国:国债拍卖竞拍倍数:2年 | B29: 不定期 | C29: G1130724 | E29: =IFERROR(LOOKUP(9.99E+307,宏观数据!$F$92:$UN$92),"") -> 2.4295 | F29: =IFERROR(LOOKUP(2,1/(宏观数据!$F$92:$UN$92<>""),宏观数据!$F$1:$UN$1),"") -> 46196 | G29: =IFERROR(E29-H29,"") -> 0.0015 | H29: =IFERROR(LOOKUP(9.99E+307,OFFSET(宏观数据!$F$92,0,0,1,LOOKUP(2,1/(宏观数据!$F$92:$UN$92<>""),COLUMN(宏观数据!$F$92:$UN$92))-COLUMN(宏观数据!$F$92))),"") -> 2.428 | I29: =IFERROR(LOOKUP(2,1/(宏观数据!$F$92:$UN$92<>"")/(宏观数据!$F$1:$UN$1<F29),宏观数据!$F$1:$UN$1),"") -> 46168
A30: 美国:国债拍卖竞拍倍数:5年 | B30: 不定期 | C30: G1130736 | E30: =IFERROR(LOOKUP(9.99E+307,宏观数据!$F$93:$UN$93),"") -> 2.1751 | F30: =IFERROR(LOOKUP(2,1/(宏观数据!$F$93:$UN$93<>""),宏观数据!$F$1:$UN$1),"") -> 46197 | G30: =IFERROR(E30-H30,"") -> 0.0071 | H30: =IFERROR(LOOKUP(9.99E+307,OFFSET(宏观数据!$F$93,0,0,1,LOOKUP(2,1/(宏观数据!$F$93:$UN$93<>""),COLUMN(宏观数据!$F$93:$UN$93))-COLUMN(宏观数据!$F$93))),"") -> 2.168 | I30: =IFERROR(LOOKUP(2,1/(宏观数据!$F$93:$UN$93<>"")/(宏观数据!$F$1:$UN$1<F30),宏观数据!$F$1:$UN$1),"") -> 46169
A31: 美国:国债拍卖竞拍倍数:10年 | B31: 不定期 | C31: G1130748 | E31: =IFERROR(LOOKUP(9.99E+307,宏观数据!$F$94:$UN$94),"") -> 2.5652 | F31: =IFERROR(LOOKUP(2,1/(宏观数据!$F$94:$UN$94<>""),宏观数据!$F$1:$UN$1),"") -> 46183 | G31: =IFERROR(E31-H31,"") -> 0.4321 | H31: =IFERROR(LOOKUP(9.99E+307,OFFSET(宏观数据!$F$94,0,0,1,LOOKUP(2,1/(宏观数据!$F$94:$UN$94<>""),COLUMN(宏观数据!$F$94:$UN$94))-COLUMN(宏观数据!$F$94))),"") -> 2.1331 | I31: =IFERROR(LOOKUP(2,1/(宏观数据!$F$94:$UN$94<>"")/(宏观数据!$F$1:$UN$1<F31),宏观数据!$F$1:$UN$1),"") -> 46154
A32: 美国:国债拍卖竞拍倍数:30年 | B32: 不定期 | C32: G1130766 | E32: =IFERROR(LOOKUP(9.99E+307,宏观数据!$F$95:$UN$95),"") -> 2.3282 | F32: =IFERROR(LOOKUP(2,1/(宏观数据!$F$95:$UN$95<>""),宏观数据!$F$1:$UN$1),"") -> 46184 | G32: =IFERROR(E32-H32,"") -> 0.2755 | H32: =IFERROR(LOOKUP(9.99E+307,OFFSET(宏观数据!$F$95,0,0,1,LOOKUP(2,1/(宏观数据!$F$95:$UN$95<>""),COLUMN(宏观数据!$F$95:$UN$95))-COLUMN(宏观数据!$F$95))),"") -> 2.0527 | I32: =IFERROR(LOOKUP(2,1/(宏观数据!$F$95:$UN$95<>"")/(宏观数据!$F$1:$UN$1<F32),宏观数据!$F$1:$UN$1),"") -> 46155
A33: 美国:当周初次申请失业金人数:非季调 | B33: 周度 | C33: V7993283 | E33: =IFERROR(LOOKUP(9.99E+307,宏观数据!$F$96:$UN$96),"") -> 213550 | F33: =IFERROR(LOOKUP(2,1/(宏观数据!$F$96:$UN$96<>""),宏观数据!$F$1:$UN$1),"") -> 46200 | G33: =IFERROR(E33-H33,"") -> 5545 | H33: =IFERROR(LOOKUP(9.99E+307,OFFSET(宏观数据!$F$96,0,0,1,LOOKUP(2,1/(宏观数据!$F$96:$UN$96<>""),COLUMN(宏观数据!$F$96:$UN$96))-COLUMN(宏观数据!$F$96))),"") -> 208005 | I33: =IFERROR(LOOKUP(2,1/(宏观数据!$F$96:$UN$96<>"")/(宏观数据!$F$1:$UN$1<F33),宏观数据!$F$1:$UN$1),"") -> 46193
A34: 美国:密歇根大学:通胀率预期:1年 | B34: 月度 | C34: P9918147 | E34: =IFERROR(LOOKUP(9.99E+307,宏观数据!$F$97:$UN$97),"") -> 4.6 | F34: =IFERROR(LOOKUP(2,1/(宏观数据!$F$97:$UN$97<>""),宏观数据!$F$1:$UN$1),"") -> 46203 | G34: =IFERROR(E34-H34,"") -> -0.2 | H34: =IFERROR(LOOKUP(9.99E+307,OFFSET(宏观数据!$F$97,0,0,1,LOOKUP(2,1/(宏观数据!$F$97:$UN$97<>""),COLUMN(宏观数据!$F$97:$UN$97))-COLUMN(宏观数据!$F$97))),"") -> 4.8 | I34: =IFERROR(LOOKUP(2,1/(宏观数据!$F$97:$UN$97<>"")/(宏观数据!$F$1:$UN$1<F34),宏观数据!$F$1:$UN$1),"") -> 46173
A35: 美国:新增非农就业人数:季调:初值 | B35: 月度 | C35: G1137704 | E35: =IFERROR(LOOKUP(9.99E+307,宏观数据!$F$98:$UN$98),"") -> 57 | F35: =IFERROR(LOOKUP(2,1/(宏观数据!$F$98:$UN$98<>""),宏观数据!$F$1:$UN$1),"") -> 46203 | G35: =IFERROR(E35-H35,"") -> -115 | H35: =IFERROR(LOOKUP(9.99E+307,OFFSET(宏观数据!$F$98,0,0,1,LOOKUP(2,1/(宏观数据!$F$98:$UN$98<>""),COLUMN(宏观数据!$F$98:$UN$98))-COLUMN(宏观数据!$F$98))),"") -> 172 | I35: =IFERROR(LOOKUP(2,1/(宏观数据!$F$98:$UN$98<>"")/(宏观数据!$F$1:$UN$1<F35),宏观数据!$F$1:$UN$1),"") -> 46173
A36: 期货结算价(连续):布伦特原油 | B36: 日度 | C36: S0031525 | E36: =IFERROR(LOOKUP(9.99E+307,宏观数据!$F$99:$UN$99),"") -> 72.12 | F36: =IFERROR(LOOKUP(2,1/(宏观数据!$F$99:$UN$99<>""),宏观数据!$F$1:$UN$1),"") -> 46206 | G36: =IFERROR(E36-H36,"") -> 0.32 | H36: =IFERROR(LOOKUP(9.99E+307,OFFSET(宏观数据!$F$99,0,0,1,LOOKUP(2,1/(宏观数据!$F$99:$UN$99<>""),COLUMN(宏观数据!$F$99:$UN$99))-COLUMN(宏观数据!$F$99))),"") -> 71.8 | I36: =IFERROR(LOOKUP(2,1/(宏观数据!$F$99:$UN$99<>"")/(宏观数据!$F$1:$UN$1<F36),宏观数据!$F$1:$UN$1),"") -> 46205
A37: 美国:核心CPI:非季调:同比 | B37: 月度 | C37: G0000029 | D37: % | E37: =IFERROR(LOOKUP(9.99E+307,宏观数据!$F$108:$UN$108),"") -> 2.9 | F37: =IFERROR(LOOKUP(2,1/(宏观数据!$F$108:$UN$108<>""),宏观数据!$F$1:$UN$1),"") -> 46173 | G37: =IFERROR(E37-H37,"") -> 0.1 | H37: =IFERROR(LOOKUP(9.99E+307,OFFSET(宏观数据!$F$108,0,0,1,LOOKUP(2,1/(宏观数据!$F$108:$UN$108<>""),COLUMN(宏观数据!$F$108:$UN$108))-COLUMN(宏观数据!$F$108))),"") -> 2.8 | I37: =IFERROR(LOOKUP(2,1/(宏观数据!$F$108:$UN$108<>"")/(宏观数据!$F$1:$UN$1<F37),宏观数据!$F$1:$UN$1),"") -> 46142
A38: 美国:国债拍卖最高收益率:TIPS债券:10年 | B38: 日度 | C38: G1130774 | D38: % | E38: =IFERROR(LOOKUP(9.99E+307,宏观数据!$F$110:$UN$110),"") -> 2.169 | F38: =IFERROR(LOOKUP(2,1/(宏观数据!$F$110:$UN$110<>""),宏观数据!$F$1:$UN$1),"") -> 46163 | G38: =IFERROR(E38-H38,"") -> 0.273 | H38: =IFERROR(LOOKUP(9.99E+307,OFFSET(宏观数据!$F$110,0,0,1,LOOKUP(2,1/(宏观数据!$F$110:$UN$110<>""),COLUMN(宏观数据!$F$110:$UN$110))-COLUMN(宏观数据!$F$110))),"") -> 1.896 | I38: =IFERROR(LOOKUP(2,1/(宏观数据!$F$110:$UN$110<>"")/(宏观数据!$F$1:$UN$1<F38),宏观数据!$F$1:$UN$1),"") -> 46100
A39: 全球:官方黄金储备变动量:当月值 | B39: 月度 | C39: F2284050 | D39: 亿美元 | E39: =IFERROR(LOOKUP(9.99E+307,宏观数据!$F$111:$UN$111),"") -> 41.238112 | F39: =IFERROR(LOOKUP(2,1/(宏观数据!$F$111:$UN$111<>""),宏观数据!$F$1:$UN$1),"") -> 46173 | G39: =IFERROR(E39-H39,"") -> 19.707336 | H39: =IFERROR(LOOKUP(9.99E+307,OFFSET(宏观数据!$F$111,0,0,1,LOOKUP(2,1/(宏观数据!$F$111:$UN$111<>""),COLUMN(宏观数据!$F$111:$UN$111))-COLUMN(宏观数据!$F$111))),"") -> 21.530776 | I39: =IFERROR(LOOKUP(2,1/(宏观数据!$F$111:$UN$111<>"")/(宏观数据!$F$1:$UN$1<F39),宏观数据!$F$1:$UN$1),"") -> 46142
A40: 美国:隔夜逆回购(ONRRP)出让金额:国债:第一批次 | B40: 周度 | C40: G1168931 | D40: 亿美元 | E40: =IFERROR(LOOKUP(9.99E+307,宏观数据!$F$113:$UN$113),"") -> 2.175 | F40: =IFERROR(LOOKUP(2,1/(宏观数据!$F$113:$UN$113<>""),宏观数据!$F$1:$UN$1),"") -> 46205 | G40: =IFERROR(E40-H40,"") -> 1.174 | H40: =IFERROR(LOOKUP(9.99E+307,OFFSET(宏观数据!$F$113,0,0,1,LOOKUP(2,1/(宏观数据!$F$113:$UN$113<>""),COLUMN(宏观数据!$F$113:$UN$113))-COLUMN(宏观数据!$F$113))),"") -> 1.001 | I40: =IFERROR(LOOKUP(2,1/(宏观数据!$F$113:$UN$113<>"")/(宏观数据!$F$1:$UN$1<F40),宏观数据!$F$1:$UN$1),"") -> 46204
A41: 美国:准备金余额利率(IORB) | B41: 日度 | C41: N9689792 | D41: % | E41: =IFERROR(LOOKUP(9.99E+307,宏观数据!$F$126:$UN$126),"") -> 3.65 | F41: =IFERROR(LOOKUP(2,1/(宏观数据!$F$126:$UN$126<>""),宏观数据!$F$1:$UN$1),"") -> 46209 | G41: =IFERROR(E41-H41,"") -> 0 | H41: =IFERROR(LOOKUP(9.99E+307,OFFSET(宏观数据!$F$126,0,0,1,LOOKUP(2,1/(宏观数据!$F$126:$UN$126<>""),COLUMN(宏观数据!$F$126:$UN$126))-COLUMN(宏观数据!$F$126))),"") -> 3.65 | I41: =IFERROR(LOOKUP(2,1/(宏观数据!$F$126:$UN$126<>"")/(宏观数据!$F$1:$UN$1<F41),宏观数据!$F$1:$UN$1),"") -> 46208
A42: 美国:SOFR-IORB利差 | B42: 周度 | C42: X4477229 | D42: % | E42: =IFERROR(LOOKUP(9.99E+307,宏观数据!$F$127:$UN$127),"") -> 0.01 | F42: =IFERROR(LOOKUP(2,1/(宏观数据!$F$127:$UN$127<>""),宏观数据!$F$1:$UN$1),"") -> 46204 | G42: =IFERROR(E42-H42,"") -> -0.02 | H42: =IFERROR(LOOKUP(9.99E+307,OFFSET(宏观数据!$F$127,0,0,1,LOOKUP(2,1/(宏观数据!$F$127:$UN$127<>""),COLUMN(宏观数据!$F$127:$UN$127))-COLUMN(宏观数据!$F$127))),"") -> 0.03 | I42: =IFERROR(LOOKUP(2,1/(宏观数据!$F$127:$UN$127<>"")/(宏观数据!$F$1:$UN$1<F42),宏观数据!$F$1:$UN$1),"") -> 46203
A43: 美国:担保隔夜融资利率(SOFR):成交额 | B43: 周度 | C43: G1168802 | D43: % | E43: =IFERROR(LOOKUP(9.99E+307,宏观数据!$F$128:$UN$128),"") -> 3321 | F43: =IFERROR(LOOKUP(2,1/(宏观数据!$F$128:$UN$128<>""),宏观数据!$F$1:$UN$1),"") -> 46204 | G43: =IFERROR(E43-H43,"") -> -97 | H43: =IFERROR(LOOKUP(9.99E+307,OFFSET(宏观数据!$F$128,0,0,1,LOOKUP(2,1/(宏观数据!$F$128:$UN$128<>""),COLUMN(宏观数据!$F$128:$UN$128))-COLUMN(宏观数据!$F$128))),"") -> 3418 | I43: =IFERROR(LOOKUP(2,1/(宏观数据!$F$128:$UN$128<>"")/(宏观数据!$F$1:$UN$1<F43),宏观数据!$F$1:$UN$1),"") -> 46203
A44: 美国:企业债收益率:穆迪Aaa | B44: 日度 | C44: G0005431 | D44: % | E44: =IFERROR(LOOKUP(9.99E+307,宏观数据!$F$129:$UN$129),"") -> 5.6 | F44: =IFERROR(LOOKUP(2,1/(宏观数据!$F$129:$UN$129<>""),宏观数据!$F$1:$UN$1),"") -> 46204 | G44: =IFERROR(E44-H44,"") -> 0.05 | H44: =IFERROR(LOOKUP(9.99E+307,OFFSET(宏观数据!$F$129,0,0,1,LOOKUP(2,1/(宏观数据!$F$129:$UN$129<>""),COLUMN(宏观数据!$F$129:$UN$129))-COLUMN(宏观数据!$F$129))),"") -> 5.55 | I44: =IFERROR(LOOKUP(2,1/(宏观数据!$F$129:$UN$129<>"")/(宏观数据!$F$1:$UN$1<F44),宏观数据!$F$1:$UN$1),"") -> 46203
A45: 美国:存款机构:资产:储备银行信贷:贷款 | B45: 月度 | C45: G0005586 | D45: 亿美元 | E45: =IFERROR(LOOKUP(9.99E+307,宏观数据!$F$130:$UN$130),"") -> 7832 | F45: =IFERROR(LOOKUP(2,1/(宏观数据!$F$130:$UN$130<>""),宏观数据!$F$1:$UN$1),"") -> 46204 | G45: =IFERROR(E45-H45,"") -> -114 | H45: =IFERROR(LOOKUP(9.99E+307,OFFSET(宏观数据!$F$130,0,0,1,LOOKUP(2,1/(宏观数据!$F$130:$UN$130<>""),COLUMN(宏观数据!$F$130:$UN$130))-COLUMN(宏观数据!$F$130))),"") -> 7946 | I45: =IFERROR(LOOKUP(2,1/(宏观数据!$F$130:$UN$130<>"")/(宏观数据!$F$1:$UN$1<F45),宏观数据!$F$1:$UN$1),"") -> 46197
A46: 美国:存款机构:资产:储备银行信贷 | B46: 月度 | C46: G1100023 | D46: 亿美元 | E46: =IFERROR(LOOKUP(9.99E+307,宏观数据!$F$131:$UN$131),"") -> 6677116 | F46: =IFERROR(LOOKUP(2,1/(宏观数据!$F$131:$UN$131<>""),宏观数据!$F$1:$UN$1),"") -> 46204 | G46: =IFERROR(E46-H46,"") -> -11679 | H46: =IFERROR(LOOKUP(9.99E+307,OFFSET(宏观数据!$F$131,0,0,1,LOOKUP(2,1/(宏观数据!$F$131:$UN$131<>""),COLUMN(宏观数据!$F$131:$UN$131))-COLUMN(宏观数据!$F$131))),"") -> 6688795 | I46: =IFERROR(LOOKUP(2,1/(宏观数据!$F$131:$UN$131<>"")/(宏观数据!$F$1:$UN$1<F46),宏观数据!$F$1:$UN$1),"") -> 46197
A47: 美国:所有商业银行:资产:银行信贷:季调:同比 | B47: 月度 | C47: K9194659 | D47: % | E47: =IFERROR(LOOKUP(9.99E+307,宏观数据!$F$132:$UN$132),"") -> 7.1 | F47: =IFERROR(LOOKUP(2,1/(宏观数据!$F$132:$UN$132<>""),宏观数据!$F$1:$UN$1),"") -> 46112 | G47: =IFERROR(E47-H47,"") -> 2.1 | H47: =IFERROR(LOOKUP(9.99E+307,OFFSET(宏观数据!$F$132,0,0,1,LOOKUP(2,1/(宏观数据!$F$132:$UN$132<>""),COLUMN(宏观数据!$F$132:$UN$132))-COLUMN(宏观数据!$F$132))),"") -> 5 | I47: =IFERROR(LOOKUP(2,1/(宏观数据!$F$132:$UN$132<>"")/(宏观数据!$F$1:$UN$1<F47),宏观数据!$F$1:$UN$1),"") -> 46022
A48: 美国:所有商业银行:资产:银行信贷:非季调 | B48: 月度 | C48: G1109125 | D48: 亿美元 | E48: =IFERROR(LOOKUP(9.99E+307,宏观数据!$F$133:$UN$133),"") -> 19652818 | F48: =IFERROR(LOOKUP(2,1/(宏观数据!$F$133:$UN$133<>""),宏观数据!$F$1:$UN$1),"") -> 46197 | G48: =IFERROR(E48-H48,"") -> 34115 | H48: =IFERROR(LOOKUP(9.99E+307,OFFSET(宏观数据!$F$133,0,0,1,LOOKUP(2,1/(宏观数据!$F$133:$UN$133<>""),COLUMN(宏观数据!$F$133:$UN$133))-COLUMN(宏观数据!$F$133))),"") -> 19618703 | I48: =IFERROR(LOOKUP(2,1/(宏观数据!$F$133:$UN$133<>"")/(宏观数据!$F$1:$UN$1<F48),宏观数据!$F$1:$UN$1),"") -> 46190
A49: 美国:M1:季调 | B49: 月度 | C49: G0003382 | E49: =IFERROR(LOOKUP(9.99E+307,宏观数据!$F$134:$UN$134),"") -> 19750.9 | F49: =IFERROR(LOOKUP(2,1/(宏观数据!$F$134:$UN$134<>""),宏观数据!$F$1:$UN$1),"") -> 46173 | G49: =IFERROR(E49-H49,"") -> 219.2 | H49: =IFERROR(LOOKUP(9.99E+307,OFFSET(宏观数据!$F$134,0,0,1,LOOKUP(2,1/(宏观数据!$F$134:$UN$134<>""),COLUMN(宏观数据!$F$134:$UN$134))-COLUMN(宏观数据!$F$134))),"") -> 19531.7 | I49: =IFERROR(LOOKUP(2,1/(宏观数据!$F$134:$UN$134<>"")/(宏观数据!$F$1:$UN$1<F49),宏观数据!$F$1:$UN$1),"") -> 46142
A50: 美国:M2:季调 | B50: 月度 | C50: G0003383 | E50: =IFERROR(LOOKUP(9.99E+307,宏观数据!$F$135:$UN$135),"") -> 23052.3 | F50: =IFERROR(LOOKUP(2,1/(宏观数据!$F$135:$UN$135<>""),宏观数据!$F$1:$UN$1),"") -> 46173 | G50: =IFERROR(E50-H50,"") -> 247.8 | H50: =IFERROR(LOOKUP(9.99E+307,OFFSET(宏观数据!$F$135,0,0,1,LOOKUP(2,1/(宏观数据!$F$135:$UN$135<>""),COLUMN(宏观数据!$F$135:$UN$135))-COLUMN(宏观数据!$F$135))),"") -> 22804.5 | I50: =IFERROR(LOOKUP(2,1/(宏观数据!$F$135:$UN$135<>"")/(宏观数据!$F$1:$UN$1<F50),宏观数据!$F$1:$UN$1),"") -> 46142
A51: 美国:所有商业银行:资产:银行信贷:贷款和租赁:工商业贷款:季调 | B51: 月度 | C51: G1109086 | D51: 亿美元 | E51: =IFERROR(LOOKUP(9.99E+307,宏观数据!$F$136:$UN$136),"") -> 2901015.8 | F51: =IFERROR(LOOKUP(2,1/(宏观数据!$F$136:$UN$136<>""),宏观数据!$F$1:$UN$1),"") -> 46197 | G51: =IFERROR(E51-H51,"") -> 6023.8 | H51: =IFERROR(LOOKUP(9.99E+307,OFFSET(宏观数据!$F$136,0,0,1,LOOKUP(2,1/(宏观数据!$F$136:$UN$136<>""),COLUMN(宏观数据!$F$136:$UN$136))-COLUMN(宏观数据!$F$136))),"") -> 2894992 | I51: =IFERROR(LOOKUP(2,1/(宏观数据!$F$136:$UN$136<>"")/(宏观数据!$F$1:$UN$1<F51),宏观数据!$F$1:$UN$1),"") -> 46190
A52: 美国:存款机构:资产:金融资产:贷款(扣除特定准备金):贷款总额:同业贷款:居民:美元 | B52: 月度 | C52: O5930218 | D52: 亿美元 | E52: =IFERROR(LOOKUP(9.99E+307,宏观数据!$F$137:$UN$137),"") -> 605321.13 | F52: =IFERROR(LOOKUP(2,1/(宏观数据!$F$137:$UN$137<>""),宏观数据!$F$1:$UN$1),"") -> 45291 | G52: =IFERROR(E52-H52,"") | H52: =IFERROR(LOOKUP(9.99E+307,OFFSET(宏观数据!$F$137,0,0,1,LOOKUP(2,1/(宏观数据!$F$137:$UN$137<>""),COLUMN(宏观数据!$F$137:$UN$137))-COLUMN(宏观数据!$F$137))),"") | I52: =IFERROR(LOOKUP(2,1/(宏观数据!$F$137:$UN$137<>"")/(宏观数据!$F$1:$UN$1<F52),宏观数据!$F$1:$UN$1),"")
A53: 美国:所有商业银行:资产:银行信贷:贷款和租赁:消费贷款:季调 | B53: 月度 | C53: G1109091 | D53: 亿美元 | E53: =IFERROR(LOOKUP(9.99E+307,宏观数据!$F$138:$UN$138),"") -> 1896780.8 | F53: =IFERROR(LOOKUP(2,1/(宏观数据!$F$138:$UN$138<>""),宏观数据!$F$1:$UN$1),"") -> 46197 | G53: =IFERROR(E53-H53,"") -> 2150.7 | H53: =IFERROR(LOOKUP(9.99E+307,OFFSET(宏观数据!$F$138,0,0,1,LOOKUP(2,1/(宏观数据!$F$138:$UN$138<>""),COLUMN(宏观数据!$F$138:$UN$138))-COLUMN(宏观数据!$F$138))),"") -> 1894630.1 | I53: =IFERROR(LOOKUP(2,1/(宏观数据!$F$138:$UN$138<>"")/(宏观数据!$F$1:$UN$1<F53),宏观数据!$F$1:$UN$1),"") -> 46190
A54: 美国:工业生产指数:非季调:当月同比 | B54: 月度 | C54: G1120852 | D54: % | E54: =IFERROR(LOOKUP(9.99E+307,宏观数据!$F$139:$UN$139),"") -> 1.63 | F54: =IFERROR(LOOKUP(2,1/(宏观数据!$F$139:$UN$139<>""),宏观数据!$F$1:$UN$1),"") -> 46173 | G54: =IFERROR(E54-H54,"") -> 0.48 | H54: =IFERROR(LOOKUP(9.99E+307,OFFSET(宏观数据!$F$139,0,0,1,LOOKUP(2,1/(宏观数据!$F$139:$UN$139<>""),COLUMN(宏观数据!$F$139:$UN$139))-COLUMN(宏观数据!$F$139))),"") -> 1.15 | I54: =IFERROR(LOOKUP(2,1/(宏观数据!$F$139:$UN$139<>"")/(宏观数据!$F$1:$UN$1<F54),宏观数据!$F$1:$UN$1),"") -> 46142
A55: 美国:GDP:不变价:季调:折年数:同比 | B55: 季度 | C55: G1112986 | D55: % | E55: =IFERROR(LOOKUP(9.99E+307,宏观数据!$F$140:$UN$140),"") -> 2.6847 | F55: =IFERROR(LOOKUP(2,1/(宏观数据!$F$140:$UN$140<>""),宏观数据!$F$1:$UN$1),"") -> 46112 | G55: =IFERROR(E55-H55,"") -> 0.6954 | H55: =IFERROR(LOOKUP(9.99E+307,OFFSET(宏观数据!$F$140,0,0,1,LOOKUP(2,1/(宏观数据!$F$140:$UN$140<>""),COLUMN(宏观数据!$F$140:$UN$140))-COLUMN(宏观数据!$F$140))),"") -> 1.9893 | I55: =IFERROR(LOOKUP(2,1/(宏观数据!$F$140:$UN$140<>"")/(宏观数据!$F$1:$UN$1<F55),宏观数据!$F$1:$UN$1),"") -> 46022
A56: 美国:非农企业全部员工:平均时薪:私营部门:季调:同比 | B56: 月度 | C56: L5830501 | D56: % | E56: =IFERROR(LOOKUP(9.99E+307,宏观数据!$F$141:$UN$141),"") -> 3.5 | F56: =IFERROR(LOOKUP(2,1/(宏观数据!$F$141:$UN$141<>""),宏观数据!$F$1:$UN$1),"") -> 46203 | G56: =IFERROR(E56-H56,"") -> 0.1 | H56: =IFERROR(LOOKUP(9.99E+307,OFFSET(宏观数据!$F$141,0,0,1,LOOKUP(2,1/(宏观数据!$F$141:$UN$141<>""),COLUMN(宏观数据!$F$141:$UN$141))-COLUMN(宏观数据!$F$141))),"") -> 3.4 | I56: =IFERROR(LOOKUP(2,1/(宏观数据!$F$141:$UN$141<>"")/(宏观数据!$F$1:$UN$1<F56),宏观数据!$F$1:$UN$1),"") -> 46173
A57: 美国:个人可支配收入:不变价:季调:同比 | B57: 月度 | C57: D7259310 | D57: % | E57: =IFERROR(LOOKUP(9.99E+307,宏观数据!$F$142:$UN$142),"") -> 0.7 | F57: =IFERROR(LOOKUP(2,1/(宏观数据!$F$142:$UN$142<>""),宏观数据!$F$1:$UN$1),"") -> 46112 | G57: =IFERROR(E57-H57,"") -> -0.3 | H57: =IFERROR(LOOKUP(9.99E+307,OFFSET(宏观数据!$F$142,0,0,1,LOOKUP(2,1/(宏观数据!$F$142:$UN$142<>""),COLUMN(宏观数据!$F$142:$UN$142))-COLUMN(宏观数据!$F$142))),"") -> 1 | I57: =IFERROR(LOOKUP(2,1/(宏观数据!$F$142:$UN$142<>"")/(宏观数据!$F$1:$UN$1<F57),宏观数据!$F$1:$UN$1),"") -> 46022
A58: 美国:所有商业银行:资产:银行信贷:贷款和租赁:房地产贷款:季调 | B58: 月度 | C58: G1109087 | D58: 亿美元 | E58: =IFERROR(LOOKUP(9.99E+307,宏观数据!$F$143:$UN$143),"") -> 5798603.8 | F58: =IFERROR(LOOKUP(2,1/(宏观数据!$F$143:$UN$143<>""),宏观数据!$F$1:$UN$1),"") -> 46197 | G58: =IFERROR(E58-H58,"") -> -2264.9 | H58: =IFERROR(LOOKUP(9.99E+307,OFFSET(宏观数据!$F$143,0,0,1,LOOKUP(2,1/(宏观数据!$F$143:$UN$143<>""),COLUMN(宏观数据!$F$143:$UN$143))-COLUMN(宏观数据!$F$143))),"") -> 5800868.7 | I58: =IFERROR(LOOKUP(2,1/(宏观数据!$F$143:$UN$143<>"")/(宏观数据!$F$1:$UN$1<F58),宏观数据!$F$1:$UN$1),"") -> 46190
A59: 美国:核心CPI | B59: 月度 | C59: G0000030 | D59: % | E59: =IFERROR(LOOKUP(9.99E+307,宏观数据!$F$148:$UN$148),"") -> 2.8 | F59: =IFERROR(LOOKUP(2,1/(宏观数据!$F$148:$UN$148<>""),宏观数据!$F$1:$UN$1),"") -> 46173 | G59: =IFERROR(E59-H59,"") -> 0.1 | H59: =IFERROR(LOOKUP(9.99E+307,OFFSET(宏观数据!$F$148,0,0,1,LOOKUP(2,1/(宏观数据!$F$148:$UN$148<>""),COLUMN(宏观数据!$F$148:$UN$148))-COLUMN(宏观数据!$F$148))),"") -> 2.7 | I59: =IFERROR(LOOKUP(2,1/(宏观数据!$F$148:$UN$148<>"")/(宏观数据!$F$1:$UN$1<F59),宏观数据!$F$1:$UN$1),"") -> 46142
A60: 全球地缘政治风险指数 | B60: 月度 | C60: W5726665 | D60: 点 | E60: =IFERROR(LOOKUP(9.99E+307,宏观数据!$F$149:$UN$149),"") -> 173.63956 | F60: =IFERROR(LOOKUP(2,1/(宏观数据!$F$149:$UN$149<>""),宏观数据!$F$1:$UN$1),"") -> 46203 | G60: =IFERROR(E60-H60,"") -> -29.917114 | H60: =IFERROR(LOOKUP(9.99E+307,OFFSET(宏观数据!$F$149,0,0,1,LOOKUP(2,1/(宏观数据!$F$149:$UN$149<>""),COLUMN(宏观数据!$F$149:$UN$149))-COLUMN(宏观数据!$F$149))),"") -> 203.55667 | I60: =IFERROR(LOOKUP(2,1/(宏观数据!$F$149:$UN$149<>"")/(宏观数据!$F$1:$UN$1<F60),宏观数据!$F$1:$UN$1),"") -> 46173
A61: 美国中小企业乐观指数 | B61: 月度 | C61: G1131647 | D61: 点 | E61: =IFERROR(LOOKUP(9.99E+307,宏观数据!$F$150:$UN$150),"") -> 95.3 | F61: =IFERROR(LOOKUP(2,1/(宏观数据!$F$150:$UN$150<>""),宏观数据!$F$1:$UN$1),"") -> 46173 | G61: =IFERROR(E61-H61,"") -> -0.6 | H61: =IFERROR(LOOKUP(9.99E+307,OFFSET(宏观数据!$F$150,0,0,1,LOOKUP(2,1/(宏观数据!$F$150:$UN$150<>""),COLUMN(宏观数据!$F$150:$UN$150))-COLUMN(宏观数据!$F$150))),"") -> 95.9 | I61: =IFERROR(LOOKUP(2,1/(宏观数据!$F$150:$UN$150<>"")/(宏观数据!$F$1:$UN$1<F61),宏观数据!$F$1:$UN$1),"") -> 46142
A62: 美国:财政赤字率 (赤字/GDP) | B62: 年度 | C62: G1147446 | D62: % | E62: =IFERROR(LOOKUP(9.99E+307,宏观数据!$F$161:$UN$161),"") -> 6.1 | F62: =IFERROR(LOOKUP(2,1/(宏观数据!$F$161:$UN$161<>""),宏观数据!$F$1:$UN$1),"") -> 46022 | G62: =IFERROR(E62-H62,"") | H62: =IFERROR(LOOKUP(9.99E+307,OFFSET(宏观数据!$F$161,0,0,1,LOOKUP(2,1/(宏观数据!$F$161:$UN$161<>""),COLUMN(宏观数据!$F$161:$UN$161))-COLUMN(宏观数据!$F$161))),"") | I62: =IFERROR(LOOKUP(2,1/(宏观数据!$F$161:$UN$161<>"")/(宏观数据!$F$1:$UN$1<F62),宏观数据!$F$1:$UN$1),"")

Sheet 宏观数据
A1: 开始日期 | B1: 截止日期 | C1: EDBclose | D1: 日期 | E1: Date | F1: 45291 | G1: 45658 | H1: 45659 | I1: 45660 | J1: 45661 | K1: 45662 | L1: 45663 | M1: 45664 | N1: 45665 | O1: 45666 | P1: 45667 | Q1: 45668 | R1: 45669 | S1: 45670 | T1: 45671 | U1: 45672 | V1: 45673 | W1: 45674 | X1: 45675 | Y1: 45676 | Z1: 45677 | AA1: 45678 | AB1: 45679 | AC1: 45680 | AD1: 45681 | AE1: 45682 | AF1: 45683 | AG1: 45684 | AH1: 45685 | AI1: 45686 | AJ1: 45687 | AK1: 45688 | AL1: 45689 | AM1: 45690 | AN1: 45691 | AO1: 45692 | AP1: 45693 | AQ1: 45694 | AR1: 45695 | AS1: 45696 | AT1: 45697 | AU1: 45698 | AV1: 45699 | AW1: 45700 | AX1: 45701 | AY1: 45702 | AZ1: 45703 | BA1: 45704 | BB1: 45705 | BC1: 45706 | BD1: 45707 | BE1: 45708 | BF1: 45709 | BG1: 45710 | BH1: 45711 | BI1: 45712 | BJ1: 45713 | BK1: 45714 | BL1: 45715 | BM1: 45716 | BN1: 45717 | BO1: 45718 | BP1: 45719 | BQ1: 45720 | BR1: 45721 | BS1: 45722 | BT1: 45723 | BU1: 45724 | BV1: 45725 | BW1: 45726 | BX1: 45727 | BY1: 45728 | BZ1: 45729 | CA1: 45730 | CB1: 45731 | CC1: 45732 | CD1: 45733 | CE1: 45734 | CF1: 45735 | CG1: 45736 | CH1: 45737 | CI1: 45738 | CJ1: 45739 | CK1: 45740 | CL1: 45741 | CM1: 45742 | CN1: 45743 | CO1: 45744 | CP1: 45745 | CQ1: 45746 | CR1: 45747 | CS1: 45748 | CT1: 45749 | CU1: 45750 | CV1: 45751 | CW1: 45752 | CX1: 45753 | CY1: 45754 | CZ1: 45755 | DA1: 45756 | DB1: 45757 | DC1: 45758 | DD1: 45759 | DE1: 45760 | DF1: 45761 | DG1: 45762 | DH1: 45763 | DI1: 45764 | DJ1: 45765 | DK1: 45766 | DL1: 45767 | DM1: 45768 | DN1: 45769 | DO1: 45770 | DP1: 45771 | DQ1: 45772 | DR1: 45773 | DS1: 45774 | DT1: 45775 | DU1: 45776 | DV1: 45777 | DW1: 45778 | DX1: 45779 | DY1: 45780 | DZ1: 45781 | EA1: 45782 | EB1: 45783 | EC1: 45784 | ED1: 45785 | EE1: 45786 | EF1: 45787 | EG1: 45788 | EH1: 45789 | EI1: 45790 | EJ1: 45791 | EK1: 45792 | EL1: 45793 | EM1: 45794 | EN1: 45795 | EO1: 45796 | EP1: 45797 | EQ1: 45798 | ER1: 45799 | ES1: 45800 | ET1: 45801 | EU1: 45802 | EV1: 45803 | EW1: 45804 | EX1: 45805 | EY1: 45806 | EZ1: 45807 | FA1: 45808 | FB1: 45809 | FC1: 45810 | FD1: 45811 | FE1: 45812 | FF1: 45813 | FG1: 45814 | FH1: 45815 | FI1: 45816 | FJ1: 45817 | FK1: 45818 | FL1: 45819 | FM1: 45820 | FN1: 45821 | FO1: 45822 | FP1: 45823 | FQ1: 45824 | FR1: 45825 | FS1: 45826 | FT1: 45827 | FU1: 45828 | FV1: 45829 | FW1: 45830 | FX1: 45831 | FY1: 45832 | FZ1: 45833 | GA1: 45834 | GB1: 45835 | GC1: 45836 | GD1: 45837 | GE1: 45838 | GF1: 45839 | GG1: 45840 | GH1: 45841 | GI1: 45842 | GJ1: 45843 | GK1: 45844 | GL1: 45845 | GM1: 45846 | GN1: 45847 | GO1: 45848 | GP1: 45849 | GQ1: 45850 | GR1: 45851 | GS1: 45852 | GT1: 45853 | GU1: 45854 | GV1: 45855 | GW1: 45856 | GX1: 45857 | GY1: 45858 | GZ1: 45859 | HA1: 45860 | HB1: 45861 | HC1: 45862 | HD1: 45863 | HE1: 45864 | HF1: 45865 | HG1: 45866 | HH1: 45867 | HI1: 45868 | HJ1: 45869 | HK1: 45870 | HL1: 45871 | HM1: 45872 | HN1: 45873 | HO1: 45874 | HP1: 45875 | HQ1: 45876 | HR1: 45877 | HS1: 45878 | HT1: 45879 | HU1: 45880 | HV1: 45881 | HW1: 45882 | HX1: 45883 | HY1: 45884 | HZ1: 45885 | IA1: 45886 | IB1: 45887 | IC1: 45888 | ID1: 45889 | IE1: 45890 | IF1: 45891 | IG1: 45892 | IH1: 45893 | II1: 45894 | IJ1: 45895 | IK1: 45896 | IL1: 45897 | IM1: 45898 | IN1: 45899 | IO1: 45900 | IP1: 45901 | IQ1: 45902 | IR1: 45903 | IS1: 45904 | IT1: 45905 | IU1: 45906 | IV1: 45907 | IW1: 45908 | IX1: 45909 | IY1: 45910 | IZ1: 45911 | JA1: 45912 | JB1: 45913 | JC1: 45914 | JD1: 45915 | JE1: 45916 | JF1: 45917 | JG1: 45918 | JH1: 45919 | JI1: 45920 | JJ1: 45921 | JK1: 45922 | JL1: 45923 | JM1: 45924 | JN1: 45925 | JO1: 45926 | JP1: 45927 | JQ1: 45928 | JR1: 45929 | JS1: 45930 | JT1: 45931 | JU1: 45932 | JV1: 45933 | JW1: 45934 | JX1: 45935 | JY1: 45936 | JZ1: 45937 | KA1: 45938 | KB1: 45939 | KC1: 45940 | KD1: 45941 | KE1: 45942 | KF1: 45943 | KG1: 45944 | KH1: 45945 | KI1: 45946 | KJ1: 45947 | KK1: 45948 | KL1: 45949 | KM1: 45950 | KN1: 45951 | KO1: 45952 | KP1: 45953 | KQ1: 45954 | KR1: 45955 | KS1: 45956 | KT1: 45957 | KU1: 45958 | KV1: 45959 | KW1: 45960 | KX1: 45961 | KY1: 45962 | KZ1: 45963 | LA1: 45964 | LB1: 45965 | LC1: 45966 | LD1: 45967 | LE1: 45968 | LF1: 45969 | LG1: 45970 | LH1: 45971 | LI1: 45972 | LJ1: 45973 | LK1: 45974 | LL1: 45975 | LM1: 45976 | LN1: 45977 | LO1: 45978 | LP1: 45979 | LQ1: 45980 | LR1: 45981 | LS1: 45982 | LT1: 45983 | LU1: 45984 | LV1: 45985 | LW1: 45986 | LX1: 45987 | LY1: 45988 | LZ1: 45989 | MA1: 45990 | MB1: 45991 | MC1: 45992 | MD1: 45993 | ME1: 45994 | MF1: 45995 | MG1: 45996 | MH1: 45997 | MI1: 45998 | MJ1: 45999 | MK1: 46000 | ML1: 46001 | MM1: 46002 | MN1: 46003 | MO1: 46004 | MP1: 46005 | MQ1: 46006 | MR1: 46007 | MS1: 46008 | MT1: 46009 | MU1: 46010 | MV1: 46011 | MW1: 46012 | MX1: 46013 | MY1: 46014 | MZ1: 46015 | NA1: 46016 | NB1: 46017 | NC1: 46018 | ND1: 46019 | NE1: 46020 | NF1: 46021 | NG1: 46022 | NH1: 46023 | NI1: 46024 | NJ1: 46025 | NK1: 46026 | NL1: 46027 | NM1: 46028 | NN1: 46029 | NO1: 46030 | NP1: 46031 | NQ1: 46032 | NR1: 46033 | NS1: 46034 | NT1: 46035 | NU1: 46036 | NV1: 46037 | NW1: 46038 | NX1: 46039 | NY1: 46040 | NZ1: 46041 | OA1: 46042 | OB1: 46043 | OC1: 46044 | OD1: 46045 | OE1: 46046 | OF1: 46047 | OG1: 46048 | OH1: 46049 | OI1: 46050 | OJ1: 46051 | OK1: 46052 | OL1: 46053 | OM1: 46054 | ON1: 46055 | OO1: 46056 | OP1: 46057 | OQ1: 46058 | OR1: 46059 | OS1: 46060 | OT1: 46061 | OU1: 46062 | OV1: 46063 | OW1: 46064 | OX1: 46065 | OY1: 46066 | OZ1: 46067 | PA1: 46068 | PB1: 46069 | PC1: 46070 | PD1: 46071 | PE1: 46072 | PF1: 46073 | PG1: 46074 | PH1: 46075 | PI1: 46076 | PJ1: 46077 | PK1: 46078 | PL1: 46079 | PM1: 46080 | PN1: 46081 | PO1: 46082 | PP1: 46083 | PQ1: 46084 | PR1: 46085 | PS1: 46086 | PT1: 46087 | PU1: 46088 | PV1: 46089 | PW1: 46090 | PX1: 46091 | PY1: 46092 | PZ1: 46093 | QA1: 46094 | QB1: 46095 | QC1: 46096 | QD1: 46097 | QE1: 46098 | QF1: 46099 | QG1: 46100 | QH1: 46101 | QI1: 46102 | QJ1: 46103 | QK1: 46104 | QL1: 46105 | QM1: 46106 | QN1: 46107 | QO1: 46108 | QP1: 46109 | QQ1: 46110 | QR1: 46111 | QS1: 46112 | QT1: 46113 | QU1: 46114 | QV1: 46115 | QW1: 46116 | QX1: 46117 | QY1: 46118 | QZ1: 46119 | RA1: 46120 | RB1: 46121 | RC1: 46122 | RD1: 46123 | RE1: 46124 | RF1: 46125 | RG1: 46126 | RH1: 46127 | RI1: 46128 | RJ1: 46129 | RK1: 46130 | RL1: 46131 | RM1: 46132 | RN1: 46133 | RO1: 46134 | RP1: 46135 | RQ1: 46136 | RR1: 46137 | RS1: 46138 | RT1: 46139 | RU1: 46140 | RV1: 46141 | RW1: 46142 | RX1: 46143 | RY1: 46144 | RZ1: 46145 | SA1: 46146 | SB1: 46147 | SC1: 46148 | SD1: 46149 | SE1: 46150 | SF1: 46151 | SG1: 46152 | SH1: 46153 | SI1: 46154 | SJ1: 46155 | SK1: 46156 | SL1: 46157 | SM1: 46158 | SN1: 46159 | SO1: 46160 | SP1: 46161 | SQ1: 46162 | SR1: 46163 | SS1: 46164 | ST1: 46165 | SU1: 46166 | SV1: 46167 | SW1: 46168 | SX1: 46169 | SY1: 46170 | SZ1: 46171 | TA1: 46172 | TB1: 46173 | TC1: 46174 | TD1: 46175 | TE1: 46176 | TF1: 46177 | TG1: 46178 | TH1: 46179 | TI1: 46180 | TJ1: 46181 | TK1: 46182 | TL1: 46183 | TM1: 46184 | TN1: 46185 | TO1: 46186 | TP1: 46187 | TQ1: 46188 | TR1: 46189 | TS1: 46190 | TT1: 46191 | TU1: 46192 | TV1: 46193 | TW1: 46194 | TX1: 46195 | TY1: 46196 | TZ1: 46197 | UA1: 46198 | UB1: 46199 | UC1: 46200 | UD1: 46201 | UE1: 46202 | UF1: 46203 | UG1: 46204 | UH1: 46205 | UI1: 46206 | UJ1: 46207 | UK1: 46208 | UL1: 46209 | UM1: 46234 | UN1: 46265 | UO1: 46295 | UP1: 46326 | UQ1: 46356 | UR1: 46387 | US1: 46477 | UT1: 46752
A2: 45658 | B2: 46388 | C2: EDBclose | D2: 万得一致预测:中国:制造业PMI | E2: M0331594 | F2: {=[1]!WSD(E2:E175,C2,A2,B2,"TradingCalendar=SSE","PriceAdj=","rptType=1","Direction=V","Version=1","ShowParams=Y","cols=561;rows=174")} | BM2: 48.4 | CR2: 51.7 | FA2: 49.5 | GE2: 49.3 | HJ2: 49.45 | IO2: 49.25 | JS2: 49.6 | KX2: 49.44 | MB2: 49.3 | NG2: 50.05 | OL2: 50.08 | PN2: 49.31 | QS2: 49.88 | RW2: 50.18 | TB2: 50.25 | UF2: 50.2 | UM2: 50.08
D3: 中国:制造业PMI | E3: M0017126 | AK3: 49.1 | BM3: 50.2 | CR3: 50.5 | DV3: 49 | FA3: 49.5 | GE3: 49.7 | HJ3: 49.3 | IO3: 49.4 | JS3: 49.8 | KX3: 49 | MB3: 49.2 | NG3: 50.1 | OL3: 49.3 | PN3: 49 | QS3: 50.4 | RW3: 50.3 | TB3: 50 | UF3: 50.3
D4: 万得一致预测:中国:非制造业PMI | E4: A9541823 | FA4: 50.6 | GE4: 50.3 | HJ4: 50.4 | IO4: 50.1 | KX4: 50.3 | PN4: 49.85 | QS4: 49.85 | RW4: 49.9 | UF4: 49.85
D5: 中国:制造业PMI:生产 | E5: M0017127 | AK5: 49.8 | BM5: 52.5 | CR5: 52.6 | DV5: 49.8 | FA5: 50.7 | GE5: 51 | HJ5: 50.5 | IO5: 50.8 | JS5: 51.9 | KX5: 49.7 | MB5: 50 | NG5: 51.7 | OL5: 50.6 | PN5: 49.6 | QS5: 51.4 | RW5: 51.5 | TB5: 51.2 | UF5: 51.4
D6: 中国:制造业PMI:新订单 | E6: M0017128 | AK6: 49.2 | BM6: 51.1 | CR6: 51.8 | DV6: 49.2 | FA6: 49.8 | GE6: 50.2 | HJ6: 49.4 | IO6: 49.5 | JS6: 49.7 | KX6: 48.8 | MB6: 49.2 | NG6: 50.8 | OL6: 49.2 | PN6: 48.6 | QS6: 51.6 | RW6: 50.6 | TB6: 49.9 | UF6: 51.2
D7: 中国:制造业PMI:新出口订单 | E7: M0017129 | AK7: 46.4 | BM7: 48.6 | CR7: 49 | DV7: 44.7 | FA7: 47.5 | GE7: 47.7 | HJ7: 47.1 | IO7: 47.2 | JS7: 47.8 | KX7: 45.9 | MB7: 47.6 | NG7: 49 | OL7: 47.8 | PN7: 45 | QS7: 49.1 | RW7: 50.3 | TB7: 48.6 | UF7: 50.1
D8: 中国:非制造业PMI:商务活动 | E8: M0048236 | AK8: 50.2 | BM8: 50.4 | CR8: 50.8 | DV8: 50.4 | FA8: 50.3 | GE8: 50.5 | HJ8: 50.1 | IO8: 50.3 | JS8: 50 | KX8: 50.1 | MB8: 49.5 | NG8: 50.2 | OL8: 49.4 | PN8: 49.5 | QS8: 50.1 | RW8: 49.4 | TB8: 50.1 | UF8: 50.2
D9: 中国:社会消费品零售总额:当月同比(1-2月合并) | E9: M0001428 | BM9: 4 | CR9: 5.9 | DV9: 5.1 | FA9: 6.4 | GE9: 4.8 | HJ9: 3.7 | IO9: 3.4 | JS9: 3 | KX9: 2.9 | MB9: 1.3 | NG9: 0.9 | PN9: 2.8 | QS9: 1.7 | RW9: 0.2 | TB9: -0.6
D10: 万得一致预测:中国:社会消费品零售总额:当月同比 | E10: M0061679 | BM10: 4.5 | CR10: 4.36 | DV10: 5.48 | FA10: 4.84 | GE10: 5.56 | HJ10: 4.87 | IO10: 3.84 | JS10: 3.11 | KX10: 2.62 | MB10: 2.93 | NG10: 1.42 | PN10: 2.8 | QS10: 2.45 | RW10: 2.03 | TB10: 0.09 | UF10: 0.13 | UM10: 1.5
D11: 万得一致预测:中国:固定资产投资完成额:累计同比 | E11: M0061678 | BM11: 3.76 | CR11: 4.03 | DV11: 4.26 | FA11: 3.94 | GE11: 3.73 | HJ11: 2.68 | IO11: 1.29 | JS11: 0.03 | KX11: -0.73 | MB11: -2.16 | NG11: -2.44 | PN11: -2.66 | QS11: 1.65 | RW11: 1.73 | TB11: -1.69 | UF11: -4.77 | UO11: -2.07 | UR11: 0.88 | US11: 3.4
D12: 万得一致预测:中国:固定资产投资完成额:制造业:累计同比 | E12: T2627623 | BM12: 9.23 | CR12: 8.9 | DV12: 9.07 | FA12: 8.5 | GE12: 8.35 | HJ12: 7.17 | IO12: 5.43 | JS12: 4.54 | KX12: 3.44 | MB12: 0.6 | NG12: 1.47 | PN12: 0.03 | QS12: 2.4 | RW12: 4.25 | TB12: 0.1 | UF12: -0.4 | UO12: 0.9 | UR12: 2.7
D13: 万得一致预测:中国:固定资产投资完成额:基础设施建设:累计同比 | E13: L7439791 | BM13: 7.08 | CR13: 7.2 | DV13: 10 | GE13: 8.84 | HJ13: 6.58 | IO13: 5.44 | JS13: 3.45 | KX13: 2.8 | MB13: 1.45 | NG13: 0.8 | PN13: 0.2 | QS13: 7.08 | RW13: 8.23 | TB13: 2.05 | UF13: 0.75 | UO13: 2.55 | UR13: 4.44
D14: 万得一致预测:中国:固定资产投资完成额:房地产开发:累计同比 | E14: V6384553 | BM14: -9.68 | CR14: -10.2 | DV14: -10.1 | FA14: -10.5 | GE14: -11.09 | HJ14: -11.53 | IO14: -12.4 | JS14: -13.36 | KX14: -14.48 | MB14: -15.35 | NG14: -15.91 | PN14: -20.02 | QS14: -13.68 | RW14: -11.25 | TB14: -14.63 | UF14: -17.4 | UO14: -15.25 | UR14: -13.52
D15: 中国:固定资产投资完成额:累计同比 | E15: M0000273 | BM15: 4.1 | CR15: 4.2 | DV15: 4 | FA15: 3.7 | GE15: 2.8 | HJ15: 1.6 | IO15: 0.5 | JS15: -0.5 | KX15: -1.7 | MB15: -2.6 | NG15: -3.8 | PN15: 1.8 | QS15: 1.7 | RW15: -1.6 | TB15: -4.1
D16: 中国:固定资产投资完成额:制造业:累计同比 | E16: M0000357 | BM16: 9 | CR16: 9.1 | DV16: 8.8 | FA16: 8.5 | GE16: 7.5 | HJ16: 6.2 | IO16: 5.1 | JS16: 4 | KX16: 2.7 | MB16: 1.9 | NG16: 0.6 | PN16: 3.1 | QS16: 4.1 | RW16: 1.2 | TB16: -0.4
D17: 中国:固定资产投资完成额:基础设施建设(Wind衍生计算):累计同比 | E17: M5440435 | BM17: 9.95 | CR17: 11.5 | DV17: 10.85 | FA17: 10.42 | GE17: 8.9 | HJ17: 7.29 | IO17: 5.42 | JS17: 3.34 | KX17: 1.51 | MB17: 0.13 | NG17: -1.48 | PN17: 9.76 | QS17: 9.24 | RW17: 4.92 | TB17: 0.75
D18: 中国:固定资产投资完成额:房地产业:累计同比 | E18: M0000449 | BM18: -9.1 | CR18: -10 | DV18: -10.6 | FA18: -11.1 | GE18: -11.5 | HJ18: -12.4 | IO18: -13.2 | JS18: -14 | KX18: -14.9 | MB18: -16 | NG18: -17.5 | PN18: -10.7 | QS18: -10.6 | RW18: -13.4 | TB18: -15.9
D19: 中国:民间固定资产投资完成额:累计同比 | E19: M5438208 | BM19: 0 | CR19: 0.4 | DV19: 0.2 | FA19: 0 | GE19: -0.6 | HJ19: -1.5 | IO19: -2.3 | JS19: -3.1 | KX19: -4.5 | MB19: -5.3 | NG19: -6.4 | PN19: -2.6 | QS19: -2.2 | RW19: -5.2 | TB19: -7.1
D20: 中国:工业增加值:规模以上工业企业:当月同比(1-2月拆分) | E20: M0000545 | AK20: -11.11 | BM20: 31.02 | CR20: 7.7 | DV20: 6.1 | FA20: 5.8 | GE20: 6.8 | HJ20: 5.7 | IO20: 5.2 | JS20: 6.5 | KX20: 4.9 | MB20: 4.8 | NG20: 5.2 | OL20: 6.3 | PN20: 6.3 | QS20: 5.7 | RW20: 4.1 | TB20: 4.5
D21: 中国:出口金额:当月同比 | E21: M0000607 | AK21: 5.895336 | BM21: -3.104739 | CR21: 12.162615 | DV21: 8.023317 | FA21: 4.65278 | GE21: 5.679733 | HJ21: 6.996015 | IO21: 4.235673 | JS21: 8.175012 | KX21: -1.272919 | MB21: 5.811098 | NG21: 6.457242 | OL21: 10 | PN21: 39.6 | QS21: 2.5 | RW21: 14 | TB21: 19.4
D22: 万得一致预测:中国:出口金额:当月同比 | E22: M0061680 | AK22: 1.5 | BM22: 5.13 | CR22: 3.48 | DV22: 0.75 | FA22: 6.24 | GE22: 3.21 | HJ22: 5.88 | IO22: 5.92 | JS22: 5.94 | KX22: 2.95 | MB22: 3.19 | NG22: 2.59 | OL22: 4.68 | PN22: 6 | QS22: 3.96 | RW22: 7.15 | TB22: 12.33 | UF22: 18.51
D23: 中国:PPI:当月同比 | E23: M0001227 | AK23: -2.3 | BM23: -2.2 | CR23: -2.5 | DV23: -2.7 | FA23: -3.3 | GE23: -3.6 | HJ23: -3.6 | IO23: -2.9 | JS23: -2.3 | KX23: -2.1 | MB23: -2.2 | NG23: -1.9 | OL23: -1.4 | PN23: -0.9 | QS23: 0.5 | RW23: 2.8 | TB23: 3.9
D24: 万得一致预测:中国:PPI:当月同比 | E24: M0061677 | AK24: -1.6 | BM24: -2.06 | CR24: -2.19 | DV24: -2.83 | FA24: -3.17 | GE24: -3.23 | HJ24: -3.39 | IO24: -2.88 | JS24: -2.4 | KX24: -2.28 | MB24: -2.03 | NG24: -1.99 | OL24: -1.45 | PN24: -1.14 | QS24: 0.45 | RW24: 1.56 | TB24: 3.53 | UF24: 4.07 | UO24: 4.5 | UR24: -0.65
D25: 中国:CPI:当月同比 | E25: M0000612 | AK25: 0.5 | BM25: -0.7 | CR25: -0.1 | DV25: -0.1 | FA25: -0.1 | GE25: 0.1 | HJ25: 0 | IO25: -0.4 | JS25: -0.3 | KX25: 0.2 | MB25: 0.7 | NG25: 0.8 | OL25: 0.2 | PN25: 1.3 | QS25: 1 | RW25: 1.2 | TB25: 1.2
D26: 万得一致预测:中国:CPI:当月同比 | E26: M0061676 | AK26: 0.3 | BM26: -0.37 | CR26: -0.12 | DV26: -0.15 | FA26: -0.17 | GE26: -0.03 | HJ26: -0.14 | IO26: -0.2 | JS26: -0.15 | KX26: -0.04 | MB26: 0.67 | NG26: 0.76 | OL26: 0.44 | PN26: 0.91 | QS26: 1.27 | RW26: 0.94 | TB26: 1.37 | UF26: 1.18 | UM26: 0.1 | UO26: 0.3 | UR26: 1.2
D27: 中国:人民币存款准备金率:大型存款类金融机构 | E27: M0061518 | AK27: 9.5 | BM27: 9.5 | CR27: 9.5 | DV27: 9.5 | FA27: 9 | GE27: 9 | HJ27: 9 | IO27: 9 | JS27: 9 | KX27: 9 | MB27: 9 | NG27: 9 | OL27: 9 | PN27: 9 | QS27: 9 | RW27: 9 | TB27: 9 | UF27: 9
D28: 中国:央行工具流动性投放情况:常备借贷便利(SLF):净投放 | E28: N7822723 | AK28: -70.9 | BM28: -33.1 | CR28: 12.4 | DV28: -16.4 | FA28: 5 | GE28: 3 | HJ28: -3 | IO28: 2 | JS28: 19 | KX28: -24 | MB28: -3 | NG28: 71 | OL28: -79 | PN28: 0 | QS28: 8 | RW28: -7 | TB28: 9 | UF28: 0
D29: 中国:央行工具流动性投放情况:中期借贷便利(MLF):净投放 | E29: Z0569230 | AK29: -7950 | BM29: -2000 | CR29: 630 | DV29: 5000 | FA29: 3750 | GE29: 1180 | HJ29: 1000 | IO29: 3000 | JS29: 3000 | KX29: 2000 | MB29: 1000 | NG29: 1000 | OL29: 7000 | PN29: 3000 | QS29: 500 | RW29: -2000 | TB29: 1000 | UF29: 2000
D30: 中国:央行工具流动性投放情况:抵押补充贷款(PSL):净投放 | E30: Z7194825 | BM30: -1000 | CR30: -2000 | FA30: -2700 | GE30: -3000 | HJ30: -2300 | IO30: -1608 | JS30: -883 | KX30: -55 | MB30: 254 | NG30: -56 | OL30: 1744 | PN30: 0 | QS30: 0 | RW30: -2000 | TB30: -1545 | UF30: -500
D31: 中国:央行工具流动性投放情况:其他结构性货币政策工具:净投放 | E31: P5747228 | FA31: -107 | GE31: 2018 | HJ31: -12 | IO31: 1005 | JS31: -70 | KX31: -173 | MB31: 1150 | NG31: 1594 | OL31: 641 | PN31: -76 | QS31: 1728 | RW31: 3667 | TB31: 1129 | UF31: -1372
D32: 中国:央行工具流动性投放情况:法定存款准备金率:净投放 | E32: C8808133 | FA32: 10000
D33: 中国:社会融资规模存量:同比 | E33: M5525763 | AK33: 8 | BM33: 8.2 | CR33: 8.4 | DV33: 8.7 | FA33: 8.7 | GE33: 8.9 | HJ33: 9 | IO33: 8.8 | JS33: 8.7 | KX33: 8.5 | MB33: 8.5 | NG33: 8.3 | OL33: 8.2 | PN33: 8.2 | QS33: 7.9 | RW33: 7.8 | TB33: 7.7
D34: 万得一致预测:中国:社会融资规模存量:同比 | E34: X5100205 | AK34: 8.1 | BM34: 8.3 | CR34: 8.15 | DV34: 8.8 | FA34: 8.78 | GE34: 8.81 | HJ34: 9.08 | IO34: 8.85 | JS34: 8.63 | KX34: 8.61 | MB34: 8.45 | NG34: 8.22 | OL34: 8.25 | PN34: 8.07 | QS34: 7.97 | RW34: 7.89 | TB34: 7.59 | UF34: 7.43 | UO34: 7.83 | UR34: 7.94 | US34: 8.3
D35: 中国:社会融资规模存量:人民币贷款:同比 | E35: M5525764 | AK35: 7.2 | BM35: 7.1 | CR35: 7.2 | DV35: 7.1 | FA35: 7 | GE35: 7 | HJ35: 6.8 | IO35: 6.6 | JS35: 6.4 | KX35: 6.3 | MB35: 6.3 | NG35: 6.3 | OL35: 6.1 | PN35: 6.1 | QS35: 5.8 | RW35: 5.6 | TB35: 5.5
D36: 中国:社会融资规模存量:未贴现银行承兑汇票:同比 | E36: M5525768 | AK36: -14.6 | BM36: -14 | CR36: -12.1 | DV36: -7.6 | FA36: -7.4 | GE36: -7.4 | HJ36: -10.4 | IO36: -4.1 | JS36: 4.4 | KX36: -2.2 | MB36: 0.4 | NG36: -0.3 | OL36: 6.7 | PN36: 12.9 | QS36: 2.3 | RW36: -7.9 | TB36: -6.2
D37: 中国:社会融资规模存量:企业债券:同比 | E37: M5525769 | AK37: 4.1 | BM37: 4 | CR37: 2.4 | DV37: 3.2 | FA37: 3.4 | GE37: 3.5 | HJ37: 3.8 | IO37: 3.7 | JS37: 4.5 | KX37: 4.9 | MB37: 5.6 | NG37: 6 | OL37: 6.1 | PN37: 6.2 | QS37: 7.9 | RW37: 8.3 | TB37: 8.4
D38: 中国:社会融资规模存量:政府债券:同比 | E38: M6179510 | AK38: 16.7 | BM38: 18.1 | CR38: 19.4 | DV38: 20.9 | FA38: 20.9 | GE38: 21.3 | HJ38: 21.9 | IO38: 21.1 | JS38: 20.2 | KX38: 19.2 | MB38: 18.8 | NG38: 17.1 | OL38: 17.3 | PN38: 16.6 | QS38: 15.9 | RW38: 15.6 | TB38: 15.1
D39: 中国:M1:同比 | E39: M0001383 | AK39: 0.4 | BM39: 0.1 | CR39: 1.6 | DV39: 1.5 | FA39: 2.3 | GE39: 4.6 | HJ39: 5.6 | IO39: 6 | JS39: 7.2 | KX39: 6.2 | MB39: 4.9 | NG39: 3.8 | OL39: 4.9 | PN39: 5.9 | QS39: 5.1 | RW39: 5 | TB39: 5.5
D40: 万得一致预测:中国:M1:同比 | E40: Y0910594 | BM40: 1.2 | CR40: 0.33 | DV40: 3 | FA40: 1.8 | GE40: 2.44 | HJ40: 5.27 | IO40: 5.87 | JS40: 6 | KX40: 6.55 | MB40: 5 | NG40: 3.77 | OL40: 2.93 | PN40: 5.15 | QS40: 5.23 | RW40: 5 | TB40: 4.8 | UF40: 4.88 | UM40: 3.7 | UN40: 3.8 | UO40: 5 | UP40: 3.4 | UQ40: 3.2 | UR40: 4.8
D41: 中国:M2:同比 | E41: M0001385 | AK41: 7 | BM41: 7 | CR41: 7 | DV41: 8 | FA41: 7.9 | GE41: 8.3 | HJ41: 8.8 | IO41: 8.8 | JS41: 8.4 | KX41: 8.2 | MB41: 8 | NG41: 8.5 | OL41: 9 | PN41: 9 | QS41: 8.5 | RW41: 8.6 | TB41: 8.6
D42: 万得一致预测:中国:M2:同比 | E42: M0061683 | AK42: 8.4 | BM42: 7.04 | CR42: 7.01 | DV42: 7.54 | FA42: 8.08 | GE42: 8.04 | HJ42: 8.3 | IO42: 8.68 | JS42: 8.51 | KX42: 8.04 | MB42: 8.2 | NG42: 7.91 | OL42: 8.42 | PN42: 8.82 | QS42: 8.74 | RW42: 8.42 | TB42: 8.55 | UF42: 8.48 | UO42: 7.6 | UR42: 7.68 | US42: 7.1
D43: 中国:国债收益率:1年 | E43: M0325686 | H43: 1.0676 | I43: 1.0572 | L43: 1.0328 | M43: 1.0602 | N43: 1.1056 | O43: 1.167 | P43: 1.24 | S43: 1.2029 | T43: 1.2149 | U43: 1.212 | V43: 1.2301 | W43: 1.2465 | Z43: 1.2408 | AA43: 1.2607 | AB43: 1.2682 | AC43: 1.2619 | AD43: 1.2714 | AF43: 1.2876 | AG43: 1.2363 | AP43: 1.241 | AQ43: 1.2288 | AR43: 1.2134 | AS43: 1.2101 | AU43: 1.2412 | AV43: 1.2691 | AW43: 1.2556 | AX43: 1.2757 | AY43: 1.319 | BB43: 1.3853 | BC43: 1.4524 | BD43: 1.4464 | BE43: 1.4556 | BF43: 1.4689 | BI43: 1.4769 | BJ43: 1.4751 | BK43: 1.4622 | BL43: 1.4714 | BM43: 1.4981 | BP43: 1.4641 | BQ43: 1.4449 | BR43: 1.4469 | BS43: 1.4699 | BT43: 1.5064 | BW43: 1.5582 | BX43: 1.5814 | BY43: 1.5937 | BZ43: 1.5405 | CA43: 1.5653 | CD43: 1.5693 | CE43: 1.5674 | CF43: 1.5666 | CG43: 1.5478 | CH43: 1.5374 | CK43: 1.5393 | CL43: 1.5218 | CM43: 1.5227 | CN43: 1.5165 | CO43: 1.5161 | CR43: 1.5176 | CS43: 1.5354 | CT43: 1.5451 | CU43: 1.5025 | CY43: 1.4506 | CZ43: 1.4506 | DA43: 1.4559 | DB43: 1.4323 | DC43: 1.3977 | DF43: 1.4028 | DG43: 1.407 | DH43: 1.4174 | DI43: 1.4194 | DJ43: 1.4379 | DM43: 1.4431 | DN43: 1.4399 | DO43: 1.4494 | DP43: 1.4449 | DQ43: 1.4552 | DS43: 1.4637 | DT43: 1.4596 | DU43: 1.4589 | DV43: 1.4553 | EB43: 1.4607 | EC43: 1.4462 | ED43: 1.4155 | EE43: 1.4043 | EH43: 1.4076 | EI43: 1.4296 | EJ43: 1.4177 | EK43: 1.4289 | EL43: 1.4489 | EO43: 1.4453 | EP43: 1.4377 | EQ43: 1.4489 | ER43: 1.4417 | ES43: 1.4519 | EV43: 1.4511 | EW43: 1.4516 | EX43: 1.4678 | EY43: 1.4766 | EZ43: 1.4669 | FD43: 1.464 | FE43: 1.4605 | FF43: 1.4355 | FG43: 1.4156 | FJ43: 1.4119 | FK43: 1.4085 | FL43: 1.4069 | FM43: 1.4072 | FN43: 1.4075 | FQ43: 1.3997 | FR43: 1.3951 | FS43: 1.3749 | FT43: 1.362 | FU43: 1.3646 | FX43: 1.3554 | FY43: 1.3614 | FZ43: 1.3628 | GA43: 1.3637 | GB43: 1.3577 | GE43: 1.3469 | GF43: 1.3427 | GG43: 1.3403 | GH43: 1.3404 | GI43: 1.3377 | GL43: 1.3381 | GM43: 1.348 | GN43: 1.3638 | GO43: 1.3714 | GP43: 1.3834 | GS43: 1.3757 | GT43: 1.3662 | GU43: 1.3623 | GV43: 1.3592 | GW43: 1.3548 | GZ43: 1.3598 | HA43: 1.3514 | HB43: 1.3732 | HC43: 1.3891 | HD43: 1.412 | HG43: 1.3805 | HH43: 1.3788 | HI43: 1.4059 | HJ43: 1.3808 | HK43: 1.3816 | HN43: 1.3592 | HO43: 1.3767 | HP43: 1.3693 | HQ43: 1.364 | HR43: 1.3606 | HU43: 1.356 | HV43: 1.3626 | HW43: 1.3762 | HX43: 1.3677 | HY43: 1.3697 | IB43: 1.3751 | IC43: 1.4016 | ID43: 1.3845 | IE43: 1.3895 | IF43: 1.3905 | II43: 1.3749 | IJ43: 1.3613 | IK43: 1.3612 | IL43: 1.3656 | IM43: 1.3709 | IP43: 1.3681 | IQ43: 1.3659 | IR43: 1.3661 | IS43: 1.3671 | IT43: 1.3826 | IW43: 1.3995 | IX43: 1.397 | IY43: 1.4019 | IZ43: 1.4126 | JA43: 1.3986 | JD43: 1.4014 | JE43: 1.4002 | JF43: 1.3984 | JG43: 1.3924 | JH43: 1.3888 | JK43: 1.3875 | JL43: 1.3945 | JM43: 1.3911 | JN43: 1.4051 | JO43: 1.3918 | JQ43: 1.3933 | JR43: 1.4005 | JS43: 1.3928 | KB43: 1.3825 | KC43: 1.3799 | KD43: 1.3848 | KF43: 1.3871 | KG43: 1.3976 | KH43: 1.4159 | KI43: 1.4217 | KJ43: 1.4126 | KM43: 1.4159 | KN43: 1.4211 | KO43: 1.4165 | KP43: 1.4149 | KQ43: 1.4152 | KT43: 1.3944 | KU43: 1.3822 | KV43: 1.3348 | KW43: 1.3347 | KX43: 1.3313 | LA43: 1.3446 | LB43: 1.3553 | LC43: 1.3581 | LD43: 1.3571 | LE43: 1.3567 | LH43: 1.3582 | LI43: 1.3489 | LJ43: 1.3444 | LK43: 1.342 | LL43: 1.3427 | LO43: 1.3457 | LP43: 1.3431 | LQ43: 1.344 | LR43: 1.342 | LS43: 1.342 | LV43: 1.3408 | LW43: 1.3461 | LX43: 1.3476 | LY43: 1.3557 | LZ43: 1.3538 | MC43: 1.3513 | MD43: 1.3508 | ME43: 1.3457 | MF43: 1.3405 | MG43: 1.3393 | MJ43: 1.3404 | MK43: 1.3369 | ML43: 1.3334 | MM43: 1.3247 | MN43: 1.3906 | MQ43: 1.3862 | MR43: 1.3857 | MS43: 1.3827 | MT43: 1.3771 | MU43: 1.3608 | MX43: 1.359 | MY43: 1.3481 | MZ43: 1.3404 | NA43: 1.3225 | NB43: 1.2881 | NE43: 1.3183 | NF43: 1.3415 | NG43: 1.3418 | NK43: 1.3381 | NL43: 1.3457 | NM43: 1.3516 | NN43: 1.3589 | NO43: 1.3417 | NP43: 1.315 | NS43: 1.2899 | NT43: 1.2845 | NU43: 1.2891 | NV43: 1.2799 | NW43: 1.2761 | NZ43: 1.2603 | OA43: 1.2315 | OB43: 1.2379 | OC43: 1.2402 | OD43: 1.2383 | OG43: 1.2497 | OH43: 1.2512 | OI43: 1.2604 | OJ43: 1.2559 | OK43: 1.2541 | ON43: 1.3101 | OO43: 1.3018 | OP43: 1.2996 | OQ43: 1.3113 | OR43: 1.2999 | OU43: 1.3133 | OV43: 1.3052 | OW43: 1.3034 | OX43: 1.3081 | OY43: 1.3173 | OZ43: 1.3098 | PJ43: 1.3007 | PK43: 1.3091 | PL43: 1.3134 | PM43: 1.3091 | PN43: 1.3084 | PP43: 1.2965 | PQ43: 1.2853 | PR43: 1.2748 | PS43: 1.2753 | PT43: 1.2723 | PW43: 1.2715 | PX43: 1.2727 | PY43: 1.2686 | PZ43: 1.2546 | QA43: 1.2565 | QD43: 1.259 | QE43: 1.2609 | QF43: 1.2524 | QG43: 1.2489 | QH43: 1.2437 | QK43: 1.2456 | QL43: 1.2561 | QM43: 1.2525 | QN43: 1.251 | QO43: 1.2434 | QR43: 1.211 | QS43: 1.2078 | QT43: 1.2285 | QU43: 1.234 | QV43: 1.2263 | QZ43: 1.2148 | RA43: 1.2166 | RB43: 1.2137 | RC43: 1.2158 | RF43: 1.2084 | RG43: 1.2022 | RH43: 1.1858 | RI43: 1.1718 | RJ43: 1.1814 | RM43: 1.1707 | RN43: 1.1574 | RO43: 1.1522 | RP43: 1.1555 | RQ43: 1.1494 | RT43: 1.1543 | RU43: 1.1642 | RV43: 1.1663 | RW43: 1.1573 | SC43: 1.1673 | SD43: 1.1783 | SE43: 1.1801 | SF43: 1.1898 | SH43: 1.1866 | SI43: 1.1874 | SJ43: 1.1918 | SK43: 1.2004 | SL43: 1.1993 | SO43: 1.199 | SP43: 1.1857 | SQ43: 1.1698 | SR43: 1.1666 | SS43: 1.1706 | SV43: 1.1726 | SW43: 1.1709 | SX43: 1.1658 | SY43: 1.1497 | SZ43: 1.1501 | TC43: 1.1387 | TD43: 1.1364 | TE43: 1.1293 | TF43: 1.1307 | TG43: 1.1356 | TJ43: 1.1421 | TK43: 1.1365 | TL43: 1.1483 | TM43: 1.1481 | TN43: 1.158 | TQ43: 1.1654 | TR43: 1.1754 | TS43: 1.1644 | TT43: 1.1453 | TX43: 1.1382 | TY43: 1.1367 | TZ43: 1.1328 | UA43: 1.1141 | UB43: 1.1089 | UE43: 1.1049 | UF43: 1.0999 | UG43: 1.1319 | UH43: 1.1336 | UI43: 1.1365
D44: 中债国债到期收益率:2年 | E44: S0059745 | H44: 1.1011 | I44: 1.0205 | L44: 1.0133 | M44: 1.0483 | N44: 1.0908 | O44: 1.1708 | P44: 1.2112 | S44: 1.2516 | T44: 1.221 | U44: 1.2135 | V44: 1.2366 | W44: 1.2708 | Z44: 1.2755 | AA44: 1.2506 | AB44: 1.2554 | AC44: 1.2804 | AD44: 1.3004 | AF44: 1.3154 | AG44: 1.2515 | AP44: 1.2521 | AQ44: 1.2129 | AR44: 1.237 | AS44: 1.237 | AU44: 1.2721 | AV44: 1.2736 | AW44: 1.2758 | AX44: 1.3023 | AY44: 1.3606 | BB44: 1.3854 | BC44: 1.3916 | BD44: 1.3676 | BE44: 1.4267 | BF44: 1.4706 | BI44: 1.4726 | BJ44: 1.4449 | BK44: 1.4239 | BL44: 1.4639 | BM44: 1.4253 | BP44: 1.3834 | BQ44: 1.4056 | BR44: 1.3995 | BS44: 1.447 | BT44: 1.507 | BW44: 1.5355 | BX44: 1.5975 | BY44: 1.5578 | BZ44: 1.5644 | CA44: 1.5474 | CD44: 1.5774 | CE44: 1.5374 | CF44: 1.6027 | CG44: 1.555 | CH44: 1.5804 | CK44: 1.5863 | CL44: 1.5811 | CM44: 1.561 | CN44: 1.5508 | CO44: 1.5302 | CR44: 1.5663 | CS44: 1.5791 | CT44: 1.5611 | CU44: 1.4853 | CY44: 1.4278 | CZ44: 1.4703 | DA44: 1.4328 | DB44: 1.4053 | DC44: 1.3979 | DF44: 1.4131 | DG44: 1.423 | DH44: 1.4261 | DI44: 1.4413 | DJ44: 1.4495 | DM44: 1.4618 | DN44: 1.4567 | DO44: 1.4725 | DP44: 1.4781 | DQ44: 1.4838 | DS44: 1.4788 | DT44: 1.483 | DU44: 1.4616 | DV44: 1.4507 | EB44: 1.454 | EC44: 1.4415 | ED44: 1.4067 | EE44: 1.4296 | EH44: 1.4375 | EI44: 1.4167 | EJ44: 1.4356 | EK44: 1.454 | EL44: 1.4749 | EO44: 1.4645 | EP44: 1.4834 | EQ44: 1.4775 | ER44: 1.4801 | ES44: 1.4747 | EV44: 1.4676 | EW44: 1.4723 | EX44: 1.4755 | EY44: 1.4875 | EZ44: 1.4617 | FD44: 1.4831 | FE44: 1.462 | FF44: 1.4391 | FG44: 1.4257 | FJ44: 1.4286 | FK44: 1.4331 | FL44: 1.4186 | FM44: 1.4263 | FN44: 1.4132 | FQ44: 1.4032 | FR44: 1.3712 | FS44: 1.3701 | FT44: 1.3701 | FU44: 1.3662 | FX44: 1.3683 | FY44: 1.3733 | FZ44: 1.3728 | GA44: 1.3703 | GB44: 1.3605 | GE44: 1.3635 | GF44: 1.3663 | GG44: 1.3586 | GH44: 1.3611 | GI44: 1.3534 | GL44: 1.3508 | GM44: 1.3633 | GN44: 1.3771 | GO44: 1.3965 | GP44: 1.3995 | GS44: 1.4127 | GT44: 1.3921 | GU44: 1.3875 | GV44: 1.3851 | GW44: 1.3803 | GZ44: 1.3908 | HA44: 1.3934 | HB44: 1.4087 | HC44: 1.4556 | HD44: 1.4355 | HG44: 1.4155 | HH44: 1.4445 | HI44: 1.4289 | HJ44: 1.4195 | HK44: 1.4258 | HN44: 1.4253 | HO44: 1.4253 | HP44: 1.4154 | HQ44: 1.4054 | HR44: 1.3956 | HU44: 1.4061 | HV44: 1.4096 | HW44: 1.3996 | HX44: 1.4023 | HY44: 1.4021 | IB44: 1.4342 | IC44: 1.4273 | ID44: 1.4398 | IE44: 1.4373 | IF44: 1.4341 | II44: 1.4194 | IJ44: 1.417 | IK44: 1.411 | IL44: 1.4184 | IM44: 1.4042 | IP44: 1.3994 | IQ44: 1.3994 | IR44: 1.385 | IS44: 1.4036 | IT44: 1.4081 | IW44: 1.4065 | IX44: 1.4205 | IY44: 1.4298 | IZ44: 1.4177 | JA44: 1.4295 | JD44: 1.4245 | JE44: 1.4095 | JF44: 1.4345 | JG44: 1.4806 | JH44: 1.4859 | JK44: 1.4908 | JL44: 1.5015 | JM44: 1.5163 | JN44: 1.5211 | JO44: 1.5125 | JQ44: 1.5038 | JR44: 1.5081 | JS44: 1.4934 | KB44: 1.4857 | KC44: 1.5016 | KD44: 1.4822 | KF44: 1.4922 | KG44: 1.494 | KH44: 1.4997 | KI44: 1.4981 | KJ44: 1.494 | KM44: 1.5014 | KN44: 1.4961 | KO44: 1.5011 | KP44: 1.4961 | KQ44: 1.4923 | KT44: 1.4814 | KU44: 1.4408 | KV44: 1.4063 | KW44: 1.4067 | KX44: 1.4022 | LA44: 1.4143 | LB44: 1.4233 | LC44: 1.431 | LD44: 1.4342 | LE44: 1.4337 | LH44: 1.4322 | LI44: 1.433 | LJ44: 1.4319 | LK44: 1.428 | LL44: 1.4312 | LO44: 1.4312 | LP44: 1.4311 | LQ44: 1.4299 | LR44: 1.4291 | LS44: 1.4303 | LV44: 1.4313 | LW44: 1.43 | LX44: 1.4342 | LY44: 1.4317 | LZ44: 1.4183 | MC44: 1.4162 | MD44: 1.4166 | ME44: 1.4137 | MF44: 1.4054 | MG44: 1.4036 | MJ44: 1.4034 | MK44: 1.3987 | ML44: 1.3886 | MM44: 1.3919 | MN44: 1.3951 | MQ44: 1.3986 | MR44: 1.4036 | MS44: 1.4001 | MT44: 1.3876 | MU44: 1.3752 | MX44: 1.3652 | MY44: 1.3502 | MZ44: 1.3401 | NA44: 1.3358 | NB44: 1.3378 | NE44: 1.3438 | NF44: 1.3555 | NG44: 1.3605 | NK44: 1.3522 | NL44: 1.3813 | NM44: 1.3988 | NN44: 1.4388 | NO44: 1.4388 | NP44: 1.4362 | NS44: 1.4392 | NT44: 1.4386 | NU44: 1.4344 | NV44: 1.4241 | NW44: 1.4043 | NZ44: 1.4072 | OA44: 1.3949 | OB44: 1.3994 | OC44: 1.4034 | OD44: 1.3959 | OG44: 1.4034 | OH44: 1.4098 | OI44: 1.3988 | OJ44: 1.3908 | OK44: 1.3765 | ON44: 1.3852 | OO44: 1.3772 | OP44: 1.3769 | OQ44: 1.3634 | OR44: 1.3597 | OU44: 1.3577 | OV44: 1.3552 | OW44: 1.358 | OX44: 1.3576 | OY44: 1.3577 | OZ44: 1.3542 | PJ44: 1.3569 | PK44: 1.3608 | PL44: 1.3657 | PM44: 1.3638 | PN44: 1.3589 | PP44: 1.3579 | PQ44: 1.3508 | PR44: 1.3349 | PS44: 1.3486 | PT44: 1.3432 | PW44: 1.3605 | PX44: 1.3622 | PY44: 1.3639 | PZ44: 1.3614 | QA44: 1.3532 | QD44: 1.3593 | QE44: 1.3393 | QF44: 1.3205 | QG44: 1.3106 | QH44: 1.3087 | QK44: 1.3163 | QL44: 1.3112 | QM44: 1.3123 | QN44: 1.3023 | QO44: 1.2964 | QR44: 1.2672 | QS44: 1.2746 | QT44: 1.285 | QU44: 1.2899 | QV44: 1.3033 | QZ44: 1.3023 | RA44: 1.3215 | RB44: 1.3266 | RC44: 1.3289 | RF44: 1.3271 | RG44: 1.3204 | RH44: 1.3108 | RI44: 1.3084 | RJ44: 1.2936 | RM44: 1.2923 | RN44: 1.2812 | RO44: 1.2601 | RP44: 1.255 | RQ44: 1.2393 | RT44: 1.259 | RU44: 1.264 | RV44: 1.2565 | RW44: 1.2552 | SC44: 1.2802 | SD44: 1.2721 | SE44: 1.2808 | SF44: 1.2777 | SH44: 1.2779 | SI44: 1.2776 | SJ44: 1.2717 | SK44: 1.2743 | SL44: 1.2733 | SO44: 1.2684 | SP44: 1.2617 | SQ44: 1.2552 | SR44: 1.2583 | SS44: 1.2623 | SV44: 1.2561 | SW44: 1.2513 | SX44: 1.2378 | SY44: 1.2264 | SZ44: 1.2256 | TC44: 1.2276 | TD44: 1.2285 | TE44: 1.2352 | TF44: 1.2369 | TG44: 1.2376 | TJ44: 1.2587 | TK44: 1.2706 | TL44: 1.28 | TM44: 1.2881 | TN44: 1.2937 | TQ44: 1.3012 | TR44: 1.2832 | TS44: 1.2662 | TT44: 1.2437 | TX44: 1.2462 | TY44: 1.2637 | TZ44: 1.2562 | UA44: 1.2527 | UB44: 1.2462 | UE44: 1.2362 | UF44: 1.2467 | UG44: 1.257 | UH44: 1.2471 | UI44: 1.2473
D45: 中债国债到期收益率:3年 | E45: S0059746 | H45: 1.1694 | I45: 1.1122 | L45: 1.1196 | M45: 1.1558 | N45: 1.1833 | O45: 1.2412 | P45: 1.2577 | S45: 1.3039 | T45: 1.2907 | U45: 1.2578 | V45: 1.2803 | W45: 1.2806 | Z45: 1.3059 | AA45: 1.281 | AB45: 1.281 | AC45: 1.3028 | AD45: 1.3437 | AF45: 1.3337 | AG45: 1.3108 | AP45: 1.309 | AQ45: 1.2871 | AR45: 1.2796 | AS45: 1.2758 | AU45: 1.3092 | AV45: 1.2967 | AW45: 1.3086 | AX45: 1.3272 | AY45: 1.3747 | BB45: 1.3939 | BC45: 1.4289 | BD45: 1.4239 | BE45: 1.4639 | BF45: 1.4839 | BI45: 1.5239 | BJ45: 1.5175 | BK45: 1.4975 | BL45: 1.5354 | BM45: 1.5182 | BP45: 1.4814 | BQ45: 1.4965 | BR45: 1.5016 | BS45: 1.5468 | BT45: 1.5923 | BW45: 1.6123 | BX45: 1.6777 | BY45: 1.6415 | BZ45: 1.6222 | CA45: 1.6214 | CD45: 1.6871 | CE45: 1.6676 | CF45: 1.6607 | CG45: 1.6188 | CH45: 1.636 | CK45: 1.6387 | CL45: 1.6339 | CM45: 1.614 | CN45: 1.5988 | CO45: 1.5876 | CR45: 1.606 | CS45: 1.6268 | CT45: 1.5985 | CU45: 1.5263 | CY45: 1.4664 | CZ45: 1.5062 | DA45: 1.4689 | DB45: 1.4387 | DC45: 1.4315 | DF45: 1.4605 | DG45: 1.4621 | DH45: 1.4618 | DI45: 1.4741 | DJ45: 1.4822 | DM45: 1.4945 | DN45: 1.4866 | DO45: 1.5018 | DP45: 1.5208 | DQ45: 1.5192 | DS45: 1.523 | DT45: 1.5177 | DU45: 1.5009 | DV45: 1.4766 | EB45: 1.4939 | EC45: 1.4815 | ED45: 1.4504 | EE45: 1.4633 | EH45: 1.4661 | EI45: 1.4533 | EJ45: 1.4727 | EK45: 1.5048 | EL45: 1.507 | EO45: 1.4973 | EP45: 1.5041 | EQ45: 1.4997 | ER45: 1.4958 | ES45: 1.4956 | EV45: 1.4944 | EW45: 1.499 | EX45: 1.5002 | EY45: 1.5153 | EZ45: 1.4777 | FD45: 1.4877 | FE45: 1.4703 | FF45: 1.4555 | FG45: 1.4354 | FJ45: 1.4354 | FK45: 1.4509 | FL45: 1.4385 | FM45: 1.4408 | FN45: 1.4258 | FQ45: 1.4054 | FR45: 1.3808 | FS45: 1.3889 | FT45: 1.397 | FU45: 1.4 | FX45: 1.4028 | FY45: 1.4133 | FZ45: 1.4108 | GA45: 1.4057 | GB45: 1.3931 | GE45: 1.3959 | GF45: 1.3985 | GG45: 1.391 | GH45: 1.3772 | GI45: 1.3791 | GL45: 1.3813 | GM45: 1.3884 | GN45: 1.3942 | GO45: 1.4098 | GP45: 1.4158 | GS45: 1.4267 | GT45: 1.4108 | GU45: 1.4116 | GV45: 1.4114 | GW45: 1.4043 | GZ45: 1.4202 | HA45: 1.4229 | HB45: 1.4467 | HC45: 1.4744 | HD45: 1.4777 | HG45: 1.455 | HH45: 1.4793 | HI45: 1.4558 | HJ45: 1.443 | HK45: 1.4451 | HN45: 1.4392 | HO45: 1.4392 | HP45: 1.4295 | HQ45: 1.4227 | HR45: 1.4159 | HU45: 1.4321 | HV45: 1.4257 | HW45: 1.4092 | HX45: 1.4154 | HY45: 1.4091 | IB45: 1.4466 | IC45: 1.4907 | ID45: 1.5059 | IE45: 1.5112 | IF45: 1.5064 | II45: 1.5022 | IJ45: 1.4973 | IK45: 1.4925 | IL45: 1.4977 | IM45: 1.4776 | IP45: 1.4776 | IQ45: 1.4751 | IR45: 1.4701 | IS45: 1.4751 | IT45: 1.4876 | IW45: 1.495 | IX45: 1.495 | IY45: 1.5048 | IZ45: 1.4923 | JA45: 1.4973 | JD45: 1.4973 | JE45: 1.5083 | JF45: 1.4953 | JG45: 1.5053 | JH45: 1.5124 | JK45: 1.5049 | JL45: 1.5245 | JM45: 1.5335 | JN45: 1.5336 | JO45: 1.5401 | JQ45: 1.5359 | JR45: 1.5349 | JS45: 1.5204 | KB45: 1.5144 | KC45: 1.5198 | KD45: 1.5029 | KF45: 1.5114 | KG45: 1.5102 | KH45: 1.5183 | KI45: 1.5203 | KJ45: 1.514 | KM45: 1.536 | KN45: 1.5311 | KO45: 1.5332 | KP45: 1.5325 | KQ45: 1.5294 | KT45: 1.5169 | KU45: 1.4655 | KV45: 1.4254 | KW45: 1.4132 | KX45: 1.4146 | LA45: 1.4211 | LB45: 1.4311 | LC45: 1.4452 | LD45: 1.4479 | LE45: 1.4449 | LH45: 1.4449 | LI45: 1.4384 | LJ45: 1.438 | LK45: 1.4405 | LL45: 1.4397 | LO45: 1.4381 | LP45: 1.4381 | LQ45: 1.4386 | LR45: 1.4356 | LS45: 1.4348 | LV45: 1.4348 | LW45: 1.4338 | LX45: 1.4368 | LY45: 1.4501 | LZ45: 1.4351 | MC45: 1.4353 | MD45: 1.4369 | ME45: 1.4329 | MF45: 1.4357 | MG45: 1.4205 | MJ45: 1.4155 | MK45: 1.4131 | ML45: 1.4109 | MM45: 1.4109 | MN45: 1.4161 | MQ45: 1.4214 | MR45: 1.4213 | MS45: 1.4136 | MT45: 1.3986 | MU45: 1.3941 | MX45: 1.3951 | MY45: 1.3856 | MZ45: 1.3784 | NA45: 1.3682 | NB45: 1.3627 | NE45: 1.3762 | NF45: 1.378 | NG45: 1.383 | NK45: 1.3752 | NL45: 1.4063 | NM45: 1.4406 | NN45: 1.475 | NO45: 1.4576 | NP45: 1.4606 | NS45: 1.4601 | NT45: 1.4603 | NU45: 1.4611 | NV45: 1.4485 | NW45: 1.4286 | NZ45: 1.432 | OA45: 1.4196 | OB45: 1.4218 | OC45: 1.4304 | OD45: 1.4223 | OG45: 1.42 | OH45: 1.4231 | OI45: 1.416 | OJ45: 1.4063 | OK45: 1.4014 | ON45: 1.3996 | OO45: 1.3893 | OP45: 1.3896 | OQ45: 1.3806 | OR45: 1.3809 | OU45: 1.3788 | OV45: 1.3788 | OW45: 1.3788 | OX45: 1.3759 | OY45: 1.3761 | OZ45: 1.3742 | PJ45: 1.3744 | PK45: 1.3806 | PL45: 1.3856 | PM45: 1.3826 | PN45: 1.3776 | PP45: 1.3727 | PQ45: 1.3628 | PR45: 1.358 | PS45: 1.3629 | PT45: 1.3629 | PW45: 1.3742 | PX45: 1.3782 | PY45: 1.3781 | PZ45: 1.3754 | QA45: 1.3704 | QD45: 1.3771 | QE45: 1.3641 | QF45: 1.3521 | QG45: 1.3471 | QH45: 1.3451 | QK45: 1.3563 | QL45: 1.3481 | QM45: 1.3428 | QN45: 1.3356 | QO45: 1.3228 | QR45: 1.2931 | QS45: 1.3088 | QT45: 1.3326 | QU45: 1.3296 | QV45: 1.3339 | QZ45: 1.343 | RA45: 1.3605 | RB45: 1.3597 | RC45: 1.3594 | RF45: 1.3569 | RG45: 1.3525 | RH45: 1.3427 | RI45: 1.3397 | RJ45: 1.325 | RM45: 1.3259 | RN45: 1.3199 | RO45: 1.3031 | RP45: 1.2926 | RQ45: 1.2779 | RT45: 1.2959 | RU45: 1.296 | RV45: 1.2745 | RW45: 1.2802 | SC45: 1.2882 | SD45: 1.289 | SE45: 1.2942 | SF45: 1.2954 | SH45: 1.2922 | SI45: 1.289 | SJ45: 1.2897 | SK45: 1.2952 | SL45: 1.2917 | SO45: 1.2932 | SP45: 1.2889 | SQ45: 1.2882 | SR45: 1.2874 | SS45: 1.302 | SV45: 1.2976 | SW45: 1.2976 | SX45: 1.2803 | SY45: 1.2628 | SZ45: 1.2705 | TC45: 1.2709 | TD45: 1.2762 | TE45: 1.2838 | TF45: 1.2814 | TG45: 1.2839 | TJ45: 1.2942 | TK45: 1.3018 | TL45: 1.3066 | TM45: 1.3141 | TN45: 1.3141 | TQ45: 1.3156 | TR45: 1.3063 | TS45: 1.2971 | TT45: 1.2854 | TX45: 1.2938 | TY45: 1.2979 | TZ45: 1.3003 | UA45: 1.2926 | UB45: 1.289 | UE45: 1.2734 | UF45: 1.2923 | UG45: 1.3052 | UH45: 1.2927 | UI45: 1.2901
D46: 中债国开债到期收益率:3年 | E46: M1004265 | H46: 1.4075 | I46: 1.39 | L46: 1.415 | M46: 1.455 | N46: 1.4725 | O46: 1.508 | P46: 1.5055 | S46: 1.545 | T46: 1.48 | U46: 1.485 | V46: 1.51 | W46: 1.515 | Z46: 1.5175 | AA46: 1.4975 | AB46: 1.5 | AC46: 1.54 | AD46: 1.5425 | AF46: 1.5427 | AG46: 1.4877 | AP46: 1.4827 | AQ46: 1.4627 | AR46: 1.4727 | AS46: 1.4747 | AU46: 1.5174 | AV46: 1.5251 | AW46: 1.5351 | AX46: 1.5551 | AY46: 1.5903 | BB46: 1.6153 | BC46: 1.6303 | BD46: 1.6153 | BE46: 1.6518 | BF46: 1.6868 | BI46: 1.7343 | BJ46: 1.713 | BK46: 1.7055 | BL46: 1.7405 | BM46: 1.7249 | BP46: 1.6767 | BQ46: 1.6792 | BR46: 1.6792 | BS46: 1.7142 | BT46: 1.7598 | BW46: 1.7648 | BX46: 1.8148 | BY46: 1.7523 | BZ46: 1.7422 | CA46: 1.713 | CD46: 1.7568 | CE46: 1.7468 | CF46: 1.7368 | CG46: 1.7396 | CH46: 1.74 | CK46: 1.7399 | CL46: 1.7397 | CM46: 1.7297 | CN46: 1.7442 | CO46: 1.7393 | CR46: 1.7443 | CS46: 1.7568 | CT46: 1.7343 | CU46: 1.6688 | CY46: 1.6056 | CZ46: 1.6785 | DA46: 1.661 | DB46: 1.6479 | DC46: 1.6171 | DF46: 1.6171 | DG46: 1.6321 | DH46: 1.6246 | DI46: 1.6439 | DJ46: 1.6489 | DM46: 1.6539 | DN46: 1.6481 | DO46: 1.6593 | DP46: 1.6643 | DQ46: 1.6643 | DS46: 1.6635 | DT46: 1.6618 | DU46: 1.6412 | DV46: 1.6335 | EB46: 1.6412 | EC46: 1.6336 | ED46: 1.5936 | EE46: 1.5841 | EH46: 1.6032 | EI46: 1.5809 | EJ46: 1.5922 | EK46: 1.6084 | EL46: 1.6144 | EO46: 1.6108 | EP46: 1.6073 | EQ46: 1.6149 | ER46: 1.6171 | ES46: 1.6154 | EV46: 1.6104 | EW46: 1.6204 | EX46: 1.6304 | EY46: 1.6404 | EZ46: 1.6304 | FD46: 1.6392 | FE46: 1.6292 | FF46: 1.6217 | FG46: 1.6042 | FJ46: 1.6017 | FK46: 1.6017 | FL46: 1.5942 | FM46: 1.6042 | FN46: 1.602 | FQ46: 1.6045 | FR46: 1.5857 | FS46: 1.5832 | FT46: 1.5782 | FU46: 1.5782 | FX46: 1.5782 | FY46: 1.5907 | FZ46: 1.5907 | GA46: 1.5807 | GB46: 1.5757 | GE46: 1.5807 | GF46: 1.5657 | GG46: 1.5557 | GH46: 1.5572 | GI46: 1.5557 | GL46: 1.5582 | GM46: 1.5682 | GN46: 1.5732 | GO46: 1.5922 | GP46: 1.5972 | GS46: 1.6072 | GT46: 1.6 | GU46: 1.6 | GV46: 1.6025 | GW46: 1.6 | GZ46: 1.6125 | HA46: 1.6225 | HB46: 1.64 | HC46: 1.68 | HD46: 1.675 | HG46: 1.66 | HH46: 1.675 | HI46: 1.6625 | HJ46: 1.64 | HK46: 1.64 | HN46: 1.645 | HO46: 1.65 | HP46: 1.6425 | HQ46: 1.64 | HR46: 1.63 | HU46: 1.645 | HV46: 1.66 | HW46: 1.6525 | HX46: 1.66 | HY46: 1.67 | IB46: 1.72 | IC46: 1.705 | ID46: 1.7125 | IE46: 1.7006 | IF46: 1.6955 | II46: 1.683 | IJ46: 1.6769 | IK46: 1.6769 | IL46: 1.7019 | IM46: 1.6916 | IP46: 1.6846 | IQ46: 1.6744 | IR46: 1.6619 | IS46: 1.6644 | IT46: 1.6794 | IW46: 1.7019 | IX46: 1.7207 | IY46: 1.7504 | IZ46: 1.7461 | JA46: 1.7411 | JD46: 1.7656 | JE46: 1.78 | JF46: 1.76 | JG46: 1.7701 | JH46: 1.7807 | JK46: 1.7708 | JL46: 1.7838 | JM46: 1.7923 | JN46: 1.802 | JO46: 1.8009 | JQ46: 1.7954 | JR46: 1.7996 | JS46: 1.7796 | KB46: 1.7802 | KC46: 1.7827 | KD46: 1.7613 | KF46: 1.7813 | KG46: 1.7826 | KH46: 1.7888 | KI46: 1.7955 | KJ46: 1.7852 | KM46: 1.794 | KN46: 1.7925 | KO46: 1.7822 | KP46: 1.7816 | KQ46: 1.7813 | KT46: 1.7738 | KU46: 1.745 | KV46: 1.7275 | KW46: 1.7231 | KX46: 1.7206 | LA46: 1.7256 | LB46: 1.7287 | LC46: 1.7248 | LD46: 1.7363 | LE46: 1.7516 | LH46: 1.7456 | LI46: 1.7399 | LJ46: 1.731 | LK46: 1.7303 | LL46: 1.724 | LO46: 1.7159 | LP46: 1.7158 | LQ46: 1.7185 | LR46: 1.7165 | LS46: 1.7159 | LV46: 1.7107 | LW46: 1.7136 | LX46: 1.7244 | LY46: 1.7266 | LZ46: 1.7189 | MC46: 1.7097 | MD46: 1.7099 | ME46: 1.7206 | MF46: 1.7641 | MG46: 1.7642 | MJ46: 1.7644 | MK46: 1.7433 | ML46: 1.735 | MM46: 1.7282 | MN46: 1.7348 | MQ46: 1.7373 | MR46: 1.732 | MS46: 1.7152 | MT46: 1.7002 | MU46: 1.6802 | MX46: 1.6827 | MY46: 1.6702 | MZ46: 1.671 | NA46: 1.676 | NB46: 1.6744 | NE46: 1.6894 | NF46: 1.6975 | NG46: 1.6969 | NK46: 1.6911 | NL46: 1.7011 | NM46: 1.7211 | NN46: 1.7361 | NO46: 1.7261 | NP46: 1.7261 | NS46: 1.7236 | NT46: 1.7236 | NU46: 1.721 | NV46: 1.718 | NW46: 1.7085 | NZ46: 1.711 | OA46: 1.706 | OB46: 1.7085 | OC46: 1.7135 | OD46: 1.701 | OG46: 1.701 | OH46: 1.7035 | OI46: 1.6972 | OJ46: 1.6922 | OK46: 1.6922 | ON46: 1.6931 | OO46: 1.6916 | OP46: 1.6916 | OQ46: 1.6802 | OR46: 1.6702 | OU46: 1.6602 | OV46: 1.6652 | OW46: 1.6677 | OX46: 1.6604 | OY46: 1.6604 | OZ46: 1.6585 | PJ46: 1.6576 | PK46: 1.6701 | PL46: 1.6801 | PM46: 1.6725 | PN46: 1.6695 | PP46: 1.6543 | PQ46: 1.6443 | PR46: 1.6268 | PS46: 1.6293 | PT46: 1.6293 | PW46: 1.6493 | PX46: 1.6418 | PY46: 1.6443 | PZ46: 1.6268 | QA46: 1.6143 | QD46: 1.6193 | QE46: 1.6118 | QF46: 1.5951 | QG46: 1.5939 | QH46: 1.5922 | QK46: 1.6009 | QL46: 1.6078 | QM46: 1.6052 | QN46: 1.597 | QO46: 1.5861 | QR46: 1.5646 | QS46: 1.5703 | QT46: 1.5803 | QU46: 1.5715 | QV46: 1.5595 | QZ46: 1.5645 | RA46: 1.577 | RB46: 1.5887 | RC46: 1.5895 | RF46: 1.5908 | RG46: 1.5903 | RH46: 1.5733 | RI46: 1.5633 | RJ46: 1.5482 | RM46: 1.5537 | RN46: 1.5484 | RO46: 1.5433 | RP46: 1.5446 | RQ46: 1.5458 | RT46: 1.5581 | RU46: 1.5506 | RV46: 1.5381 | RW46: 1.5406 | SC46: 1.5481 | SD46: 1.5386 | SE46: 1.5354 | SF46: 1.5304 | SH46: 1.5221 | SI46: 1.5137 | SJ46: 1.5079 | SK46: 1.5069 | SL46: 1.5069 | SO46: 1.5032 | SP46: 1.5079 | SQ46: 1.5072 | SR46: 1.511 | SS46: 1.506 | SV46: 1.4983 | SW46: 1.4758 | SX46: 1.4608 | SY46: 1.4528 | SZ46: 1.4528 | TC46: 1.446 | TD46: 1.451 | TE46: 1.4527 | TF46: 1.4452 | TG46: 1.4502 | TJ46: 1.4502 | TK46: 1.4602 | TL46: 1.4667 | TM46: 1.4817 | TN46: 1.4817 | TQ46: 1.4867 | TR46: 1.4749 | TS46: 1.4697 | TT46: 1.4597 | TX46: 1.4656 | TY46: 1.4676 | TZ46: 1.4613 | UA46: 1.4567 | UB46: 1.4546 | UE46: 1.4438 | UF46: 1.4613 | UG46: 1.477 | UH46: 1.4731 | UI46: 1.4701
D47: 中债国开债到期收益率:1年 | E47: M1004263 | H47: 1.2618 | I47: 1.2818 | L47: 1.2918 | M47: 1.3418 | N47: 1.35 | O47: 1.36 | P47: 1.3805 | S47: 1.4101 | T47: 1.3901 | U47: 1.3902 | V47: 1.4352 | W47: 1.4601 | Z47: 1.4502 | AA47: 1.4502 | AB47: 1.4304 | AC47: 1.4804 | AD47: 1.4804 | AF47: 1.4951 | AG47: 1.4482 | AP47: 1.4434 | AQ47: 1.4308 | AR47: 1.4309 | AS47: 1.4308 | AU47: 1.477 | AV47: 1.507 | AW47: 1.492 | AX47: 1.512 | AY47: 1.5217 | BB47: 1.5426 | BC47: 1.5876 | BD47: 1.5776 | BE47: 1.6022 | BF47: 1.6322 | BI47: 1.6522 | BJ47: 1.6822 | BK47: 1.6622 | BL47: 1.6922 | BM47: 1.6822 | BP47: 1.6622 | BQ47: 1.6422 | BR47: 1.6422 | BS47: 1.6522 | BT47: 1.6822 | BW47: 1.693 | BX47: 1.713 | BY47: 1.688 | BZ47: 1.688 | CA47: 1.678 | CD47: 1.698 | CE47: 1.693 | CF47: 1.6968 | CG47: 1.6823 | CH47: 1.6523 | CK47: 1.6523 | CL47: 1.6448 | CM47: 1.6423 | CN47: 1.6523 | CO47: 1.6473 | CR47: 1.6373 | CS47: 1.6423 | CT47: 1.6423 | CU47: 1.5948 | CY47: 1.5573 | CZ47: 1.6148 | DA47: 1.5948 | DB47: 1.5806 | DC47: 1.5551 | DF47: 1.5602 | DG47: 1.5752 | DH47: 1.5702 | DI47: 1.5752 | DJ47: 1.5703 | DM47: 1.5756 | DN47: 1.5681 | DO47: 1.5683 | DP47: 1.5708 | DQ47: 1.5684 | DS47: 1.5698 | DT47: 1.571 | DU47: 1.5708 | DV47: 1.5656 | EB47: 1.5659 | EC47: 1.5312 | ED47: 1.4821 | EE47: 1.4747 | EH47: 1.4773 | EI47: 1.4776 | EJ47: 1.4853 | EK47: 1.4877 | EL47: 1.5052 | EO47: 1.505 | EP47: 1.5 | EQ47: 1.51 | ER47: 1.5125 | ES47: 1.515 | EV47: 1.53 | EW47: 1.5325 | EX47: 1.55 | EY47: 1.5575 | EZ47: 1.53 | FD47: 1.54 | FE47: 1.5325 | FF47: 1.5299 | FG47: 1.505 | FJ47: 1.495 | FK47: 1.4975 | FL47: 1.495 | FM47: 1.5 | FN47: 1.5005 | FQ47: 1.505 | FR47: 1.4925 | FS47: 1.4925 | FT47: 1.49 | FU47: 1.485 | FX47: 1.48 | FY47: 1.4925 | FZ47: 1.4975 | GA47: 1.49 | GB47: 1.4775 | GE47: 1.475 | GF47: 1.47 | GG47: 1.4575 | GH47: 1.4474 | GI47: 1.446 | GL47: 1.4495 | GM47: 1.465 | GN47: 1.48 | GO47: 1.4914 | GP47: 1.4946 | GS47: 1.4974 | GT47: 1.4849 | GU47: 1.4842 | GV47: 1.4801 | GW47: 1.4789 | GZ47: 1.4851 | HA47: 1.4886 | HB47: 1.4943 | HC47: 1.5319 | HD47: 1.5219 | HG47: 1.5078 | HH47: 1.5192 | HI47: 1.5092 | HJ47: 1.4992 | HK47: 1.4967 | HN47: 1.4967 | HO47: 1.4992 | HP47: 1.4991 | HQ47: 1.4988 | HR47: 1.4951 | HU47: 1.5026 | HV47: 1.527 | HW47: 1.5223 | HX47: 1.5219 | HY47: 1.5258 | IB47: 1.5577 | IC47: 1.5678 | ID47: 1.5663 | IE47: 1.5639 | IF47: 1.5655 | II47: 1.5564 | IJ47: 1.5376 | IK47: 1.5376 | IL47: 1.5391 | IM47: 1.5346 | IP47: 1.5334 | IQ47: 1.534 | IR47: 1.5338 | IS47: 1.5331 | IT47: 1.5415 | IW47: 1.5615 | IX47: 1.5733 | IY47: 1.584 | IZ47: 1.5755 | JA47: 1.578 | JD47: 1.5932 | JE47: 1.5929 | JF47: 1.5917 | JG47: 1.6017 | JH47: 1.6264 | JK47: 1.6297 | JL47: 1.6433 | JM47: 1.6466 | JN47: 1.657 | JO47: 1.6219 | JQ47: 1.6232 | JR47: 1.6202 | JS47: 1.6002 | KB47: 1.6162 | KC47: 1.6173 | KD47: 1.6108 | KF47: 1.6251 | KG47: 1.6356 | KH47: 1.6383 | KI47: 1.6354 | KJ47: 1.625 | KM47: 1.6308 | KN47: 1.6406 | KO47: 1.6423 | KP47: 1.644 | KQ47: 1.642 | KT47: 1.639 | KU47: 1.6245 | KV47: 1.6095 | KW47: 1.597 | KX47: 1.587 | LA47: 1.597 | LB47: 1.605 | LC47: 1.607 | LD47: 1.6121 | LE47: 1.6121 | LH47: 1.6171 | LI47: 1.6121 | LJ47: 1.6101 | LK47: 1.6121 | LL47: 1.6121 | LO47: 1.6131 | LP47: 1.6171 | LQ47: 1.6196 | LR47: 1.6201 | LS47: 1.6191 | LV47: 1.6221 | LW47: 1.6231 | LX47: 1.6301 | LY47: 1.6321 | LZ47: 1.6246 | MC47: 1.6251 | MD47: 1.6251 | ME47: 1.6296 | MF47: 1.6421 | MG47: 1.6296 | MJ47: 1.6296 | MK47: 1.6171 | ML47: 1.6153 | MM47: 1.6081 | MN47: 1.6097 | MQ47: 1.609 | MR47: 1.604 | MS47: 1.6015 | MT47: 1.5925 | MU47: 1.5725 | MX47: 1.5725 | MY47: 1.56 | MZ47: 1.555 | NA47: 1.53 | NB47: 1.5275 | NE47: 1.545 | NF47: 1.55 | NG47: 1.55 | NK47: 1.5525 | NL47: 1.5765 | NM47: 1.5765 | NN47: 1.579 | NO47: 1.5783 | NP47: 1.5779 | NS47: 1.5853 | NT47: 1.5885 | NU47: 1.5985 | NV47: 1.5987 | NW47: 1.5942 | NZ47: 1.6004 | OA47: 1.5958 | OB47: 1.5987 | OC47: 1.5939 | OD47: 1.5759 | OG47: 1.577 | OH47: 1.5822 | OI47: 1.5827 | OJ47: 1.5801 | OK47: 1.5833 | ON47: 1.5856 | OO47: 1.5897 | OP47: 1.5876 | OQ47: 1.5783 | OR47: 1.5701 | OU47: 1.5709 | OV47: 1.5757 | OW47: 1.5795 | OX47: 1.5732 | OY47: 1.5638 | OZ47: 1.5647 | PJ47: 1.5703 | PK47: 1.5785 | PL47: 1.582 | PM47: 1.5744 | PN47: 1.5694 | PP47: 1.5589 | PQ47: 1.5439 | PR47: 1.5101 | PS47: 1.5104 | PT47: 1.5056 | PW47: 1.5161 | PX47: 1.5131 | PY47: 1.5117 | PZ47: 1.5017 | QA47: 1.4892 | QD47: 1.4947 | QE47: 1.4855 | QF47: 1.4851 | QG47: 1.4705 | QH47: 1.4709 | QK47: 1.4633 | QL47: 1.4658 | QM47: 1.4743 | QN47: 1.4696 | QO47: 1.4602 | QR47: 1.4456 | QS47: 1.4369 | QT47: 1.4394 | QU47: 1.4289 | QV47: 1.412 | QZ47: 1.4076 | RA47: 1.4235 | RB47: 1.431 | RC47: 1.4275 | RF47: 1.427 | RG47: 1.4291 | RH47: 1.4241 | RI47: 1.3991 | RJ47: 1.3991 | RM47: 1.4041 | RN47: 1.3991 | RO47: 1.3791 | RP47: 1.3791 | RQ47: 1.3691 | RT47: 1.4041 | RU47: 1.3865 | RV47: 1.3765 | RW47: 1.3691 | SC47: 1.3841 | SD47: 1.3841 | SE47: 1.3741 | SF47: 1.3707 | SH47: 1.3688 | SI47: 1.3663 | SJ47: 1.3663 | SK47: 1.3663 | SL47: 1.3663 | SO47: 1.3638 | SP47: 1.3588 | SQ47: 1.3538 | SR47: 1.3588 | SS47: 1.3588 | SV47: 1.3581 | SW47: 1.3521 | SX47: 1.3471 | SY47: 1.3471 | SZ47: 1.3521 | TC47: 1.3521 | TD47: 1.3521 | TE47: 1.3542 | TF47: 1.3555 | TG47: 1.3576 | TJ47: 1.3683 | TK47: 1.3718 | TL47: 1.3744 | TM47: 1.3745 | TN47: 1.3814 | TQ47: 1.3796 | TR47: 1.3846 | TS47: 1.3774 | TT47: 1.375 | TX47: 1.3775 | TY47: 1.3909 | TZ47: 1.3864 | UA47: 1.3764 | UB47: 1.3761 | UE47: 1.3456 | UF47: 1.3484 | UG47: 1.3616 | UH47: 1.3616 | UI47: 1.3566
D48: 中债企业债到期收益率(AAA):1年 | E48: S0059771 | H48: 1.6435 | I48: 1.6322 | L48: 1.6172 | M48: 1.6276 | N48: 1.6343 | O48: 1.657 | P48: 1.678 | S48: 1.7 | T48: 1.7338 | U48: 1.7438 | V48: 1.7764 | W48: 1.7893 | Z48: 1.8059 | AA48: 1.8102 | AB48: 1.801 | AC48: 1.8237 | AD48: 1.8374 | AF48: 1.8423 | AG48: 1.8121 | AP48: 1.8109 | AQ48: 1.795 | AR48: 1.7683 | AS48: 1.7668 | AU48: 1.7719 | AV48: 1.7865 | AW48: 1.7888 | AX48: 1.8038 | AY48: 1.8297 | BB48: 1.855 | BC48: 1.8895 | BD48: 1.8929 | BE48: 1.9297 | BF48: 1.9705 | BI48: 2.017 | BJ48: 2.0395 | BK48: 2.0396 | BL48: 2.065 | BM48: 2.0808 | BP48: 2.0658 | BQ48: 2.0562 | BR48: 2.04 | BS48: 2.0507 | BT48: 2.0914 | BW48: 2.0907 | BX48: 2.1085 | BY48: 2.0995 | BZ48: 2.0615 | CA48: 2.039 | CD48: 2.0441 | CE48: 2.0248 | CF48: 2.013 | CG48: 1.9989 | CH48: 1.9827 | CK48: 1.9717 | CL48: 1.943 | CM48: 1.9334 | CN48: 1.9334 | CO48: 1.9297 | CR48: 1.9312 | CS48: 1.9287 | CT48: 1.9267 | CU48: 1.8751 | CY48: 1.7954 | CZ48: 1.8011 | DA48: 1.8011 | DB48: 1.7961 | DC48: 1.795 | DF48: 1.8051 | DG48: 1.8057 | DH48: 1.8064 | DI48: 1.8128 | DJ48: 1.8086 | DM48: 1.8116 | DN48: 1.812 | DO48: 1.8299 | DP48: 1.8361 | DQ48: 1.8367 | DS48: 1.8276 | DT48: 1.8234 | DU48: 1.8257 | DV48: 1.8088 | EB48: 1.8122 | EC48: 1.7926 | ED48: 1.7676 | EE48: 1.746 | EH48: 1.7427 | EI48: 1.7305 | EJ48: 1.7118 | EK48: 1.6947 | EL48: 1.7062 | EO48: 1.7123 | EP48: 1.6923 | EQ48: 1.6864 | ER48: 1.6963 | ES48: 1.698 | EV48: 1.688 | EW48: 1.6873 | EX48: 1.7071 | EY48: 1.7193 | EZ48: 1.7223 | FD48: 1.7272 | FE48: 1.7318 | FF48: 1.7373 | FG48: 1.7268 | FJ48: 1.7141 | FK48: 1.71 | FL48: 1.7101 | FM48: 1.706 | FN48: 1.7001 | FQ48: 1.702 | FR48: 1.7009 | FS48: 1.6952 | FT48: 1.7002 | FU48: 1.6934 | FX48: 1.693 | FY48: 1.6843 | FZ48: 1.6777 | GA48: 1.685 | GB48: 1.695 | GE48: 1.695 | GF48: 1.67 | GG48: 1.6607 | GH48: 1.6522 | GI48: 1.6344 | GL48: 1.6131 | GM48: 1.6202 | GN48: 1.62 | GO48: 1.62 | GP48: 1.6211 | GS48: 1.62 | GT48: 1.6023 | GU48: 1.6 | GV48: 1.6 | GW48: 1.5954 | GZ48: 1.59 | HA48: 1.6016 | HB48: 1.6435 | HC48: 1.6816 | HD48: 1.69 | HG48: 1.6889 | HH48: 1.7097 | HI48: 1.7176 | HJ48: 1.6832 | HK48: 1.6856 | HN48: 1.6647 | HO48: 1.66 | HP48: 1.66 | HQ48: 1.65 | HR48: 1.6486 | HU48: 1.6572 | HV48: 1.6616 | HW48: 1.66 | HX48: 1.6738 | HY48: 1.6775 | IB48: 1.71 | IC48: 1.71 | ID48: 1.7075 | IE48: 1.7104 | IF48: 1.7304 | II48: 1.7264 | IJ48: 1.7138 | IK48: 1.7044 | IL48: 1.705 | IM48: 1.6819 | IP48: 1.674 | IQ48: 1.6501 | IR48: 1.651 | IS48: 1.6329 | IT48: 1.6652 | IW48: 1.67 | IX48: 1.66 | IY48: 1.675 | IZ48: 1.7 | JA48: 1.7104 | JD48: 1.7074 | JE48: 1.6954 | JF48: 1.6906 | JG48: 1.6833 | JH48: 1.6936 | JK48: 1.6918 | JL48: 1.6896 | JM48: 1.7282 | JN48: 1.7464 | JO48: 1.7395 | JQ48: 1.7233 | JR48: 1.7361 | JS48: 1.7189 | KB48: 1.7123 | KC48: 1.7044 | KD48: 1.6998 | KF48: 1.7002 | KG48: 1.7158 | KH48: 1.7201 | KI48: 1.717 | KJ48: 1.7099 | KM48: 1.7152 | KN48: 1.7137 | KO48: 1.7052 | KP48: 1.6962 | KQ48: 1.6966 | KT48: 1.6993 | KU48: 1.6938 | KV48: 1.6741 | KW48: 1.6779 | KX48: 1.67 | LA48: 1.6678 | LB48: 1.6805 | LC48: 1.6783 | LD48: 1.6841 | LE48: 1.6865 | LH48: 1.6869 | LI48: 1.6946 | LJ48: 1.6957 | LK48: 1.7053 | LL48: 1.7027 | LO48: 1.6942 | LP48: 1.6977 | LQ48: 1.6977 | LR48: 1.6927 | LS48: 1.6981 | LV48: 1.6963 | LW48: 1.6884 | LX48: 1.6995 | LY48: 1.7135 | LZ48: 1.7193 | MC48: 1.7105 | MD48: 1.7223 | ME48: 1.7196 | MF48: 1.7505 | MG48: 1.752 | MJ48: 1.7468 | MK48: 1.7435 | ML48: 1.7468 | MM48: 1.7396 | MN48: 1.737 | MQ48: 1.7534 | MR48: 1.7591 | MS48: 1.7555 | MT48: 1.7555 | MU48: 1.7446 | MX48: 1.7296 | MY48: 1.7195 | MZ48: 1.7198 | NA48: 1.6907 | NB48: 1.6861 | NE48: 1.6815 | NF48: 1.6895 | NG48: 1.6787 | NK48: 1.6514 | NL48: 1.6508 | NM48: 1.6573 | NN48: 1.6706 | NO48: 1.6742 | NP48: 1.6821 | NS48: 1.6818 | NT48: 1.7 | NU48: 1.7 | NV48: 1.6979 | NW48: 1.6968 | NZ48: 1.6974 | OA48: 1.6927 | OB48: 1.6853 | OC48: 1.6952 | OD48: 1.7056 | OG48: 1.7075 | OH48: 1.7157 | OI48: 1.6988 | OJ48: 1.7037 | OK48: 1.7008 | ON48: 1.696 | OO48: 1.7048 | OP48: 1.7043 | OQ48: 1.7038 | OR48: 1.7057 | OU48: 1.6957 | OV48: 1.6969 | OW48: 1.68 | OX48: 1.68 | OY48: 1.6784 | OZ48: 1.6784 | PJ48: 1.6777 | PK48: 1.6659 | PL48: 1.6787 | PM48: 1.68 | PN48: 1.6782 | PP48: 1.6796 | PQ48: 1.6711 | PR48: 1.6583 | PS48: 1.6543 | PT48: 1.6421 | PW48: 1.6444 | PX48: 1.6442 | PY48: 1.6386 | PZ48: 1.6352 | QA48: 1.6298 | QD48: 1.6304 | QE48: 1.6266 | QF48: 1.6181 | QG48: 1.615 | QH48: 1.6147 | QK48: 1.6189 | QL48: 1.6037 | QM48: 1.6006 | QN48: 1.6006 | QO48: 1.5675 | QR48: 1.56 | QS48: 1.58 | QT48: 1.5724 | QU48: 1.5727 | QV48: 1.5709 | QZ48: 1.5577 | RA48: 1.5541 | RB48: 1.5486 | RC48: 1.5417 | RF48: 1.5426 | RG48: 1.5368 | RH48: 1.5318 | RI48: 1.5326 | RJ48: 1.5221 | RM48: 1.5093 | RN48: 1.5143 | RO48: 1.521 | RP48: 1.5113 | RQ48: 1.5146 | RT48: 1.5133 | RU48: 1.5233 | RV48: 1.5185 | RW48: 1.5145 | SC48: 1.5123 | SD48: 1.5142 | SE48: 1.5164 | SF48: 1.5271 | SH48: 1.5298 | SI48: 1.5261 | SJ48: 1.5142 | SK48: 1.508 | SL48: 1.5035 | SO48: 1.5013 | SP48: 1.5002 | SQ48: 1.4855 | SR48: 1.4843 | SS48: 1.4891 | SV48: 1.4823 | SW48: 1.4811 | SX48: 1.4727 | SY48: 1.4705 | SZ48: 1.4727 | TC48: 1.4689 | TD48: 1.4664 | TE48: 1.4669 | TF48: 1.4601 | TG48: 1.4606 | TJ48: 1.4593 | TK48: 1.4699 | TL48: 1.4822 | TM48: 1.5161 | TN48: 1.5298 | TQ48: 1.5286 | TR48: 1.5251 | TS48: 1.5366 | TT48: 1.5232 | TX48: 1.5242 | TY48: 1.5359 | TZ48: 1.5208 | UA48: 1.5045 | UB48: 1.5 | UE48: 1.5 | UF48: 1.5 | UG48: 1.5 | UH48: 1.505 | UI48: 1.505
D49: 中债城投债到期收益率(AAA):1年 | E49: M0048432 | H49: 1.68 | I49: 1.6695 | L49: 1.66 | M49: 1.6683 | N49: 1.6824 | O49: 1.686 | P49: 1.7078 | S49: 1.7402 | T49: 1.7702 | U49: 1.785 | V49: 1.8226 | W49: 1.8251 | Z49: 1.8388 | AA49: 1.8488 | AB49: 1.8353 | AC49: 1.849 | AD49: 1.8686 | AF49: 1.8588 | AG49: 1.8298 | AP49: 1.8249 | AQ49: 1.8087 | AR49: 1.7952 | AS49: 1.7745 | AU49: 1.797 | AV49: 1.8114 | AW49: 1.8133 | AX49: 1.8233 | AY49: 1.8462 | BB49: 1.8699 | BC49: 1.9001 | BD49: 1.9009 | BE49: 1.9237 | BF49: 1.9624 | BI49: 2.0024 | BJ49: 2.0224 | BK49: 2.0091 | BL49: 2.0333 | BM49: 2.036 | BP49: 2.0273 | BQ49: 2.0288 | BR49: 2.0204 | BS49: 2.0238 | BT49: 2.0669 | BW49: 2.0802 | BX49: 2.0931 | BY49: 2.089 | BZ49: 2.0606 | CA49: 2.05 | CD49: 2.0533 | CE49: 2.0408 | CF49: 2.0263 | CG49: 1.9911 | CH49: 1.981 | CK49: 1.9748 | CL49: 1.966 | CM49: 1.9625 | CN49: 1.95 | CO49: 1.9515 | CR49: 1.95 | CS49: 1.94 | CT49: 1.9442 | CU49: 1.8914 | CY49: 1.8293 | CZ49: 1.8264 | DA49: 1.8388 | DB49: 1.8357 | DC49: 1.8222 | DF49: 1.8198 | DG49: 1.8248 | DH49: 1.8275 | DI49: 1.8294 | DJ49: 1.8296 | DM49: 1.842 | DN49: 1.8436 | DO49: 1.8505 | DP49: 1.8516 | DQ49: 1.8489 | DS49: 1.8258 | DT49: 1.8307 | DU49: 1.8325 | DV49: 1.8306 | EB49: 1.8207 | EC49: 1.8083 | ED49: 1.784 | EE49: 1.7673 | EH49: 1.7515 | EI49: 1.7325 | EJ49: 1.7227 | EK49: 1.7101 | EL49: 1.7191 | EO49: 1.72 | EP49: 1.7046 | EQ49: 1.707 | ER49: 1.7034 | ES49: 1.7072 | EV49: 1.7074 | EW49: 1.71 | EX49: 1.7269 | EY49: 1.7352 | EZ49: 1.7398 | FD49: 1.7208 | FE49: 1.7471 | FF49: 1.7455 | FG49: 1.7448 | FJ49: 1.7302 | FK49: 1.7301 | FL49: 1.7324 | FM49: 1.7316 | FN49: 1.7294 | FQ49: 1.7288 | FR49: 1.7308 | FS49: 1.7224 | FT49: 1.7154 | FU49: 1.7131 | FX49: 1.7061 | FY49: 1.7163 | FZ49: 1.7204 | GA49: 1.7283 | GB49: 1.733 | GE49: 1.7249 | GF49: 1.7257 | GG49: 1.7193 | GH49: 1.7068 | GI49: 1.6871 | GL49: 1.674 | GM49: 1.6786 | GN49: 1.6762 | GO49: 1.6744 | GP49: 1.6871 | GS49: 1.7003 | GT49: 1.6878 | GU49: 1.681 | GV49: 1.6694 | GW49: 1.6637 | GZ49: 1.684 | HA49: 1.6827 | HB49: 1.695 | HC49: 1.7283 | HD49: 1.7407 | HG49: 1.7156 | HH49: 1.7256 | HI49: 1.7323 | HJ49: 1.716 | HK49: 1.7013 | HN49: 1.6913 | HO49: 1.6912 | HP49: 1.68 | HQ49: 1.6728 | HR49: 1.6731 | HU49: 1.6719 | HV49: 1.6721 | HW49: 1.6721 | HX49: 1.6824 | HY49: 1.7017 | IB49: 1.7317 | IC49: 1.7476 | ID49: 1.7305 | IE49: 1.7373 | IF49: 1.7343 | II49: 1.7368 | IJ49: 1.733 | IK49: 1.725 | IL49: 1.7222 | IM49: 1.7183 | IP49: 1.7092 | IQ49: 1.7138 | IR49: 1.7102 | IS49: 1.7002 | IT49: 1.7025 | IW49: 1.7017 | IX49: 1.7017 | IY49: 1.7141 | IZ49: 1.7133 | JA49: 1.7219 | JD49: 1.7135 | JE49: 1.7164 | JF49: 1.7205 | JG49: 1.7307 | JH49: 1.7309 | JK49: 1.742 | JL49: 1.7523 | JM49: 1.7662 | JN49: 1.7667 | JO49: 1.7655 | JQ49: 1.7581 | JR49: 1.7761 | JS49: 1.7665 | KB49: 1.7565 | KC49: 1.7604 | KD49: 1.7405 | KF49: 1.7508 | KG49: 1.7537 | KH49: 1.7559 | KI49: 1.7514 | KJ49: 1.7487 | KM49: 1.7382 | KN49: 1.7332 | KO49: 1.7232 | KP49: 1.7268 | KQ49: 1.7149 | KT49: 1.7157 | KU49: 1.713 | KV49: 1.6992 | KW49: 1.6887 | KX49: 1.6799 | LA49: 1.6748 | LB49: 1.6832 | LC49: 1.686 | LD49: 1.6894 | LE49: 1.703 | LH49: 1.7059 | LI49: 1.7037 | LJ49: 1.6995 | LK49: 1.7036 | LL49: 1.7031 | LO49: 1.708 | LP49: 1.7045 | LQ49: 1.7005 | LR49: 1.6948 | LS49: 1.6921 | LV49: 1.6946 | LW49: 1.6964 | LX49: 1.7092 | LY49: 1.7185 | LZ49: 1.7175 | MC49: 1.7175 | MD49: 1.7155 | ME49: 1.714 | MF49: 1.734 | MG49: 1.7478 | MJ49: 1.7585 | MK49: 1.7669 | ML49: 1.7655 | MM49: 1.7595 | MN49: 1.7577 | MQ49: 1.7716 | MR49: 1.7712 | MS49: 1.7546 | MT49: 1.7558 | MU49: 1.7485 | MX49: 1.7328 | MY49: 1.7345 | MZ49: 1.7348 | NA49: 1.7328 | NB49: 1.717 | NE49: 1.7183 | NF49: 1.7144 | NG49: 1.7021 | NK49: 1.6909 | NL49: 1.6807 | NM49: 1.6913 | NN49: 1.6934 | NO49: 1.6991 | NP49: 1.7024 | NS49: 1.702 | NT49: 1.7002 | NU49: 1.6991 | NV49: 1.707 | NW49: 1.7091 | NZ49: 1.7109 | OA49: 1.709 | OB49: 1.6967 | OC49: 1.6964 | OD49: 1.6988 | OG49: 1.7035 | OH49: 1.7025 | OI49: 1.7034 | OJ49: 1.7032 | OK49: 1.6935 | ON49: 1.7003 | OO49: 1.7013 | OP49: 1.7025 | OQ49: 1.702 | OR49: 1.7009 | OU49: 1.6984 | OV49: 1.6959 | OW49: 1.7007 | OX49: 1.6933 | OY49: 1.685 | OZ49: 1.685 | PJ49: 1.6874 | PK49: 1.6812 | PL49: 1.6955 | PM49: 1.6972 | PN49: 1.6893 | PP49: 1.6835 | PQ49: 1.6775 | PR49: 1.6754 | PS49: 1.6706 | PT49: 1.6477 | PW49: 1.6591 | PX49: 1.6459 | PY49: 1.6434 | PZ49: 1.6427 | QA49: 1.6318 | QD49: 1.636 | QE49: 1.6321 | QF49: 1.6279 | QG49: 1.6229 | QH49: 1.619 | QK49: 1.6082 | QL49: 1.6011 | QM49: 1.6026 | QN49: 1.6055 | QO49: 1.6093 | QR49: 1.6059 | QS49: 1.5926 | QT49: 1.5957 | QU49: 1.5832 | QV49: 1.5672 | QZ49: 1.5537 | RA49: 1.5541 | RB49: 1.5538 | RC49: 1.5431 | RF49: 1.549 | RG49: 1.5447 | RH49: 1.5474 | RI49: 1.5515 | RJ49: 1.5547 | RM49: 1.5454 | RN49: 1.5455 | RO49: 1.5326 | RP49: 1.5293 | RQ49: 1.5218 | RT49: 1.5186 | RU49: 1.5211 | RV49: 1.5126 | RW49: 1.5138 | SC49: 1.5188 | SD49: 1.5181 | SE49: 1.5211 | SF49: 1.5319 | SH49: 1.5258 | SI49: 1.5103 | SJ49: 1.5001 | SK49: 1.5079 | SL49: 1.5037 | SO49: 1.5003 | SP49: 1.4901 | SQ49: 1.4815 | SR49: 1.4727 | SS49: 1.4793 | SV49: 1.4753 | SW49: 1.4698 | SX49: 1.4677 | SY49: 1.4596 | SZ49: 1.4613 | TC49: 1.4565 | TD49: 1.4475 | TE49: 1.4587 | TF49: 1.4579 | TG49: 1.4715 | TJ49: 1.469 | TK49: 1.4835 | TL49: 1.4919 | TM49: 1.5219 | TN49: 1.5321 | TQ49: 1.53 | TR49: 1.5301 | TS49: 1.5373 | TT49: 1.5208 | TX49: 1.5208 | TY49: 1.5243 | TZ49: 1.5226 | UA49: 1.5167 | UB49: 1.5103 | UE49: 1.5036 | UF49: 1.5004 | UG49: 1.5122 | UH49: 1.5316 | UI49: 1.5297
D50: 中债城投债到期收益率(AAA):3年 | E50: M0048434 | H50: 1.7791 | I50: 1.7414 | L50: 1.7294 | M50: 1.7464 | N50: 1.7441 | O50: 1.773 | P50: 1.7842 | S50: 1.8036 | T50: 1.8031 | U50: 1.8025 | V50: 1.8323 | W50: 1.8523 | Z50: 1.8625 | AA50: 1.8713 | AB50: 1.873 | AC50: 1.8797 | AD50: 1.8797 | AF50: 1.8797 | AG50: 1.8569 | AP50: 1.8566 | AQ50: 1.8358 | AR50: 1.8229 | AS50: 1.8183 | AU50: 1.831 | AV50: 1.8515 | AW50: 1.8515 | AX50: 1.8612 | AY50: 1.8861 | BB50: 1.902 | BC50: 1.9265 | BD50: 1.9277 | BE50: 1.9588 | BF50: 1.9959 | BI50: 2.0325 | BJ50: 2.0576 | BK50: 2.0599 | BL50: 2.081 | BM50: 2.0884 | BP50: 2.0886 | BQ50: 2.0755 | BR50: 2.0776 | BS50: 2.0824 | BT50: 2.1335 | BW50: 2.1561 | BX50: 2.1982 | BY50: 2.1989 | BZ50: 2.1669 | CA50: 2.1402 | CD50: 2.1609 | CE50: 2.1433 | CF50: 2.1231 | CG50: 2.0992 | CH50: 2.0753 | CK50: 2.0564 | CL50: 2.0363 | CM50: 2.0378 | CN50: 2.024 | CO50: 2.0225 | CR50: 2.0155 | CS50: 2.0172 | CT50: 2.0132 | CU50: 1.97 | CY50: 1.8907 | CZ50: 1.9016 | DA50: 1.9078 | DB50: 1.913 | DC50: 1.8993 | DF50: 1.9068 | DG50: 1.9114 | DH50: 1.9219 | DI50: 1.9161 | DJ50: 1.9124 | DM50: 1.9299 | DN50: 1.927 | DO50: 1.9532 | DP50: 1.963 | DQ50: 1.9752 | DS50: 1.9754 | DT50: 1.9685 | DU50: 1.9512 | DV50: 1.9306 | EB50: 1.923 | EC50: 1.9225 | ED50: 1.8911 | EE50: 1.863 | EH50: 1.8572 | EI50: 1.8549 | EJ50: 1.8511 | EK50: 1.8448 | EL50: 1.8595 | EO50: 1.8516 | EP50: 1.8351 | EQ50: 1.8341 | ER50: 1.8317 | ES50: 1.8267 | EV50: 1.8202 | EW50: 1.8195 | EX50: 1.8369 | EY50: 1.8519 | EZ50: 1.8405 | FD50: 1.8431 | FE50: 1.8466 | FF50: 1.8563 | FG50: 1.8486 | FJ50: 1.8342 | FK50: 1.8361 | FL50: 1.8327 | FM50: 1.8335 | FN50: 1.837 | FQ50: 1.8356 | FR50: 1.8372 | FS50: 1.842 | FT50: 1.8213 | FU50: 1.8122 | FX50: 1.8119 | FY50: 1.8102 | FZ50: 1.8324 | GA50: 1.8522 | GB50: 1.8496 | GE50: 1.845 | GF50: 1.8355 | GG50: 1.8105 | GH50: 1.8019 | GI50: 1.7774 | GL50: 1.7706 | GM50: 1.7835 | GN50: 1.7916 | GO50: 1.8039 | GP50: 1.8171 | GS50: 1.8298 | GT50: 1.8113 | GU50: 1.7972 | GV50: 1.7872 | GW50: 1.7791 | GZ50: 1.7967 | HA50: 1.8108 | HB50: 1.8374 | HC50: 1.8632 | HD50: 1.8818 | HG50: 1.8706 | HH50: 1.8982 | HI50: 1.9101 | HJ50: 1.881 | HK50: 1.8617 | HN50: 1.8525 | HO50: 1.8329 | HP50: 1.8267 | HQ50: 1.8197 | HR50: 1.8301 | HU50: 1.8305 | HV50: 1.8486 | HW50: 1.8475 | HX50: 1.8526 | HY50: 1.8705 | IB50: 1.9321 | IC50: 1.9418 | ID50: 1.9458 | IE50: 1.9461 | IF50: 1.9467 | II50: 1.9523 | IJ50: 1.9505 | IK50: 1.9307 | IL50: 1.9227 | IM50: 1.9364 | IP50: 1.9346 | IQ50: 1.9381 | IR50: 1.9296 | IS50: 1.9139 | IT50: 1.9342 | IW50: 1.9522 | IX50: 1.959 | IY50: 1.9783 | IZ50: 1.9865 | JA50: 1.9866 | JD50: 1.9679 | JE50: 1.9772 | JF50: 1.9684 | JG50: 1.9656 | JH50: 1.9889 | JK50: 1.9887 | JL50: 2.0089 | JM50: 2.0386 | JN50: 2.0682 | JO50: 2.0665 | JQ50: 2.064 | JR50: 2.0627 | JS50: 2.0419 | KB50: 2.0319 | KC50: 2.0358 | KD50: 1.9967 | KF50: 1.9922 | KG50: 1.9919 | KH50: 1.9865 | KI50: 1.9774 | KJ50: 1.9655 | KM50: 1.9595 | KN50: 1.9567 | KO50: 1.9598 | KP50: 1.9523 | KQ50: 1.9524 | KT50: 1.9509 | KU50: 1.9186 | KV50: 1.9039 | KW50: 1.8902 | KX50: 1.888 | LA50: 1.8901 | LB50: 1.89 | LC50: 1.8869 | LD50: 1.8867 | LE50: 1.9066 | LH50: 1.9164 | LI50: 1.9133 | LJ50: 1.9005 | LK50: 1.9001 | LL50: 1.8959 | LO50: 1.8904 | LP50: 1.8868 | LQ50: 1.8844 | LR50: 1.8851 | LS50: 1.8873 | LV50: 1.8989 | LW50: 1.8972 | LX50: 1.9269 | LY50: 1.9475 | LZ50: 1.9441 | MC50: 1.9437 | MD50: 1.9462 | ME50: 1.9439 | MF50: 1.978 | MG50: 1.9746 | MJ50: 1.9839 | MK50: 1.9697 | ML50: 1.9651 | MM50: 1.9491 | MN50: 1.9307 | MQ50: 1.934 | MR50: 1.9313 | MS50: 1.9188 | MT50: 1.9055 | MU50: 1.8911 | MX50: 1.882 | MY50: 1.8718 | MZ50: 1.8703 | NA50: 1.8694 | NB50: 1.8625 | NE50: 1.8702 | NF50: 1.8761 | NG50: 1.8784 | NK50: 1.8739 | NL50: 1.8756 | NM50: 1.8857 | NN50: 1.9003 | NO50: 1.8972 | NP50: 1.9002 | NS50: 1.8987 | NT50: 1.8955 | NU50: 1.8968 | NV50: 1.8964 | NW50: 1.8857 | NZ50: 1.8762 | OA50: 1.8752 | OB50: 1.8634 | OC50: 1.8549 | OD50: 1.8465 | OG50: 1.8441 | OH50: 1.8425 | OI50: 1.8446 | OJ50: 1.8467 | OK50: 1.8543 | ON50: 1.8533 | OO50: 1.8618 | OP50: 1.8635 | OQ50: 1.8635 | OR50: 1.8585 | OU50: 1.8501 | OV50: 1.8502 | OW50: 1.8403 | OX50: 1.8334 | OY50: 1.8306 | OZ50: 1.8306 | PJ50: 1.823 | PK50: 1.8272 | PL50: 1.8385 | PM50: 1.8431 | PN50: 1.8437 | PP50: 1.8369 | PQ50: 1.8307 | PR50: 1.8254 | PS50: 1.8239 | PT50: 1.8154 | PW50: 1.8279 | PX50: 1.8223 | PY50: 1.8263 | PZ50: 1.8226 | QA50: 1.8111 | QD50: 1.8319 | QE50: 1.8275 | QF50: 1.8168 | QG50: 1.8036 | QH50: 1.8022 | QK50: 1.8098 | QL50: 1.8077 | QM50: 1.8104 | QN50: 1.8067 | QO50: 1.7919 | QR50: 1.7858 | QS50: 1.7771 | QT50: 1.7658 | QU50: 1.762 | QV50: 1.7426 | QZ50: 1.7358 | RA50: 1.7234 | RB50: 1.7219 | RC50: 1.7254 | RF50: 1.7261 | RG50: 1.7307 | RH50: 1.7339 | RI50: 1.7249 | RJ50: 1.7311 | RM50: 1.7295 | RN50: 1.7253 | RO50: 1.725 | RP50: 1.7369 | RQ50: 1.7365 | RT50: 1.7451 | RU50: 1.742 | RV50: 1.7388 | RW50: 1.7341 | SC50: 1.7393 | SD50: 1.7399 | SE50: 1.7418 | SF50: 1.7339 | SH50: 1.7369 | SI50: 1.7297 | SJ50: 1.7222 | SK50: 1.7146 | SL50: 1.7032 | SO50: 1.7105 | SP50: 1.701 | SQ50: 1.6908 | SR50: 1.6885 | SS50: 1.6917 | SV50: 1.6875 | SW50: 1.6747 | SX50: 1.6646 | SY50: 1.6555 | SZ50: 1.651 | TC50: 1.6454 | TD50: 1.6461 | TE50: 1.6476 | TF50: 1.6412 | TG50: 1.6421 | TJ50: 1.6559 | TK50: 1.6684 | TL50: 1.6667 | TM50: 1.6997 | TN50: 1.7114 | TQ50: 1.7097 | TR50: 1.7056 | TS50: 1.6894 | TT50: 1.6692 | TX50: 1.6668 | TY50: 1.6736 | TZ50: 1.6706 | UA50: 1.6587 | UB50: 1.6537 | UE50: 1.6402 | UF50: 1.6327 | UG50: 1.6528 | UH50: 1.6632 | UI50: 1.6675
D51: 中债企业债到期收益率(AAA):3年 | E51: S0059773 | H51: 1.7019 | I51: 1.6958 | L51: 1.6708 | M51: 1.6998 | N51: 1.7015 | O51: 1.742 | P51: 1.7706 | S51: 1.8046 | T51: 1.81 | U51: 1.802 | V51: 1.8329 | W51: 1.8449 | Z51: 1.863 | AA51: 1.8565 | AB51: 1.8432 | AC51: 1.8497 | AD51: 1.8541 | AF51: 1.8558 | AG51: 1.8365 | AP51: 1.83 | AQ51: 1.8052 | AR51: 1.7851 | AS51: 1.7939 | AU51: 1.8172 | AV51: 1.8401 | AW51: 1.8377 | AX51: 1.8387 | AY51: 1.8607 | BB51: 1.8906 | BC51: 1.9106 | BD51: 1.9091 | BE51: 1.9376 | BF51: 1.9776 | BI51: 2.0283 | BJ51: 2.054 | BK51: 2.054 | BL51: 2.0713 | BM51: 2.0789 | BP51: 2.0638 | BQ51: 2.0581 | BR51: 2.04 | BS51: 2.06 | BT51: 2.11 | BW51: 2.135 | BX51: 2.1838 | BY51: 2.161 | BZ51: 2.1168 | CA51: 2.0978 | CD51: 2.1206 | CE51: 2.1013 | CF51: 2.0767 | CG51: 2.0413 | CH51: 2.0262 | CK51: 2.0298 | CL51: 2.0153 | CM51: 2.0156 | CN51: 2.0157 | CO51: 2.0131 | CR51: 2.0111 | CS51: 2.0187 | CT51: 2.0043 | CU51: 1.9532 | CY51: 1.8719 | CZ51: 1.8892 | DA51: 1.8964 | DB51: 1.9022 | DC51: 1.8911 | DF51: 1.8969 | DG51: 1.887 | DH51: 1.884 | DI51: 1.8836 | DJ51: 1.8863 | DM51: 1.9044 | DN51: 1.9047 | DO51: 1.9157 | DP51: 1.923 | DQ51: 1.9337 | DS51: 1.9339 | DT51: 1.9413 | DU51: 1.9254 | DV51: 1.9117 | EB51: 1.9127 | EC51: 1.9019 | ED51: 1.8718 | EE51: 1.8477 | EH51: 1.8529 | EI51: 1.8435 | EJ51: 1.8387 | EK51: 1.8332 | EL51: 1.8446 | EO51: 1.8547 | EP51: 1.8422 | EQ51: 1.8385 | ER51: 1.828 | ES51: 1.8171 | EV51: 1.8114 | EW51: 1.8127 | EX51: 1.8275 | EY51: 1.8524 | EZ51: 1.8444 | FD51: 1.8465 | FE51: 1.8457 | FF51: 1.8459 | FG51: 1.8357 | FJ51: 1.8207 | FK51: 1.8159 | FL51: 1.8149 | FM51: 1.806 | FN51: 1.8024 | FQ51: 1.8035 | FR51: 1.8031 | FS51: 1.7949 | FT51: 1.7846 | FU51: 1.772 | FX51: 1.7717 | FY51: 1.791 | FZ51: 1.8137 | GA51: 1.8233 | GB51: 1.8228 | GE51: 1.8223 | GF51: 1.8073 | GG51: 1.773 | GH51: 1.7584 | GI51: 1.7548 | GL51: 1.7482 | GM51: 1.7453 | GN51: 1.7451 | GO51: 1.7538 | GP51: 1.7565 | GS51: 1.7677 | GT51: 1.7602 | GU51: 1.7617 | GV51: 1.7272 | GW51: 1.7189 | GZ51: 1.7497 | HA51: 1.7495 | HB51: 1.781 | HC51: 1.8312 | HD51: 1.8313 | HG51: 1.8178 | HH51: 1.8273 | HI51: 1.8192 | HJ51: 1.8018 | HK51: 1.7903 | HN51: 1.789 | HO51: 1.7907 | HP51: 1.7746 | HQ51: 1.7635 | HR51: 1.7683 | HU51: 1.7855 | HV51: 1.7964 | HW51: 1.7899 | HX51: 1.7923 | HY51: 1.7983 | IB51: 1.8577 | IC51: 1.8527 | ID51: 1.8761 | IE51: 1.8896 | IF51: 1.8889 | II51: 1.8833 | IJ51: 1.8708 | IK51: 1.8611 | IL51: 1.8626 | IM51: 1.8618 | IP51: 1.8648 | IQ51: 1.8653 | IR51: 1.8552 | IS51: 1.845 | IT51: 1.8564 | IW51: 1.8624 | IX51: 1.8666 | IY51: 1.8843 | IZ51: 1.8729 | JA51: 1.8869 | JD51: 1.8869 | JE51: 1.8698 | JF51: 1.8769 | JG51: 1.8741 | JH51: 1.882 | JK51: 1.8768 | JL51: 1.9082 | JM51: 1.947 | JN51: 1.9858 | JO51: 1.9872 | JQ51: 1.9891 | JR51: 1.9689 | JS51: 1.9365 | KB51: 1.9239 | KC51: 1.9139 | KD51: 1.901 | KF51: 1.9045 | KG51: 1.904 | KH51: 1.8925 | KI51: 1.8827 | KJ51: 1.8753 | KM51: 1.8764 | KN51: 1.8494 | KO51: 1.8428 | KP51: 1.8275 | KQ51: 1.8199 | KT51: 1.8375 | KU51: 1.8294 | KV51: 1.8164 | KW51: 1.8259 | KX51: 1.8214 | LA51: 1.83 | LB51: 1.8323 | LC51: 1.8276 | LD51: 1.8292 | LE51: 1.8575 | LH51: 1.8439 | LI51: 1.8481 | LJ51: 1.8482 | LK51: 1.84 | LL51: 1.82 | LO51: 1.8081 | LP51: 1.8305 | LQ51: 1.8318 | LR51: 1.8419 | LS51: 1.8444 | LV51: 1.8498 | LW51: 1.8612 | LX51: 1.8893 | LY51: 1.9078 | LZ51: 1.8968 | MC51: 1.8977 | MD51: 1.8963 | ME51: 1.9113 | MF51: 1.93 | MG51: 1.9287 | MJ51: 1.9385 | MK51: 1.9207 | ML51: 1.9157 | MM51: 1.8917 | MN51: 1.8845 | MQ51: 1.8914 | MR51: 1.8821 | MS51: 1.8734 | MT51: 1.8602 | MU51: 1.8455 | MX51: 1.8288 | MY51: 1.8211 | MZ51: 1.7945 | NA51: 1.7912 | NB51: 1.7801 | NE51: 1.7833 | NF51: 1.7957 | NG51: 1.803 | NK51: 1.8053 | NL51: 1.8112 | NM51: 1.818 | NN51: 1.8275 | NO51: 1.8378 | NP51: 1.8374 | NS51: 1.8376 | NT51: 1.8385 | NU51: 1.8384 | NV51: 1.8386 | NW51: 1.8362 | NZ51: 1.8306 | OA51: 1.823 | OB51: 1.8232 | OC51: 1.8115 | OD51: 1.8213 | OG51: 1.8318 | OH51: 1.8296 | OI51: 1.8286 | OJ51: 1.8277 | OK51: 1.8246 | ON51: 1.8342 | OO51: 1.8324 | OP51: 1.8352 | OQ51: 1.8268 | OR51: 1.8279 | OU51: 1.8197 | OV51: 1.8206 | OW51: 1.8024 | OX51: 1.7982 | OY51: 1.7977 | OZ51: 1.7977 | PJ51: 1.7949 | PK51: 1.8032 | PL51: 1.8152 | PM51: 1.8124 | PN51: 1.8131 | PP51: 1.807 | PQ51: 1.7995 | PR51: 1.7978 | PS51: 1.7907 | PT51: 1.7887 | PW51: 1.7899 | PX51: 1.7983 | PY51: 1.784 | PZ51: 1.7819 | QA51: 1.7819 | QD51: 1.7913 | QE51: 1.7894 | QF51: 1.7851 | QG51: 1.7687 | QH51: 1.7709 | QK51: 1.7733 | QL51: 1.7742 | QM51: 1.7745 | QN51: 1.768 | QO51: 1.7611 | QR51: 1.7616 | QS51: 1.7629 | QT51: 1.7536 | QU51: 1.7493 | QV51: 1.7345 | QZ51: 1.7268 | RA51: 1.7218 | RB51: 1.7017 | RC51: 1.7068 | RF51: 1.7145 | RG51: 1.7179 | RH51: 1.7196 | RI51: 1.7232 | RJ51: 1.7182 | RM51: 1.7151 | RN51: 1.7097 | RO51: 1.7057 | RP51: 1.7053 | RQ51: 1.7041 | RT51: 1.7083 | RU51: 1.7243 | RV51: 1.7146 | RW51: 1.7179 | SC51: 1.724 | SD51: 1.7234 | SE51: 1.7271 | SF51: 1.7274 | SH51: 1.7287 | SI51: 1.7146 | SJ51: 1.7047 | SK51: 1.7027 | SL51: 1.6973 | SO51: 1.6943 | SP51: 1.6959 | SQ51: 1.6697 | SR51: 1.6665 | SS51: 1.6734 | SV51: 1.6688 | SW51: 1.6658 | SX51: 1.6592 | SY51: 1.6502 | SZ51: 1.6365 | TC51: 1.6219 | TD51: 1.6132 | TE51: 1.6219 | TF51: 1.6106 | TG51: 1.6147 | TJ51: 1.6083 | TK51: 1.6182 | TL51: 1.6179 | TM51: 1.6585 | TN51: 1.6585 | TQ51: 1.6577 | TR51: 1.6511 | TS51: 1.6444 | TT51: 1.6417 | TX51: 1.6341 | TY51: 1.6295 | TZ51: 1.6437 | UA51: 1.6374 | UB51: 1.633 | UE51: 1.6053 | UF51: 1.6086 | UG51: 1.6313 | UH51: 1.643 | UI51: 1.643
D52: 中债国债到期收益率:10年 | E52: S0059749 | H52: 1.6077 | I52: 1.6041 | L52: 1.5966 | M52: 1.6093 | N52: 1.6069 | O52: 1.6368 | P52: 1.6338 | S52: 1.6592 | T52: 1.6446 | U52: 1.633 | V52: 1.6394 | W52: 1.6593 | Z52: 1.6747 | AA52: 1.6496 | AB52: 1.6602 | AC52: 1.6645 | AD52: 1.6565 | AF52: 1.6537 | AG52: 1.6299 | AP52: 1.6207 | AQ52: 1.5958 | AR52: 1.6032 | AS52: 1.6057 | AU52: 1.6342 | AV52: 1.6274 | AW52: 1.6336 | AX52: 1.6346 | AY52: 1.6546 | BB52: 1.6934 | BC52: 1.7006 | BD52: 1.6626 | BE52: 1.685 | BF52: 1.72 | BI52: 1.7625 | BJ52: 1.7275 | BK52: 1.7251 | BL52: 1.7576 | BM52: 1.7152 | BP52: 1.6955 | BQ52: 1.7079 | BR52: 1.7083 | BS52: 1.7455 | BT52: 1.8002 | BW52: 1.8128 | BX52: 1.8853 | BY52: 1.8334 | BZ52: 1.8565 | CA52: 1.8317 | CD52: 1.8957 | CE52: 1.8885 | CF52: 1.8708 | CG52: 1.8309 | CH52: 1.8458 | CK52: 1.8413 | CL52: 1.8183 | CM52: 1.7943 | CN52: 1.8062 | CO52: 1.8126 | CR52: 1.8129 | CS52: 1.8104 | CT52: 1.7887 | CU52: 1.718 | CY52: 1.6318 | CZ52: 1.6633 | DA52: 1.6508 | DB52: 1.6444 | DC52: 1.6568 | DF52: 1.6584 | DG52: 1.6583 | DH52: 1.643 | DI52: 1.6522 | DJ52: 1.6493 | DM52: 1.6664 | DN52: 1.6509 | DO52: 1.6611 | DP52: 1.664 | DQ52: 1.6606 | DS52: 1.6607 | DT52: 1.6483 | DU52: 1.6241 | DV52: 1.6243 | EB52: 1.6298 | EC52: 1.6418 | ED52: 1.6331 | EE52: 1.6351 | EH52: 1.688 | EI52: 1.6704 | EJ52: 1.6736 | EK52: 1.6798 | EL52: 1.6793 | EO52: 1.6893 | EP52: 1.7004 | EQ52: 1.71 | ER52: 1.7186 | ES52: 1.7208 | EV52: 1.7201 | EW52: 1.7261 | EX52: 1.6832 | EY52: 1.6877 | EZ52: 1.6712 | FD52: 1.6764 | FE52: 1.6704 | FF52: 1.6741 | FG52: 1.6547 | FJ52: 1.6559 | FK52: 1.6569 | FL52: 1.642 | FM52: 1.6475 | FN52: 1.644 | FQ52: 1.6432 | FR52: 1.6364 | FS52: 1.6384 | FT52: 1.6425 | FU52: 1.6396 | FX52: 1.6418 | FY52: 1.648 | FZ52: 1.6544 | GA52: 1.6462 | GB52: 1.6462 | GE52: 1.6469 | GF52: 1.6433 | GG52: 1.6396 | GH52: 1.6407 | GI52: 1.6433 | GL52: 1.6406 | GM52: 1.6444 | GN52: 1.6446 | GO52: 1.6616 | GP52: 1.6653 | GS52: 1.6726 | GT52: 1.6557 | GU52: 1.6617 | GV52: 1.663 | GW52: 1.6652 | GZ52: 1.6774 | HA52: 1.6907 | HB52: 1.7041 | HC52: 1.7376 | HD52: 1.7324 | HG52: 1.7146 | HH52: 1.7466 | HI52: 1.718 | HJ52: 1.7044 | HK52: 1.7059 | HN52: 1.7083 | HO52: 1.7061 | HP52: 1.6999 | HQ52: 1.6894 | HR52: 1.6891 | HU52: 1.7203 | HV52: 1.7271 | HW52: 1.7262 | HX52: 1.7341 | HY52: 1.7465 | IB52: 1.7872 | IC52: 1.7725 | ID52: 1.782 | IE52: 1.7667 | IF52: 1.7818 | II52: 1.7643 | IJ52: 1.7598 | IK52: 1.7988 | IL52: 1.8478 | IM52: 1.8379 | IP52: 1.8257 | IQ52: 1.8167 | IR52: 1.7984 | IS52: 1.806 | IT52: 1.826 | IW52: 1.8514 | IX52: 1.8641 | IY52: 1.8992 | IZ52: 1.8743 | JA52: 1.867 | JD52: 1.8724 | JE52: 1.8527 | JF52: 1.8349 | JG52: 1.8546 | JH52: 1.8789 | JK52: 1.8647 | JL52: 1.877 | JM52: 1.9022 | JN52: 1.884 | JO52: 1.8768 | JQ52: 1.8781 | JR52: 1.887 | JS52: 1.8605 | KB52: 1.8466 | KC52: 1.846 | KD52: 1.8206 | KF52: 1.8383 | KG52: 1.8368 | KH52: 1.8449 | KI52: 1.8407 | KJ52: 1.8246 | KM52: 1.8498 | KN52: 1.8357 | KO52: 1.8293 | KP52: 1.8391 | KQ52: 1.8486 | KT52: 1.8423 | KU52: 1.8179 | KV52: 1.8208 | KW52: 1.8098 | KX52: 1.7954 | LA52: 1.7944 | LB52: 1.7984 | LC52: 1.7964 | LD52: 1.81 | LE52: 1.8142 | LH52: 1.8139 | LI52: 1.8119 | LJ52: 1.8071 | LK52: 1.8126 | LL52: 1.814 | LO52: 1.8109 | LP52: 1.8121 | LQ52: 1.8179 | LR52: 1.8135 | LS52: 1.8166 | LV52: 1.821 | LW52: 1.8301 | LX52: 1.8462 | LY52: 1.8537 | LZ52: 1.8412 | MC52: 1.8366 | MD52: 1.8442 | ME52: 1.8519 | MF52: 1.8718 | MG52: 1.848 | MJ52: 1.8499 | MK52: 1.8425 | ML52: 1.8447 | MM52: 1.8404 | MN52: 1.8396 | MQ52: 1.8488 | MR52: 1.8458 | MS52: 1.834 | MT52: 1.8356 | MU52: 1.8308 | MX52: 1.8415 | MY52: 1.8352 | MZ52: 1.8356 | NA52: 1.8386 | NB52: 1.8376 | NE52: 1.8584 | NF52: 1.8582 | NG52: 1.8473 | NK52: 1.8427 | NL52: 1.8584 | NM52: 1.8829 | NN52: 1.9019 | NO52: 1.8905 | NP52: 1.8782 | NS52: 1.8585 | NT52: 1.8519 | NU52: 1.8494 | NV52: 1.8544 | NW52: 1.8424 | NZ52: 1.8393 | OA52: 1.8326 | OB52: 1.8312 | OC52: 1.8425 | OD52: 1.8298 | OG52: 1.8242 | OH52: 1.8311 | OI52: 1.8164 | OJ52: 1.8174 | OK52: 1.8112 | ON52: 1.82 | OO52: 1.8172 | OP52: 1.8193 | OQ52: 1.8169 | OR52: 1.8102 | OU52: 1.8114 | OV52: 1.8094 | OW52: 1.7994 | OX52: 1.7893 | OY52: 1.7928 | OZ52: 1.7899 | PJ52: 1.8023 | PK52: 1.8158 | PL52: 1.8288 | PM52: 1.7877 | PN52: 1.7753 | PP52: 1.7761 | PQ52: 1.7807 | PR52: 1.7768 | PS52: 1.7779 | PT52: 1.781 | PW52: 1.8054 | PX52: 1.8055 | PY52: 1.8075 | PZ52: 1.8052 | QA52: 1.8143 | QD52: 1.8312 | QE52: 1.8314 | QF52: 1.8175 | QG52: 1.8252 | QH52: 1.8299 | QK52: 1.8316 | QL52: 1.8272 | QM52: 1.8233 | QN52: 1.8194 | QO52: 1.8172 | QR52: 1.8063 | QS52: 1.8171 | QT52: 1.8244 | QU52: 1.8209 | QV52: 1.8199 | QZ52: 1.8171 | RA52: 1.8136 | RB52: 1.8192 | RC52: 1.8128 | RF52: 1.7933 | RG52: 1.7829 | RH52: 1.7809 | RI52: 1.7812 | RJ52: 1.7623 | RM52: 1.7627 | RN52: 1.751 | RO52: 1.7389 | RP52: 1.7548 | RQ52: 1.7601 | RT52: 1.7697 | RU52: 1.7654 | RV52: 1.7444 | RW52: 1.7473 | SC52: 1.7654 | SD52: 1.7631 | SE52: 1.7648 | SF52: 1.767 | SH52: 1.7622 | SI52: 1.7592 | SJ52: 1.7514 | SK52: 1.7588 | SL52: 1.7658 | SO52: 1.7585 | SP52: 1.7345 | SQ52: 1.7382 | SR52: 1.7448 | SS52: 1.7519 | SV52: 1.7484 | SW52: 1.7405 | SX52: 1.7216 | SY52: 1.7193 | SZ52: 1.709 | TC52: 1.7009 | TD52: 1.7036 | TE52: 1.7128 | TF52: 1.7081 | TG52: 1.7207 | TJ52: 1.7275 | TK52: 1.7376 | TL52: 1.7476 | TM52: 1.7475 | TN52: 1.7427 | TQ52: 1.7446 | TR52: 1.7324 | TS52: 1.727 | TT52: 1.7299 | TX52: 1.7375 | TY52: 1.7437 | TZ52: 1.7454 | UA52: 1.7351 | UB52: 1.7314 | UE52: 1.717 | UF52: 1.733 | UG52: 1.7448 | UH52: 1.741 | UI52: 1.7463
D53: 中债国债到期收益率:30年 | E53: S0059752 | H53: 1.8397 | I53: 1.8501 | L53: 1.8327 | M53: 1.8602 | N53: 1.8702 | O53: 1.8932 | P53: 1.8752 | S53: 1.9051 | T53: 1.8652 | U53: 1.8602 | V53: 1.8677 | W53: 1.915 | Z53: 1.9225 | AA53: 1.89 | AB53: 1.9 | AC53: 1.9 | AD53: 1.89 | AF53: 1.891 | AG53: 1.8675 | AP53: 1.8375 | AQ53: 1.805 | AR53: 1.8025 | AS53: 1.805 | AU53: 1.825 | AV53: 1.8075 | AW53: 1.809 | AX53: 1.799 | AY53: 1.82 | BB53: 1.86 | BC53: 1.86 | BD53: 1.84 | BE53: 1.87 | BF53: 1.905 | BI53: 1.945 | BJ53: 1.915 | BK53: 1.91 | BL53: 1.935 | BM53: 1.905 | BP53: 1.89 | BQ53: 1.9 | BR53: 1.8925 | BS53: 1.9325 | BT53: 1.975 | BW53: 1.985 | BX53: 2.035 | BY53: 2.0125 | BZ53: 2.04 | CA53: 2.04 | CD53: 2.115 | CE53: 2.1151 | CF53: 2.1051 | CG53: 2.0526 | CH53: 2.0676 | CK53: 2.0501 | CL53: 2.0276 | CM53: 2.0001 | CN53: 2.0101 | CO53: 2.0251 | CR53: 2.0226 | CS53: 2.0201 | CT53: 1.9801 | CU53: 1.9052 | CY53: 1.8252 | CZ53: 1.8551 | DA53: 1.8552 | DB53: 1.8602 | DC53: 1.8627 | DF53: 1.8602 | DG53: 1.8602 | DH53: 1.8652 | DI53: 1.8982 | DJ53: 1.9042 | DM53: 1.9227 | DN53: 1.9052 | DO53: 1.9279 | DP53: 1.9327 | DQ53: 1.9276 | DS53: 1.9252 | DT53: 1.9005 | DU53: 1.8225 | DV53: 1.824 | EB53: 1.827 | EC53: 1.8475 | ED53: 1.8375 | EE53: 1.8425 | EH53: 1.905 | EI53: 1.879 | EJ53: 1.8775 | EK53: 1.8825 | EL53: 1.878 | EO53: 1.861 | EP53: 1.872 | EQ53: 1.885 | ER53: 1.887 | ES53: 1.889 | EV53: 1.8875 | EW53: 1.901 | EX53: 1.906 | EY53: 1.916 | EZ53: 1.896 | FD53: 1.895 | FE53: 1.891 | FF53: 1.896 | FG53: 1.876 | FJ53: 1.87 | FK53: 1.8695 | FL53: 1.849 | FM53: 1.8485 | FN53: 1.8495 | FQ53: 1.851 | FR53: 1.8425 | FS53: 1.8455 | FT53: 1.8431 | FU53: 1.8376 | FX53: 1.8381 | FY53: 1.8506 | FZ53: 1.8621 | GA53: 1.8491 | GB53: 1.8496 | GE53: 1.8611 | GF53: 1.8516 | GG53: 1.8451 | GH53: 1.8486 | GI53: 1.8516 | GL53: 1.8536 | GM53: 1.8596 | GN53: 1.8566 | GO53: 1.8746 | GP53: 1.8741 | GS53: 1.8821 | GT53: 1.8601 | GU53: 1.8661 | GV53: 1.883 | GW53: 1.8885 | GZ53: 1.9115 | HA53: 1.9335 | HB53: 1.938 | HC53: 1.979 | HD53: 1.9725 | HG53: 1.9525 | HH53: 1.998 | HI53: 1.96 | HJ53: 1.945 | HK53: 1.949 | HN53: 1.95 | HO53: 1.9585 | HP53: 1.958 | HQ53: 1.951 | HR53: 1.96 | HU53: 1.995 | HV53: 2.017 | HW53: 2.02 | HX53: 2.0275 | HY53: 2.0475 | IB53: 2.1145 | IC53: 2.0975 | ID53: 2.105 | IE53: 2.075 | IF53: 2.0775 | II53: 2.05 | IJ53: 2.035 | IK53: 2.07 | IL53: 2.1108 | IM53: 2.1375 | IP53: 2.1165 | IQ53: 2.1 | IR53: 2.075 | IS53: 2.085 | IT53: 2.1125 | IW53: 2.1475 | IX53: 2.171 | IY53: 2.204 | IZ53: 2.208 | JA53: 2.184 | JD53: 2.1875 | JE53: 2.1675 | JF53: 2.15 | JG53: 2.1701 | JH53: 2.1996 | JK53: 2.189 | JL53: 2.215 | JM53: 2.2501 | JN53: 2.23 | JO53: 2.217 | JQ53: 2.218 | JR53: 2.242 | JS53: 2.2461 | KB53: 2.2629 | KC53: 2.2829 | KD53: 2.2328 | KF53: 2.2729 | KG53: 2.2678 | KH53: 2.2603 | KI53: 2.2414 | KJ53: 2.2002 | KM53: 2.2162 | KN53: 2.1871 | KO53: 2.1821 | KP53: 2.1946 | KQ53: 2.2126 | KT53: 2.2031 | KU53: 2.17 | KV53: 2.177 | KW53: 2.1625 | KX53: 2.1431 | LA53: 2.1376 | LB53: 2.1421 | LC53: 2.1391 | LD53: 2.1596 | LE53: 2.1581 | LH53: 2.1476 | LI53: 2.1537 | LJ53: 2.1431 | LK53: 2.1491 | LL53: 2.1481 | LO53: 2.1391 | LP53: 2.1381 | LQ53: 2.1506 | LR53: 2.1531 | LS53: 2.1576 | LV53: 2.1586 | LW53: 2.1751 | LX53: 2.1926 | LY53: 2.2001 | LZ53: 2.1851 | MC53: 2.1901 | MD53: 2.2051 | ME53: 2.2351 | MF53: 2.2761 | MG53: 2.2571 | MJ53: 2.2577 | MK53: 2.2527 | ML53: 2.2412 | MM53: 2.2252 | MN53: 2.2487 | MQ53: 2.2792 | MR53: 2.2802 | MS53: 2.2422 | MT53: 2.2512 | MU53: 2.2252 | MX53: 2.2412 | MY53: 2.2232 | MZ53: 2.2202 | NA53: 2.2252 | NB53: 2.2233 | NE53: 2.2583 | NF53: 2.2628 | NG53: 2.2674 | NK53: 2.2529 | NL53: 2.2822 | NM53: 2.3104 | NN53: 2.3345 | NO53: 2.319 | NP53: 2.3024 | NS53: 2.292 | NT53: 2.2926 | NU53: 2.3028 | NV53: 2.3058 | NW53: 2.3036 | NZ53: 2.3417 | OA53: 2.3351 | OB53: 2.3026 | OC53: 2.3101 | OD53: 2.2871 | OG53: 2.27 | OH53: 2.285 | OI53: 2.277 | OJ53: 2.28 | OK53: 2.289 | ON53: 2.281 | OO53: 2.28 | OP53: 2.283 | OQ53: 2.271 | OR53: 2.251 | OU53: 2.248 | OV53: 2.247 | OW53: 2.2455 | OX53: 2.246 | OY53: 2.244 | OZ53: 2.246 | PJ53: 2.2426 | PK53: 2.255 | PL53: 2.2951 | PM53: 2.2896 | PN53: 2.2726 | PP53: 2.2696 | PQ53: 2.2827 | PR53: 2.2752 | PS53: 2.2717 | PT53: 2.2812 | PW53: 2.3292 | PX53: 2.3328 | PY53: 2.3503 | PZ53: 2.3404 | QA53: 2.3665 | QD53: 2.3917 | QE53: 2.3806 | QF53: 2.3607 | QG53: 2.391 | QH53: 2.3881 | QK53: 2.373 | QL53: 2.3457 | QM53: 2.3457 | QN53: 2.3498 | QO53: 2.3497 | QR53: 2.3286 | QS53: 2.3521 | QT53: 2.3667 | QU53: 2.3733 | QV53: 2.3725 | QZ53: 2.3597 | RA53: 2.3377 | RB53: 2.3393 | RC53: 2.3055 | RF53: 2.2816 | RG53: 2.2805 | RH53: 2.2784 | RI53: 2.281 | RJ53: 2.25 | RM53: 2.2556 | RN53: 2.2375 | RO53: 2.2137 | RP53: 2.2353 | RQ53: 2.2472 | RT53: 2.2557 | RU53: 2.242 | RV53: 2.219 | RW53: 2.218 | SC53: 2.239 | SD53: 2.238 | SE53: 2.2455 | SF53: 2.248 | SH53: 2.2361 | SI53: 2.232 | SJ53: 2.234 | SK53: 2.241 | SL53: 2.253 | SO53: 2.244 | SP53: 2.221 | SQ53: 2.2311 | SR53: 2.231 | SS53: 2.2345 | SV53: 2.226 | SW53: 2.2205 | SX53: 2.208 | SY53: 2.2095 | SZ53: 2.205 | TC53: 2.191 | TD53: 2.191 | TE53: 2.205 | TF53: 2.191 | TG53: 2.204 | TJ53: 2.213 | TK53: 2.22 | TL53: 2.235 | TM53: 2.238 | TN53: 2.2215 | TQ53: 2.2215 | TR53: 2.2175 | TS53: 2.2181 | TT53: 2.2201 | TX53: 2.2216 | TY53: 2.2291 | TZ53: 2.2311 | UA53: 2.2201 | UB53: 2.2176 | UE53: 2.209 | UF53: 2.236 | UG53: 2.2525 | UH53: 2.258 | UI53: 2.2685
D54: 中债国开债到期收益率:10年 | E54: M1004271 | H54: 1.6563 | I54: 1.6463 | L54: 1.6313 | M54: 1.625 | N54: 1.6225 | O54: 1.65 | P54: 1.645 | S54: 1.6725 | T54: 1.65 | U54: 1.65 | V54: 1.6625 | W54: 1.67 | Z54: 1.685 | AA54: 1.6676 | AB54: 1.6751 | AC54: 1.6901 | AD54: 1.6851 | AF54: 1.6801 | AG54: 1.6526 | AP54: 1.6351 | AQ54: 1.6012 | AR54: 1.6042 | AS54: 1.6067 | AU54: 1.6342 | AV54: 1.6275 | AW54: 1.6336 | AX54: 1.6346 | AY54: 1.6546 | BB54: 1.6934 | BC54: 1.7007 | BD54: 1.6626 | BE54: 1.6953 | BF54: 1.7303 | BI54: 1.7728 | BJ54: 1.748 | BK54: 1.7454 | BL54: 1.7779 | BM54: 1.743 | BP54: 1.7105 | BQ54: 1.7205 | BR54: 1.7165 | BS54: 1.7555 | BT54: 1.8035 | BW54: 1.823 | BX54: 1.9004 | BY54: 1.8531 | BZ54: 1.873 | CA54: 1.8506 | CD54: 1.9406 | CE54: 1.9331 | CF54: 1.9132 | CG54: 1.8598 | CH54: 1.8783 | CK54: 1.8609 | CL54: 1.8533 | CM54: 1.8233 | CN54: 1.8448 | CO54: 1.8583 | CR54: 1.8409 | CS54: 1.8459 | CT54: 1.818 | CU54: 1.7385 | CY54: 1.6675 | CZ54: 1.7075 | DA54: 1.705 | DB54: 1.7 | DC54: 1.7 | DF54: 1.7025 | DG54: 1.69 | DH54: 1.67 | DI54: 1.6875 | DJ54: 1.681 | DM54: 1.6951 | DN54: 1.6801 | DO54: 1.6971 | DP54: 1.6991 | DQ54: 1.6961 | DS54: 1.6951 | DT54: 1.6876 | DU54: 1.6551 | DV54: 1.6591 | EB54: 1.6592 | EC54: 1.6732 | ED54: 1.6612 | EE54: 1.6642 | EH54: 1.7227 | EI54: 1.6993 | EJ54: 1.7003 | EK54: 1.7123 | EL54: 1.7133 | EO54: 1.6928 | EP54: 1.7028 | EQ54: 1.71 | ER54: 1.7186 | ES54: 1.7034 | EV54: 1.694 | EW54: 1.71 | EX54: 1.7155 | EY54: 1.7265 | EZ54: 1.709 | FD54: 1.7171 | FE54: 1.7107 | FF54: 1.7146 | FG54: 1.6967 | FJ54: 1.6992 | FK54: 1.7047 | FL54: 1.6977 | FM54: 1.7066 | FN54: 1.7032 | FQ54: 1.7156 | FR54: 1.7046 | FS54: 1.7091 | FT54: 1.7091 | FU54: 1.677 | FX54: 1.6775 | FY54: 1.6875 | FZ54: 1.695 | GA54: 1.685 | GB54: 1.6825 | GE54: 1.69 | GF54: 1.681 | GG54: 1.677 | GH54: 1.6825 | GI54: 1.685 | GL54: 1.685 | GM54: 1.694 | GN54: 1.695 | GO54: 1.7165 | GP54: 1.7176 | GS54: 1.7261 | GT54: 1.7081 | GU54: 1.7151 | GV54: 1.7171 | GW54: 1.7171 | GZ54: 1.7336 | HA54: 1.7581 | HB54: 1.7676 | HC54: 1.8126 | HD54: 1.8076 | HG54: 1.7782 | HH54: 1.8177 | HI54: 1.7852 | HJ54: 1.7627 | HK54: 1.7612 | HN54: 1.7827 | HO54: 1.7852 | HP54: 1.7842 | HQ54: 1.7777 | HR54: 1.7783 | HU54: 1.8103 | HV54: 1.8293 | HW54: 1.8278 | HX54: 1.8403 | HY54: 1.8558 | IB54: 1.9079 | IC54: 1.8904 | ID54: 1.8975 | IE54: 1.8655 | IF54: 1.8781 | II54: 1.8532 | IJ54: 1.8456 | IK54: 1.8531 | IL54: 1.8826 | IM54: 1.8756 | IP54: 1.8657 | IQ54: 1.8706 | IR54: 1.8466 | IS54: 1.8591 | IT54: 1.8731 | IW54: 1.8987 | IX54: 1.9564 | IY54: 2.0101 | IZ54: 2.0432 | JA54: 2.0284 | JD54: 2.0288 | JE54: 2.0116 | JF54: 1.9866 | JG54: 1.9989 | JH54: 2.0268 | JK54: 2.0079 | JL54: 2.0221 | JM54: 2.0454 | JN54: 2.0397 | JO54: 2.038 | JQ54: 2.042 | JR54: 2.0571 | JS54: 2.0372 | KB54: 2.0332 | KC54: 2.0359 | KD54: 1.9994 | KF54: 2.0216 | KG54: 2.0173 | KH54: 2.0227 | KI54: 2.0203 | KJ54: 1.9904 | KM54: 2.0122 | KN54: 1.9916 | KO54: 1.9943 | KP54: 1.9985 | KQ54: 2.0013 | KT54: 1.9964 | KU54: 1.9694 | KV54: 1.9705 | KW54: 1.9579 | KX54: 1.9254 | LA54: 1.918 | LB54: 1.9232 | LC54: 1.9181 | LD54: 1.9331 | LE54: 1.9489 | LH54: 1.9416 | LI54: 1.9391 | LJ54: 1.9329 | LK54: 1.9373 | LL54: 1.9371 | LO54: 1.933 | LP54: 1.934 | LQ54: 1.9397 | LR54: 1.9404 | LS54: 1.9415 | LV54: 1.9444 | LW54: 1.9556 | LX54: 1.9766 | LY54: 1.9952 | LZ54: 1.974 | MC54: 1.9717 | MD54: 1.9851 | ME54: 1.9979 | MF54: 2.0312 | MG54: 2.0062 | MJ54: 2.0087 | MK54: 1.9912 | ML54: 1.9812 | MM54: 1.9737 | MN54: 1.9887 | MQ54: 2.0102 | MR54: 2.0052 | MS54: 1.9762 | MT54: 1.9837 | MU54: 1.9662 | MX54: 1.9822 | MY54: 1.9737 | MZ54: 1.9762 | NA54: 1.9812 | NB54: 1.9817 | NE54: 2.0112 | NF54: 2.0142 | NG54: 2.0012 | NK54: 1.9862 | NL54: 2.0027 | NM54: 2.0312 | NN54: 2.0467 | NO54: 2.0337 | NP54: 2.0287 | NS54: 2.0187 | NT54: 2.0212 | NU54: 2.0207 | NV54: 2.0267 | NW54: 2.0152 | NZ54: 2.0187 | OA54: 2.0035 | OB54: 1.9845 | OC54: 1.9925 | OD54: 1.9735 | OG54: 1.9725 | OH54: 1.9825 | OI54: 1.9775 | OJ54: 1.9835 | OK54: 1.9865 | ON54: 1.9825 | OO54: 1.9875 | OP54: 1.991 | OQ54: 1.984 | OR54: 1.9645 | OU54: 1.9525 | OV54: 1.955 | OW54: 1.952 | OX54: 1.946 | OY54: 1.946 | OZ54: 1.9465 | PJ54: 1.9475 | PK54: 1.9615 | PL54: 1.9855 | PM54: 1.9755 | PN54: 1.9625 | PP54: 1.9635 | PQ54: 1.968 | PR54: 1.9585 | PS54: 1.954 | PT54: 1.9595 | PW54: 1.9815 | PX54: 1.9678 | PY54: 1.9653 | PZ54: 1.9615 | QA54: 1.9646 | QD54: 1.9769 | QE54: 1.9751 | QF54: 1.9632 | QG54: 1.9724 | QH54: 1.9705 | QK54: 1.9729 | QL54: 1.9669 | QM54: 1.9618 | QN54: 1.9618 | QO54: 1.961 | QR54: 1.9395 | QS54: 1.946 | QT54: 1.9551 | QU54: 1.9553 | QV54: 1.9451 | QZ54: 1.9326 | RA54: 1.9209 | RB54: 1.926 | RC54: 1.911 | RF54: 1.8868 | RG54: 1.8745 | RH54: 1.869 | RI54: 1.8681 | RJ54: 1.8408 | RM54: 1.8374 | RN54: 1.8348 | RO54: 1.8304 | RP54: 1.8464 | RQ54: 1.8639 | RT54: 1.8744 | RU54: 1.8505 | RV54: 1.8306 | RW54: 1.838 | SC54: 1.8523 | SD54: 1.8407 | SE54: 1.8332 | SF54: 1.8327 | SH54: 1.8298 | SI54: 1.8238 | SJ54: 1.8153 | SK54: 1.8232 | SL54: 1.8274 | SO54: 1.8209 | SP54: 1.8059 | SQ54: 1.8116 | SR54: 1.8158 | SS54: 1.8233 | SV54: 1.8165 | SW54: 1.811 | SX54: 1.7776 | SY54: 1.7693 | SZ54: 1.7669 | TC54: 1.7592 | TD54: 1.7603 | TE54: 1.7678 | TF54: 1.7613 | TG54: 1.771 | TJ54: 1.781 | TK54: 1.791 | TL54: 1.807 | TM54: 1.816 | TN54: 1.802 | TQ54: 1.802 | TR54: 1.783 | TS54: 1.774 | TT54: 1.775 | TX54: 1.784 | TY54: 1.791 | TZ54: 1.789 | UA54: 1.777 | UB54: 1.777 | UE54: 1.765 | UF54: 1.7785 | UG54: 1.7935 | UH54: 1.793 | UI54: 1.797
... D56: 中债城投债到期收益率(AAA):10年 | E56: M0048437 | H56: 2.1433 | I56: 2.1169 | L56: 2.091 | M56: 2.0878 | N56: 2.0795 | O56: 2.0897 | P56: 2.0883 | S56: 2.0968 | T56: 2.0968 | U56: 2.0868 | V56: 2.0809 | W56: 2.0921 | Z56: 2.0956 | AA56: 2.0849 | AB56: 2.0802 | AC56: 2.0919 | AD56: 2.0919 | AF56: 2.0885 | AG56: 2.082 | AP56: 2.07 | AQ56: 2.0502 | AR56: 2.0402 | AS56: 2.0433 | AU56: 2.0508 | AV56: 2.0452 | AW56: 2.0448 | AX56: 2.0378 | AY56: 2.0372 | BB56: 2.0435 | BC56: 2.0725 | BD56: 2.0794 | BE56: 2.1056 | BF56: 2.1306 | BI56: 2.1623 | BJ56: 2.2006 | BK56: 2.1902 | BL56: 2.2102 | BM56: 2.2202 | BP56: 2.2302 | BQ56: 2.2407 | BR56: 2.2408 | BS56: 2.2554 | BT56: 2.3005 | BW56: 2.3205 | BX56: 2.3505 | BY56: 2.3568 | BZ56: 2.345 | CA56: 2.3494 | CD56: 2.3694 | CE56: 2.38 | CF56: 2.3852 | CG56: 2.3652 | CH56: 2.3352 | CK56: 2.3256 | CL56: 2.2856 | CM56: 2.28 | CN56: 2.27 | CO56: 2.2703 | CR56: 2.2605 | CS56: 2.259 | CT56: 2.2427 | CU56: 2.1827 | CY56: 2.1202 | CZ56: 2.1311 | DA56: 2.1411 | DB56: 2.1502 | DC56: 2.1505 | DF56: 2.1603 | DG56: 2.1646 | DH56: 2.1698 | DI56: 2.1705 | DJ56: 2.1805 | DM56: 2.1898 | DN56: 2.2009 | DO56: 2.2243 | DP56: 2.2421 | DQ56: 2.25 | DS56: 2.2502 | DT56: 2.25 | DU56: 2.2303 | DV56: 2.2203 | EB56: 2.2218 | EC56: 2.2135 | ED56: 2.2 | EE56: 2.1904 | EH56: 2.1912 | EI56: 2.1889 | EJ56: 2.1892 | EK56: 2.19 | EL56: 2.1916 | EO56: 2.1936 | EP56: 2.1805 | EQ56: 2.1736 | ER56: 2.1765 | ES56: 2.1761 | EV56: 2.1717 | EW56: 2.1521 | EX56: 2.1613 | EY56: 2.1863 | EZ56: 2.1724 | FD56: 2.1724 | FE56: 2.1624 | FF56: 2.1599 | FG56: 2.151 | FJ56: 2.1505 | FK56: 2.1413 | FL56: 2.1203 | FM56: 2.1112 | FN56: 2.1001 | FQ56: 2.0799 | FR56: 2.0801 | FS56: 2.0602 | FT56: 2.0502 | FU56: 2.0403 | FX56: 2.0325 | FY56: 2.0408 | FZ56: 2.0593 | GA56: 2.0836 | GB56: 2.077 | GE56: 2.0824 | GF56: 2.0705 | GG56: 2.0637 | GH56: 2.0437 | GI56: 2.0401 | GL56: 2.03 | GM56: 2.0452 | GN56: 2.054 | GO56: 2.0638 | GP56: 2.0737 | GS56: 2.0808 | GT56: 2.0808 | GU56: 2.0708 | GV56: 2.0632 | GW56: 2.0643 | GZ56: 2.0736 | HA56: 2.0886 | HB56: 2.1186 | HC56: 2.1603 | HD56: 2.1757 | HG56: 2.17 | HH56: 2.18 | HI56: 2.1712 | HJ56: 2.1651 | HK56: 2.1551 | HN56: 2.1451 | HO56: 2.1451 | HP56: 2.1451 | HQ56: 2.1451 | HR56: 2.1475 | HU56: 2.1565 | HV56: 2.176 | HW56: 2.181 | HX56: 2.1834 | HY56: 2.2004 | IB56: 2.2462 | IC56: 2.2664 | ID56: 2.2764 | IE56: 2.3207 | IF56: 2.3305 | II56: 2.3305 | IJ56: 2.3257 | IK56: 2.3306 | IL56: 2.3452 | IM56: 2.3604 | IP56: 2.3511 | IQ56: 2.3509 | IR56: 2.3532 | IS56: 2.3382 | IT56: 2.345 | IW56: 2.3653 | IX56: 2.3753 | IY56: 2.4003 | IZ56: 2.4168 | JA56: 2.4086 | JD56: 2.408 | JE56: 2.4181 | JF56: 2.4214 | JG56: 2.4334 | JH56: 2.4399 | JK56: 2.4547 | JL56: 2.4674 | JM56: 2.5047 | JN56: 2.5329 | JO56: 2.5589 | JQ56: 2.564 | JR56: 2.5598 | JS56: 2.5398 | KB56: 2.5168 | KC56: 2.52 | KD56: 2.52 | KF56: 2.53 | KG56: 2.5166 | KH56: 2.5254 | KI56: 2.5005 | KJ56: 2.5005 | KM56: 2.485 | KN56: 2.4751 | KO56: 2.4621 | KP56: 2.4525 | KQ56: 2.4419 | KT56: 2.4219 | KU56: 2.4052 | KV56: 2.3873 | KW56: 2.3701 | KX56: 2.3505 | LA56: 2.3405 | LB56: 2.3251 | LC56: 2.3206 | LD56: 2.3466 | LE56: 2.3591 | LH56: 2.3725 | LI56: 2.3798 | LJ56: 2.3704 | LK56: 2.3745 | LL56: 2.372 | LO56: 2.372 | LP56: 2.362 | LQ56: 2.3537 | LR56: 2.3501 | LS56: 2.3504 | LV56: 2.3604 | LW56: 2.3654 | LX56: 2.3885 | LY56: 2.4108 | LZ56: 2.4116 | MC56: 2.4165 | MD56: 2.4314 | ME56: 2.4418 | MF56: 2.4619 | MG56: 2.4696 | MJ56: 2.4722 | MK56: 2.4766 | ML56: 2.4639 | MM56: 2.46 | MN56: 2.4569 | MQ56: 2.4652 | MR56: 2.4719 | MS56: 2.4753 | MT56: 2.4644 | MU56: 2.4444 | MX56: 2.4594 | MY56: 2.4535 | MZ56: 2.4493 | NA56: 2.4438 | NB56: 2.4263 | NE56: 2.4363 | NF56: 2.4461 | NG56: 2.4489 | NK56: 2.4473 | NL56: 2.4575 | NM56: 2.4628 | NN56: 2.458 | NO56: 2.458 | NP56: 2.4468 | NS56: 2.4449 | NT56: 2.4384 | NU56: 2.4395 | NV56: 2.4234 | NW56: 2.4196 | NZ56: 2.4187 | OA56: 2.4067 | OB56: 2.3911 | OC56: 2.3945 | OD56: 2.3928 | OG56: 2.3912 | OH56: 2.3941 | OI56: 2.3909 | OJ56: 2.3836 | OK56: 2.3886 | ON56: 2.3885 | OO56: 2.3932 | OP56: 2.3978 | OQ56: 2.394 | OR56: 2.3836 | OU56: 2.3785 | OV56: 2.3667 | OW56: 2.3254 | OX56: 2.2976 | OY56: 2.2776 | OZ56: 2.2776 | PJ56: 2.28 | PK56: 2.298 | PL56: 2.308 | PM56: 2.3078 | PN56: 2.3086 | PP56: 2.3102 | PQ56: 2.2995 | PR56: 2.2895 | PS56: 2.282 | PT56: 2.2837 | PW56: 2.3061 | PX56: 2.3134 | PY56: 2.3236 | PZ56: 2.3258 | QA56: 2.3215 | QD56: 2.3278 | QE56: 2.3294 | QF56: 2.3289 | QG56: 2.3225 | QH56: 2.323 | QK56: 2.3285 | QL56: 2.3249 | QM56: 2.3222 | QN56: 2.3108 | QO56: 2.2992 | QR56: 2.2958 | QS56: 2.2858 | QT56: 2.2811 | QU56: 2.2814 | QV56: 2.2717 | QZ56: 2.2605 | RA56: 2.2505 | RB56: 2.2455 | RC56: 2.2334 | RF56: 2.2282 | RG56: 2.2163 | RH56: 2.2199 | RI56: 2.217 | RJ56: 2.1964 | RM56: 2.1958 | RN56: 2.1953 | RO56: 2.1938 | RP56: 2.1934 | RQ56: 2.1931 | RT56: 2.217 | RU56: 2.2123 | RV56: 2.205 | RW56: 2.2065 | SC56: 2.2257 | SD56: 2.2248 | SE56: 2.225 | SF56: 2.2203 | SH56: 2.2226 | SI56: 2.2262 | SJ56: 2.2228 | SK56: 2.2289 | SL56: 2.2395 | SO56: 2.2475 | SP56: 2.2393 | SQ56: 2.2247 | SR56: 2.2247 | SS56: 2.2266 | SV56: 2.1904 | SW56: 2.1704 | SX56: 2.1654 | SY56: 2.1501 | SZ56: 2.1439 | TC56: 2.13 | TD56: 2.115 | TE56: 2.1051 | TF56: 2.1039 | TG56: 2.1103 | TJ56: 2.1212 | TK56: 2.1302 | TL56: 2.1352 | TM56: 2.1703 | TN56: 2.1833 | TQ56: 2.1817 | TR56: 2.1666 | TS56: 2.1482 | TT56: 2.1301 | TX56: 2.1309 | TY56: 2.1363 | TZ56: 2.1407 | UA56: 2.1299 | UB56: 2.1331 | UE56: 2.1236 | UF56: 2.1321 | UG56: 2.138 | UH56: 2.1458 | UI56: 2.1476
D57: 美国:国债收益率:2年 | E57: G0000887 | H57: 4.25 | I57: 4.28 | L57: 4.28 | M57: 4.3 | N57: 4.28 | O57: 4.27 | P57: 4.4 | S57: 4.4 | T57: 4.37 | U57: 4.27 | V57: 4.23 | W57: 4.27 | AA57: 4.29 | AB57: 4.29 | AC57: 4.29 | AD57: 4.27 | AG57: 4.17 | AH57: 4.19 | AI57: 4.21 | AJ57: 4.18 | AK57: 4.22 | AN57: 4.26 | AO57: 4.21 | AP57: 4.17 | AQ57: 4.21 | AR57: 4.29 | AU57: 4.28 | AV57: 4.29 | AW57: 4.36 | AX57: 4.31 | AY57: 4.26 | BC57: 4.29 | BD57: 4.28 | BE57: 4.28 | BF57: 4.19 | BI57: 4.13 | BJ57: 4.07 | BK57: 4.05 | BL57: 4.07 | BM57: 3.99 | BP57: 3.96 | BQ57: 3.96 | BR57: 3.99 | BS57: 3.96 | BT57: 3.99 | BW57: 3.89 | BX57: 3.94 | BY57: 4.01 | BZ57: 3.94 | CA57: 4.02 | CD57: 4.06 | CE57: 4.04 | CF57: 3.99 | CG57: 3.95 | CH57: 3.94 | CK57: 4.04 | CL57: 3.96 | CM57: 3.98 | CN57: 3.97 | CO57: 3.89 | CR57: 3.89 | CS57: 3.87 | CT57: 3.91 | CU57: 3.71 | CV57: 3.68 | CY57: 3.73 | CZ57: 3.71 | DA57: 3.91 | DB57: 3.84 | DC57: 3.96 | DF57: 3.84 | DG57: 3.84 | DH57: 3.77 | DI57: 3.81 | DM57: 3.75 | DN57: 3.76 | DO57: 3.81 | DP57: 3.77 | DQ57: 3.74 | DT57: 3.67 | DU57: 3.65 | DV57: 3.6 | DW57: 3.7 | DX57: 3.83 | EA57: 3.83 | EB57: 3.78 | EC57: 3.78 | ED57: 3.9 | EE57: 3.88 | EH57: 3.98 | EI57: 4.02 | EJ57: 4.05 | EK57: 3.96 | EL57: 3.98 | EO57: 3.97 | EP57: 3.97 | EQ57: 4 | ER57: 4 | ES57: 4 | EW57: 3.92 | EX57: 3.96 | EY57: 3.92 | EZ57: 3.89 | FC57: 3.94 | FD57: 3.96 | FE57: 3.87 | FF57: 3.92 | FG57: 4.04 | FJ57: 4.01 | FK57: 4.01 | FL57: 3.94 | FM57: 3.9 | FN57: 3.96 | FQ57: 3.97 | FR57: 3.94 | FS57: 3.94 | FU57: 3.9 | FX57: 3.84 | FY57: 3.75 | FZ57: 3.74 | GA57: 3.7 | GB57: 3.73 | GE57: 3.72 | GF57: 3.78 | GG57: 3.78 | GH57: 3.88 | GL57: 3.9 | GM57: 3.9 | GN57: 3.86 | GO57: 3.86 | GP57: 3.9 | GS57: 3.9 | GT57: 3.95 | GU57: 3.88 | GV57: 3.91 | GW57: 3.88 | GZ57: 3.85 | HA57: 3.83 | HB57: 3.88 | HC57: 3.91 | HD57: 3.91 | HG57: 3.91 | HH57: 3.86 | HI57: 3.94 | HJ57: 3.94 | HK57: 3.69 | HN57: 3.69 | HO57: 3.72 | HP57: 3.69 | HQ57: 3.72 | HR57: 3.76 | HU57: 3.76 | HV57: 3.72 | HW57: 3.67 | HX57: 3.74 | HY57: 3.75 | IB57: 3.77 | IC57: 3.75 | ID57: 3.74 | IE57: 3.79 | IF57: 3.68 | II57: 3.73 | IJ57: 3.61 | IK57: 3.59 | IL57: 3.62 | IM57: 3.59 | IQ57: 3.66 | IR57: 3.61 | IS57: 3.59 | IT57: 3.51 | IW57: 3.49 | IX57: 3.54 | IY57: 3.54 | IZ57: 3.52 | JA57: 3.56 | JD57: 3.54 | JE57: 3.51 | JF57: 3.52 | JG57: 3.57 | JH57: 3.57 | JK57: 3.61 | JL57: 3.53 | JM57: 3.57 | JN57: 3.64 | JO57: 3.63 | JR57: 3.63 | JS57: 3.6 | JT57: 3.55 | JU57: 3.55 | JV57: 3.58 | JY57: 3.6 | JZ57: 3.57 | KA57: 3.58 | KB57: 3.6 | KC57: 3.52 | KG57: 3.48 | KH57: 3.5 | KI57: 3.41 | KJ57: 3.46 | KM57: 3.46 | KN57: 3.45 | KO57: 3.45 | KP57: 3.48 | KQ57: 3.48 | KT57: 3.48 | KU57: 3.47 | KV57: 3.59 | KW57: 3.61 | KX57: 3.6 | LA57: 3.6 | LB57: 3.58 | LC57: 3.63 | LD57: 3.57 | LE57: 3.55 | LH57: 3.58 | LJ57: 3.56 | LK57: 3.58 | LL57: 3.62 | LO57: 3.6 | LP57: 3.58 | LQ57: 3.58 | LR57: 3.55 | LS57: 3.51 | LV57: 3.46 | LW57: 3.43 | LX57: 3.45 | LZ57: 3.47 | MC57: 3.54 | MD57: 3.51 | ME57: 3.49 | MF57: 3.52 | MG57: 3.56 | MJ57: 3.57 | MK57: 3.61 | ML57: 3.54 | MM57: 3.52 | MN57: 3.52 | MQ57: 3.51 | MR57: 3.48 | MS57: 3.49 | MT57: 3.46 | MU57: 3.48 | MX57: 3.44 | MY57: 3.48 | MZ57: 3.47 | NB57: 3.46 | NE57: 3.45 | NF57: 3.45 | NG57: 3.47 | NI57: 3.47 | NL57: 3.46 | NM57: 3.47 | NN57: 3.47 | NO57: 3.49 | NP57: 3.54 | NS57: 3.54 | NT57: 3.53 | NU57: 3.51 | NV57: 3.56 | NW57: 3.59 | OA57: 3.6 | OB57: 3.6 | OC57: 3.61 | OD57: 3.6 | OG57: 3.56 | OH57: 3.53 | OI57: 3.56 | OJ57: 3.53 | OK57: 3.52 | ON57: 3.57 | OO57: 3.57 | OP57: 3.57 | OQ57: 3.47 | OR57: 3.5 | OU57: 3.48 | OV57: 3.45 | OW57: 3.52 | OX57: 3.47 | OY57: 3.4 | PC57: 3.43 | PD57: 3.47 | PE57: 3.47 | PF57: 3.48 | PI57: 3.43 | PJ57: 3.43 | PK57: 3.45 | PL57: 3.42 | PM57: 3.38 | PP57: 3.47 | PQ57: 3.51 | PR57: 3.54 | PS57: 3.57 | PT57: 3.56 | PW57: 3.56 | PX57: 3.57 | PY57: 3.64 | PZ57: 3.76 | QA57: 3.73 | QD57: 3.68 | QE57: 3.68 | QF57: 3.76 | QG57: 3.79 | QH57: 3.88 | QK57: 3.83 | QL57: 3.9 | QM57: 3.84 | QN57: 3.96 | QO57: 3.88 | QR57: 3.82 | QS57: 3.79 | QT57: 3.81 | QU57: 3.79 | QV57: 3.84 | QY57: 3.84 | QZ57: 3.81 | RA57: 3.79 | RB57: 3.78 | RC57: 3.81 | RF57: 3.78 | RG57: 3.76 | RH57: 3.76 | RI57: 3.78 | RJ57: 3.71 | RM57: 3.72 | RN57: 3.78 | RO57: 3.79 | RP57: 3.83 | RQ57: 3.78 | RT57: 3.78 | RU57: 3.84 | RV57: 3.92 | RW57: 3.88 | RX57: 3.88 | SA57: 3.95 | SB57: 3.93 | SC57: 3.87 | SD57: 3.92 | SE57: 3.9 | SH57: 3.95 | SI57: 4 | SJ57: 3.98 | SK57: 4 | SL57: 4.09 | SO57: 4.07 | SP57: 4.13 | SQ57: 4.04 | SR57: 4.08 | SS57: 4.13 | SW57: 4.01 | SX57: 4 | SY57: 3.99 | SZ57: 3.98 | TC57: 4.05 | TD57: 4.05 | TE57: 4.08 | TF57: 4.05 | TG57: 4.17 | TJ57: 4.15 | TK57: 4.13 | TL57: 4.13 | TM57: 4.05 | TN57: 4.09 | TQ57: 4.07 | TR57: 4.05 | TS57: 4.2 | TT57: 4.19 | TX57: 4.24 | TY57: 4.16 | TZ57: 4.11 | UA57: 4.09 | UB57: 4.07 | UE57: 4.1 | UF57: 4.14 | UG57: 4.17 | UH57: 4.14
D58: 美国:国债收益率:10年 | E58: G0000891 | H58: 4.57 | I58: 4.6 | L58: 4.62 | M58: 4.67 | N58: 4.67 | O58: 4.68 | P58: 4.77 | S58: 4.79 | T58: 4.78 | U58: 4.66 | V58: 4.61 | W58: 4.61 | AA58: 4.57 | AB58: 4.6 | AC58: 4.65 | AD58: 4.63 | AG58: 4.53 | AH58: 4.55 | AI58: 4.55 | AJ58: 4.52 | AK58: 4.58 | AN58: 4.54 | AO58: 4.52 | AP58: 4.43 | AQ58: 4.45 | AR58: 4.49 | AU58: 4.51 | AV58: 4.54 | AW58: 4.62 | AX58: 4.52 | AY58: 4.47 | BC58: 4.55 | BD58: 4.53 | BE58: 4.5 | BF58: 4.42 | BI58: 4.4 | BJ58: 4.3 | BK58: 4.25 | BL58: 4.29 | BM58: 4.24 | BP58: 4.16 | BQ58: 4.22 | BR58: 4.28 | BS58: 4.29 | BT58: 4.32 | BW58: 4.22 | BX58: 4.28 | BY58: 4.32 | BZ58: 4.27 | CA58: 4.31 | CD58: 4.31 | CE58: 4.29 | CF58: 4.25 | CG58: 4.24 | CH58: 4.25 | CK58: 4.34 | CL58: 4.31 | CM58: 4.35 | CN58: 4.38 | CO58: 4.27 | CR58: 4.23 | CS58: 4.17 | CT58: 4.2 | CU58: 4.06 | CV58: 4.01 | CY58: 4.15 | CZ58: 4.26 | DA58: 4.34 | DB58: 4.4 | DC58: 4.48 | DF58: 4.38 | DG58: 4.35 | DH58: 4.29 | DI58: 4.34 | DM58: 4.42 | DN58: 4.41 | DO58: 4.4 | DP58: 4.32 | DQ58: 4.29 | DT58: 4.23 | DU58: 4.19 | DV58: 4.17 | DW58: 4.25 | DX58: 4.33 | EA58: 4.36 | EB58: 4.3 | EC58: 4.26 | ED58: 4.37 | EE58: 4.37 | EH58: 4.45 | EI58: 4.49 | EJ58: 4.53 | EK58: 4.45 | EL58: 4.43 | EO58: 4.46 | EP58: 4.48 | EQ58: 4.58 | ER58: 4.54 | ES58: 4.51 | EW58: 4.43 | EX58: 4.47 | EY58: 4.43 | EZ58: 4.41 | FC58: 4.46 | FD58: 4.46 | FE58: 4.37 | FF58: 4.4 | FG58: 4.51 | FJ58: 4.49 | FK58: 4.47 | FL58: 4.41 | FM58: 4.36 | FN58: 4.41 | FQ58: 4.46 | FR58: 4.39 | FS58: 4.38 | FU58: 4.38 | FX58: 4.34 | FY58: 4.3 | FZ58: 4.29 | GA58: 4.26 | GB58: 4.29 | GE58: 4.24 | GF58: 4.26 | GG58: 4.3 | GH58: 4.35 | GL58: 4.4 | GM58: 4.42 | GN58: 4.34 | GO58: 4.35 | GP58: 4.43 | GS58: 4.43 | GT58: 4.5 | GU58: 4.46 | GV58: 4.47 | GW58: 4.44 | GZ58: 4.38 | HA58: 4.35 | HB58: 4.4 | HC58: 4.43 | HD58: 4.4 | HG58: 4.42 | HH58: 4.34 | HI58: 4.38 | HJ58: 4.37 | HK58: 4.23 | HN58: 4.22 | HO58: 4.22 | HP58: 4.22 | HQ58: 4.23 | HR58: 4.27 | HU58: 4.27 | HV58: 4.29 | HW58: 4.24 | HX58: 4.29 | HY58: 4.33 | IB58: 4.34 | IC58: 4.3 | ID58: 4.29 | IE58: 4.33 | IF58: 4.26 | II58: 4.28 | IJ58: 4.26 | IK58: 4.24 | IL58: 4.22 | IM58: 4.23 | IQ58: 4.28 | IR58: 4.22 | IS58: 4.17 | IT58: 4.1 | IW58: 4.05 | IX58: 4.08 | IY58: 4.04 | IZ58: 4.01 | JA58: 4.06 | JD58: 4.05 | JE58: 4.04 | JF58: 4.06 | JG58: 4.11 | JH58: 4.14 | JK58: 4.15 | JL58: 4.12 | JM58: 4.16 | JN58: 4.18 | JO58: 4.2 | JR58: 4.15 | JS58: 4.16 | JT58: 4.12 | JU58: 4.1 | JV58: 4.13 | JY58: 4.18 | JZ58: 4.14 | KA58: 4.13 | KB58: 4.14 | KC58: 4.05 | KG58: 4.03 | KH58: 4.05 | KI58: 3.99 | KJ58: 4.02 | KM58: 4 | KN58: 3.98 | KO58: 3.97 | KP58: 4.01 | KQ58: 4.02 | KT58: 4.01 | KU58: 3.99 | KV58: 4.08 | KW58: 4.11 | KX58: 4.11 | LA58: 4.13 | LB58: 4.1 | LC58: 4.17 | LD58: 4.11 | LE58: 4.11 | LH58: 4.13 | LJ58: 4.08 | LK58: 4.11 | LL58: 4.14 | LO58: 4.13 | LP58: 4.12 | LQ58: 4.13 | LR58: 4.1 | LS58: 4.06 | LV58: 4.04 | LW58: 4.01 | LX58: 4 | LZ58: 4.02 | MC58: 4.09 | MD58: 4.09 | ME58: 4.06 | MF58: 4.11 | MG58: 4.14 | MJ58: 4.17 | MK58: 4.18 | ML58: 4.13 | MM58: 4.14 | MN58: 4.19 | MQ58: 4.18 | MR58: 4.15 | MS58: 4.16 | MT58: 4.12 | MU58: 4.16 | MX58: 4.17 | MY58: 4.18 | MZ58: 4.15 | NB58: 4.14 | NE58: 4.12 | NF58: 4.14 | NG58: 4.18 | NI58: 4.19 | NL58: 4.17 | NM58: 4.18 | NN58: 4.15 | NO58: 4.19 | NP58: 4.18 | NS58: 4.19 | NT58: 4.18 | NU58: 4.15 | NV58: 4.17 | NW58: 4.24 | OA58: 4.3 | OB58: 4.26 | OC58: 4.26 | OD58: 4.24 | OG58: 4.22 | OH58: 4.24 | OI58: 4.26 | OJ58: 4.24 | OK58: 4.26 | ON58: 4.29 | OO58: 4.28 | OP58: 4.29 | OQ58: 4.21 | OR58: 4.22 | OU58: 4.22 | OV58: 4.16 | OW58: 4.18 | OX58: 4.09 | OY58: 4.04 | PC58: 4.05 | PD58: 4.09 | PE58: 4.08 | PF58: 4.08 | PI58: 4.03 | PJ58: 4.04 | PK58: 4.05 | PL58: 4.02 | PM58: 3.97 | PP58: 4.05 | PQ58: 4.06 | PR58: 4.09 | PS58: 4.13 | PT58: 4.15 | PW58: 4.12 | PX58: 4.15 | PY58: 4.21 | PZ58: 4.27 | QA58: 4.28 | QD58: 4.23 | QE58: 4.2 | QF58: 4.26 | QG58: 4.25 | QH58: 4.39 | QK58: 4.34 | QL58: 4.39 | QM58: 4.33 | QN58: 4.42 | QO58: 4.44 | QR58: 4.35 | QS58: 4.3 | QT58: 4.33 | QU58: 4.31 | QV58: 4.35 | QY58: 4.34 | QZ58: 4.33 | RA58: 4.29 | RB58: 4.29 | RC58: 4.31 | RF58: 4.3 | RG58: 4.26 | RH58: 4.29 | RI58: 4.32 | RJ58: 4.26 | RM58: 4.26 | RN58: 4.3 | RO58: 4.3 | RP58: 4.34 | RQ58: 4.31 | RT58: 4.35 | RU58: 4.36 | RV58: 4.42 | RW58: 4.4 | RX58: 4.39 | SA58: 4.45 | SB58: 4.43 | SC58: 4.36 | SD58: 4.41 | SE58: 4.38 | SH58: 4.42 | SI58: 4.46 | SJ58: 4.46 | SK58: 4.47 | SL58: 4.59 | SO58: 4.61 | SP58: 4.67 | SQ58: 4.57 | SR58: 4.57 | SS58: 4.56 | SW58: 4.5 | SX58: 4.48 | SY58: 4.45 | SZ58: 4.45 | TC58: 4.47 | TD58: 4.46 | TE58: 4.49 | TF58: 4.47 | TG58: 4.55 | TJ58: 4.56 | TK58: 4.53 | TL58: 4.55 | TM58: 4.45 | TN58: 4.48 | TQ58: 4.47 | TR58: 4.43 | TS58: 4.49 | TT58: 4.46 | TX58: 4.51 | TY58: 4.5 | TZ58: 4.41 | UA58: 4.4 | UB58: 4.38 | UE58: 4.38 | UF58: 4.44 | UG58: 4.48 | UH58: 4.49
